Workbook
Name Amount: #REF!
Name Amount: #REF!
Name Amount: #REF!
Name Amount: #REF!
Name Amount: #REF!
Name Amount: #REF!
Name Amount: #REF!
Name Date: #REF!
Name Date: #REF!
Name Date: #REF!
Name Date: #REF!
Name Date: #REF!
Name Date: #REF!
Name Date: #REF!
Name Description: #REF!
Name Description: #REF!
Name Description: #REF!
Name Description: #REF!
Name Description: #REF!
Name Description: #REF!
Name Description: #REF!
Name From: #REF!
Name From: #REF!
Name From: #REF!
Name From: #REF!
Name From: #REF!
Name From: #REF!
Name From: #REF!
Name To: #REF!
Name To: #REF!
Name To: #REF!
Name To: #REF!
Name To: #REF!
Name To: #REF!
Name To: #REF!

Sheet Report
F3: Sukuk Portfolio
C4: Platform | D4: Cost | E4: Total Suk. | F4: Completed | G4: Delayed | H4: Released Profit | I4: Expected Profit | J4: Cost+R Profit | K4: -1% Risk Factor | L4: Evaluated | M4: Return
C5: Sukuk Capital | D5: =Sukuk!A19 -> 0.7 | E5: =Sukuk!C23 -> 67 | F5: 1 | G5: 0 | H5: =Sukuk!B31 -> 29150.26 | I5: =Sukuk!B23-Sukuk!B31 -> 54992.42 | J5: =D5+H5 -> 29150.96 | K5: =J5/100 -> 291.5096 | L5: =J5-K5 -> 28859.45 | M5: =(L5-D5)/D5 -> 41226.786
C6: Dinar | D6: =#REF! -> #REF! | E6: =#REF! -> #REF! | F6: 0 | G6: 0 | H6: =#REF! -> #REF! | I6: =#REF!-#REF! -> #REF! | J6: =D6+H6 -> #REF! | K6: =J6/100 -> #REF! | L6: =J6-K6 -> #REF! | M6: =(L6-D6)/D6 -> #REF!
D7: =SUM(D5:D6) -> #REF! | E7: =SUM(E5:E6) -> #REF! | F7: =SUM(F5:F6) -> 1 | G7: =SUM(G5:G6) -> 0 | H7: =SUM(H5:H6) -> #REF! | I7: =SUM(I5:I6) -> #REF! | J7: =SUM(J5:J6) -> #REF! | K7: =SUM(K5:K6) -> #REF! | L7: =SUM(L5:L6) -> #REF! | M7: =(L7-D7)/D7 -> #REF!
F8: * | G8: *
B12: *Manwal

Sheet ALL
A1: أجمالي الأصول | B1: قيمة المحفظة | C1: الكاش | E1: المدة | F1: تاريخ الأستحقاق | G1: تاريخ السداد | H1: القيمة الأسمية | I1: صافي الربح | J1: الدفعة | K1: الحالة | L1: C | M1: A | N1: الشهر | O1: التدفقات | P1: رقم
A2: =SUM(B78:C78)+B2 -> 844787.09 | B2: =SUMIFS(J2:J326,F2:F326,"<>")+C2 -> 672337.44 | C2: =SUM(Sukuk!C1+Sukuk!C2+MANAFA!C2+LENDO!C2+TAMEED!C2+DINAR!C2+SAFQA!C2+TARMEEZ!C2) -> 34443.08 | E2: 16 | G2: 45484 | H2: 5000 | I2: 976.19 | J2: =SUM(H2:I2) -> 5976.19 | K2: PAID | N2: 45901 | O2: =SUMIFS(J$2:J$1009, F$2:F$1009, ">=" & DATE(YEAR(N2), MONTH(N2), 1), F$2:F$1009, "<=" & EOMONTH(N2, 0)) -> 0 | P2: 0
E3: 18 | G3: 45551 | H3: 5000 | I3: 1122.66 | J3: =SUM(H3:I3) -> 6122.66 | K3: PAID | N3: 45931 | O3: =SUMIFS(J$2:J$1009, F$2:F$1009, ">=" & DATE(YEAR(N3), MONTH(N3), 1), F$2:F$1009, "<=" & EOMONTH(N3, 0)) -> 5843.34 | P3: 0
E4: 20 | G4: 45575 | H4: 10000 | I4: 2378.56 | J4: =SUM(H4:I4) -> 12378.56 | K4: PAID | N4: 45962 | O4: =SUMIFS(J$2:J$1009, F$2:F$1009, ">=" & DATE(YEAR(N4), MONTH(N4), 1), F$2:F$1009, "<=" & EOMONTH(N4, 0)) -> 10280.28 | P4: 0
E5: 9 | G5: 45286 | H5: 5000 | I5: 459 | J5: =SUM(H5:I5) -> 5459 | K5: PAID | N5: 45992 | O5: =SUMIFS(J$2:J$1009, F$2:F$1009, ">=" & DATE(YEAR(N5), MONTH(N5), 1), F$2:F$1009, "<=" & EOMONTH(N5, 0)) -> 10729.61 | P5: 1
E6: 12 | G6: 45286 | H6: 5000 | I6: 607.05 | J6: =SUM(H6:I6) -> 5607.05 | K6: PAID | N6: 46023 | O6: =SUMIFS(J$2:J$1009, F$2:F$1009, ">=" & DATE(YEAR(N6), MONTH(N6), 1), F$2:F$1009, "<=" & EOMONTH(N6, 0)) -> 10463.54 | P6: 2
E7: 9 | G7: 45413 | H7: 20000 | I7: 1963.57 | J7: =SUM(H7:I7) -> 21963.57 | K7: PAID | L7: LATE | N7: 46054 | O7: =SUMIFS(J$2:J$1009, F$2:F$1009, ">=" & DATE(YEAR(N7), MONTH(N7), 1), F$2:F$1009, "<=" & EOMONTH(N7, 0)) -> 31643.95 | P7: 3
E8: 4 | G8: 45351 | H8: 20000 | I8: 826.52 | J8: =SUM(H8:I8) -> 20826.52 | K8: PAID | N8: 46082 | O8: =SUMIFS(J$2:J$1009, F$2:F$1009, ">=" & DATE(YEAR(N8), MONTH(N8), 1), F$2:F$1009, "<=" & EOMONTH(N8, 0)) -> 23128.39 | P8: 4
E9: 9 | G9: 45519 | H9: 10000 | I9: 953.2 | J9: =SUM(H9:I9) -> 10953.2 | K9: PAID | L9: LATE | N9: 46113 | O9: =SUMIFS(J$2:J$1009, F$2:F$1009, ">=" & DATE(YEAR(N9), MONTH(N9), 1), F$2:F$1009, "<=" & EOMONTH(N9, 0)) -> 29364.49 | P9: 5
E10: 17 | G10: 45742 | H10: 20000 | I10: 3744.86 | J10: =SUM(H10:I10) -> 23744.86 | K10: PAID | N10: 46143 | O10: =SUMIFS(J$2:J$1009, F$2:F$1009, ">=" & DATE(YEAR(N10), MONTH(N10), 1), F$2:F$1009, "<=" & EOMONTH(N10, 0)) -> 18578.03 | P10: 6
E11: 28 | F11: 46147 | H11: 5000 | I11: 1652.77 | J11: =SUM(H11:I11) -> 6652.77 | K11: =IF(F11<=TODAY(),"Check!","Waiting") -> Waiting | N11: 46174 | O11: =SUMIFS(J$2:J$1009, F$2:F$1009, ">=" & DATE(YEAR(N11), MONTH(N11), 1), F$2:F$1009, "<=" & EOMONTH(N11, 0)) -> 28338.37 | P11: 7
E12: 9 | G12: 45592 | H12: 5000 | I12: 463.86 | J12: =SUM(H12:I12) -> 5463.86 | K12: PAID | N12: 46204 | O12: =SUMIFS(J$2:J$1009, F$2:F$1009, ">=" & DATE(YEAR(N12), MONTH(N12), 1), F$2:F$1009, "<=" & EOMONTH(N12, 0)) -> 6485.95 | P12: 8
E13: 14 | G13: 45683 | H13: 5000 | I13: 631.95 | J13: =SUM(H13:I13) -> 5631.95 | K13: PAID | N13: 46235 | O13: =SUMIFS(J$2:J$1009, F$2:F$1009, ">=" & DATE(YEAR(N13), MONTH(N13), 1), F$2:F$1009, "<=" & EOMONTH(N13, 0)) -> 19687.91 | P13: 9
E14: 38 | F14: 46481 | H14: 5000 | I14: 2055.02 | J14: =SUM(H14:I14) -> 7055.02 | K14: =IF(F14<=TODAY(),"Check!","Waiting") -> Waiting | N14: 46266 | O14: =SUMIFS(J$2:J$1009, F$2:F$1009, ">=" & DATE(YEAR(N14), MONTH(N14), 1), F$2:F$1009, "<=" & EOMONTH(N14, 0)) -> 0 | P14: 10
E15: 24 | G15: 45452 | H15: 5000 | I15: 205.51 | J15: =SUM(H15:I15) -> 5205.51 | K15: PAID | N15: 46296 | O15: =SUMIFS(J$2:J$1009, F$2:F$1009, ">=" & DATE(YEAR(N15), MONTH(N15), 1), F$2:F$1009, "<=" & EOMONTH(N15, 0)) -> 24086 | P15: 11
E16: 16 | G16: 45812 | H16: 5000 | I16: 713.33 | J16: =SUM(H16:I16) -> 5713.33 | K16: PAID | L16: EARLY 7 | N16: 46327 | O16: =SUMIFS(J$2:J$1009, F$2:F$1009, ">=" & DATE(YEAR(N16), MONTH(N16), 1), F$2:F$1009, "<=" & EOMONTH(N16, 0)) -> 12083.62 | P16: 12
E17: 6 | G17: 45512 | H17: 10000 | I17: 569.01 | J17: =SUM(H17:I17) -> 10569.01 | K17: PAID | N17: 46357 | O17: =SUMIFS(J$2:J$1009, F$2:F$1009, ">=" & DATE(YEAR(N17), MONTH(N17), 1), F$2:F$1009, "<=" & EOMONTH(N17, 0)) -> 7297.5 | P17: 13
E18: 9 | G18: 45600 | H18: 5000 | I18: 390.38 | J18: =SUM(H18:I18) -> 5390.38 | K18: PAID | N18: 46388 | O18: =SUMIFS(J$2:J$1009, F$2:F$1009, ">=" & DATE(YEAR(N18), MONTH(N18), 1), F$2:F$1009, "<=" & EOMONTH(N18, 0)) -> 6547.1 | P18: 14
E19: 10 | G19: 45669 | H19: 5000 | I19: 428.76 | J19: =SUM(H19:I19) -> 5428.76 | K19: PAID | N19: 46419 | O19: =SUMIFS(J$2:J$1009, F$2:F$1009, ">=" & DATE(YEAR(N19), MONTH(N19), 1), F$2:F$1009, "<=" & EOMONTH(N19, 0)) -> 24220 | P19: 15
E20: 6 | G20: 45561 | H20: 5000 | I20: 300.25 | J20: =SUM(H20:I20) -> 5300.25 | K20: PAID | N20: 46447 | O20: =SUMIFS(J$2:J$1009, F$2:F$1009, ">=" & DATE(YEAR(N20), MONTH(N20), 1), F$2:F$1009, "<=" & EOMONTH(N20, 0)) -> 37672.51 | P20: 16
E21: 9 | G21: 45655 | H21: 5000 | I21: 458.24 | J21: =SUM(H21:I21) -> 5458.24 | K21: PAID | N21: 46478 | O21: =SUMIFS(J$2:J$1009, F$2:F$1009, ">=" & DATE(YEAR(N21), MONTH(N21), 1), F$2:F$1009, "<=" & EOMONTH(N21, 0)) -> 7055.02 | P21: 17
E22: 6 | G22: 45565 | H22: 5000 | I22: 280 | J22: =SUM(H22:I22) -> 5280 | K22: PAID | N22: 46508 | O22: =SUMIFS(J$2:J$1009, F$2:F$1009, ">=" & DATE(YEAR(N22), MONTH(N22), 1), F$2:F$1009, "<=" & EOMONTH(N22, 0)) -> 18844.23 | P22: 18
E23: 9 | G23: 45649 | H23: 5000 | I23: 431.37 | J23: =SUM(H23:I23) -> 5431.37 | K23: PAID | N23: 46539 | O23: =SUMIFS(J$2:J$1009, F$2:F$1009, ">=" & DATE(YEAR(N23), MONTH(N23), 1), F$2:F$1009, "<=" & EOMONTH(N23, 0)) -> 10287 | P23: 19
E24: 13 | F24: 45792 | H24: 5000 | I24: 610.29 | J24: =SUM(H24:I24) -> 5610.29 | K24: =IF(F24<=TODAY(),"Check!","Waiting") -> Check! | L24: DEF | N24: 46569 | O24: =SUMIFS(J$2:J$1009, F$2:F$1009, ">=" & DATE(YEAR(N24), MONTH(N24), 1), F$2:F$1009, "<=" & EOMONTH(N24, 0)) -> 42606.08 | P24: 20
E25: 24 | G25: 45705 | H25: 5000 | I25: 481.39 | J25: =SUM(H25:I25) -> 5481.39 | K25: PAID | N25: 46600 | O25: =SUMIFS(J$2:J$1009, F$2:F$1009, ">=" & DATE(YEAR(N25), MONTH(N25), 1), F$2:F$1009, "<=" & EOMONTH(N25, 0)) -> 36468 | P25: 21
E26: 24 | F26: 46140 | H26: 5000 | I26: 1151.34 | J26: =SUM(H26:I26) -> 6151.34 | K26: =IF(F26<=TODAY(),"Check!","Waiting") -> Waiting | N26: 46631 | O26: =SUMIFS(J$2:J$1009, F$2:F$1009, ">=" & DATE(YEAR(N26), MONTH(N26), 1), F$2:F$1009, "<=" & EOMONTH(N26, 0)) -> 13216.12 | P26: 22
E27: 17 | G27: 45922 | H27: 5000 | I27: 936.94 | J27: =SUM(H27:I27) -> 5936.94 | K27: PAID | M27: SU1 | N27: 46661 | O27: =SUMIFS(J$2:J$1009, F$2:F$1009, ">=" & DATE(YEAR(N27), MONTH(N27), 1), F$2:F$1009, "<=" & EOMONTH(N27, 0)) -> 0 | P27: 23
E28: 17 | F28: 45931 | H28: 5000 | I28: 843.34 | J28: =SUM(H28:I28) -> 5843.34 | K28: PAID | M28: SU1 | N28: 46692 | O28: =SUMIFS(J$2:J$1009, F$2:F$1009, ">=" & DATE(YEAR(N28), MONTH(N28), 1), F$2:F$1009, "<=" & EOMONTH(N28, 0)) -> 39303.83 | P28: 24
E29: 13 | G29: 45811 | H29: 5000 | I29: 622.41 | J29: =SUM(H29:I29) -> 5622.41 | K29: PAID | L29: EARLY 12 | N29: 46722 | O29: =SUMIFS(J$2:J$1009, F$2:F$1009, ">=" & DATE(YEAR(N29), MONTH(N29), 1), F$2:F$1009, "<=" & EOMONTH(N29, 0)) -> 39263.23 | P29: 25
A30: Note | E30: 24 | F30: 46145 | H30: 5000 | I30: 1251.93 | J30: =SUM(H30:I30) -> 6251.93 | K30: =IF(F30<=TODAY(),"Check!","Waiting") -> Waiting | N30: 46753 | O30: =SUMIFS(J$2:J$1009, F$2:F$1009, ">=" & DATE(YEAR(N30), MONTH(N30), 1), F$2:F$1009, "<=" & EOMONTH(N30, 0)) -> 0 | P30: 26
A31: Cash sum and subtract until cell 300. update if needed | E31: 9 | G31: 45753 | H31: 5000 | I31: 341.49 | J31: =SUM(H31:I31) -> 5341.49 | K31: PAID | N31: 46784 | O31: =SUMIFS(J$2:J$1009, F$2:F$1009, ">=" & DATE(YEAR(N31), MONTH(N31), 1), F$2:F$1009, "<=" & EOMONTH(N31, 0)) -> 13760.06 | P31: 27
E32: 18 | F32: 46196 | H32: 20000 | I32: 2154.87 | J32: =SUM(H32:I32) -> 22154.87 | K32: =IF(F32<=TODAY(),"Check!","Waiting") -> Waiting | N32: 46813 | O32: =SUMIFS(J$2:J$1009, F$2:F$1009, ">=" & DATE(YEAR(N32), MONTH(N32), 1), F$2:F$1009, "<=" & EOMONTH(N32, 0)) -> 34726.23 | P32: 28
E33: 30 | F33: 46110 | H33: 8000 | I33: 2571.94 | J33: =SUM(H33:I33) -> 10571.94 | K33: =IF(F33<=TODAY(),"Check!","Waiting") -> Waiting | N33: 46844 | O33: =SUMIFS(J$2:J$1009, F$2:F$1009, ">=" & DATE(YEAR(N33), MONTH(N33), 1), F$2:F$1009, "<=" & EOMONTH(N33, 0)) -> 0 | P33: 29
E34: 12 | F34: 46021 | H34: 4000 | I34: 396.34 | J34: =SUM(H34:I34) -> 4396.34 | K34: =IF(F34<=TODAY(),"Check!","Waiting") -> Waiting | N34: 46874 | O34: =SUMIFS(J$2:J$1009, F$2:F$1009, ">=" & DATE(YEAR(N34), MONTH(N34), 1), F$2:F$1009, "<=" & EOMONTH(N34, 0)) -> 7441.19 | P34: 30
E35: 9 | G35: 45901 | H35: 5000 | I35: 532.94 | J35: =SUM(H35:I35) -> 5532.94 | K35: PAID | L35: EARLY 30 | M35: SA | N35: 46905 | O35: =SUMIFS(J$2:J$1009, F$2:F$1009, ">=" & DATE(YEAR(N35), MONTH(N35), 1), F$2:F$1009, "<=" & EOMONTH(N35, 0)) -> 0 | P35: 31
E36: 26 | F36: 46453 | H36: 5000 | I36: 1518.87 | J36: =SUM(H36:I36) -> 6518.87 | K36: =IF(F36<=TODAY(),"Check!","Waiting") -> Waiting | N36: 46935 | O36: =SUMIFS(J$2:J$1009, F$2:F$1009, ">=" & DATE(YEAR(N36), MONTH(N36), 1), F$2:F$1009, "<=" & EOMONTH(N36, 0)) -> 0 | P36: 32
E37: 23 | F37: 46448 | H37: 10000 | I37: 2583.52 | J37: =SUM(H37:I37) -> 12583.52 | K37: =IF(F37<=TODAY(),"Check!","Waiting") -> Waiting | N37: 46966 | O37: =SUMIFS(J$2:J$1009, F$2:F$1009, ">=" & DATE(YEAR(N37), MONTH(N37), 1), F$2:F$1009, "<=" & EOMONTH(N37, 0)) -> 0 | P37: 33
E38: 13 | F38: 46145 | H38: 5000 | I38: 673.33 | J38: =SUM(H38:I38) -> 5673.33 | K38: =IF(F38<=TODAY(),"Check!","Waiting") -> Waiting | N38: 46997 | O38: =SUMIFS(J$2:J$1009, F$2:F$1009, ">=" & DATE(YEAR(N38), MONTH(N38), 1), F$2:F$1009, "<=" & EOMONTH(N38, 0)) -> 27780 | P38: 34
E39: 27 | F39: 46575 | H39: 10000 | I39: 2885.89 | J39: =SUM(H39:I39) -> 12885.89 | K39: =IF(F39<=TODAY(),"Check!","Waiting") -> Waiting | N39: 47027 | O39: =SUMIFS(J$2:J$1009, F$2:F$1009, ">=" & DATE(YEAR(N39), MONTH(N39), 1), F$2:F$1009, "<=" & EOMONTH(N39, 0)) -> 0 | P39: 35
E40: 19 | F40: 46348 | H40: 10000 | I40: 2083.62 | J40: =SUM(H40:I40) -> 12083.62 | K40: =IF(F40<=TODAY(),"Check!","Waiting") -> Waiting | N40: 47058 | O40: =SUMIFS(J$2:J$1009, F$2:F$1009, ">=" & DATE(YEAR(N40), MONTH(N40), 1), F$2:F$1009, "<=" & EOMONTH(N40, 0)) -> 0
E41: 31 | F41: 46729 | H41: 10000 | I41: 3045.67 | J41: =SUM(H41:I41) -> 13045.67 | K41: =IF(F41<=TODAY(),"Check!","Waiting") -> Waiting | N41: 47088 | O41: =SUMIFS(J$2:J$1009, F$2:F$1009, ">=" & DATE(YEAR(N41), MONTH(N41), 1), F$2:F$1009, "<=" & EOMONTH(N41, 0)) -> 0
E42: 43 | F42: 46573 | H42: 20000 | I42: 9720.19 | J42: =SUM(H42:I42) -> 29720.19 | K42: =IF(F42<=TODAY(),"Check!","Waiting") -> Waiting | N42: 47119 | O42: =SUMIFS(J$2:J$1009, F$2:F$1009, ">=" & DATE(YEAR(N42), MONTH(N42), 1), F$2:F$1009, "<=" & EOMONTH(N42, 0)) -> 0
E43: 21 | G43: 45900 | H43: 5000 | I43: 1153.08 | J43: =SUM(H43:I43) -> 6153.08 | K43: PAID | L43: EARLY 4 | M43: SU2 | N43: 47150 | O43: =SUMIFS(J$2:J$1009, F$2:F$1009, ">=" & DATE(YEAR(N43), MONTH(N43), 1), F$2:F$1009, "<=" & EOMONTH(N43, 0)) -> 0
E44: 24 | F44: 45998 | H44: 5000 | I44: 1333.27 | J44: =SUM(H44:I44) -> 6333.27 | K44: =IF(F44<=TODAY(),"Check!","Waiting") -> Waiting | N44: 47178 | O44: =SUMIFS(J$2:J$1009, F$2:F$1009, ">=" & DATE(YEAR(N44), MONTH(N44), 1), F$2:F$1009, "<=" & EOMONTH(N44, 0)) -> 0
E45: 27 | F45: 46089 | H45: 5000 | I45: 1618.95 | J45: =SUM(H45:I45) -> 6618.95 | K45: =IF(F45<=TODAY(),"Check!","Waiting") -> Waiting | N45: 47209 | O45: =SUMIFS(J$2:J$1009, F$2:F$1009, ">=" & DATE(YEAR(N45), MONTH(N45), 1), F$2:F$1009, "<=" & EOMONTH(N45, 0)) -> 0
E46: 18 | G46: 45796 | H46: 5000 | I46: 1007.84 | J46: =SUM(H46:I46) -> 6007.84 | K46: PAID | L46: EARLY 17 | N46: 47239 | O46: =SUMIFS(J$2:J$1009, F$2:F$1009, ">=" & DATE(YEAR(N46), MONTH(N46), 1), F$2:F$1009, "<=" & EOMONTH(N46, 0)) -> 0
E47: 24 | G47: 45916 | H47: 5000 | I47: 915.69 | J47: =SUM(H47:I47) -> 5915.69 | K47: PAID | L47: EARLY 4m | M47: SA2 | N47: 47270 | O47: =SUMIFS(J$2:J$1009, F$2:F$1009, ">=" & DATE(YEAR(N47), MONTH(N47), 1), F$2:F$1009, "<=" & EOMONTH(N47, 0)) -> 0
E48: 15 | G48: 45761 | H48: 10000 | I48: 1624.85 | J48: =SUM(H48:I48) -> 11624.85 | K48: PAID | N48: 47300 | O48: =SUMIFS(J$2:J$1009, F$2:F$1009, ">=" & DATE(YEAR(N48), MONTH(N48), 1), F$2:F$1009, "<=" & EOMONTH(N48, 0)) -> 0
E49: 27 | G49: 45911 | H49: 5000 | I49: 929.21 | J49: =SUM(H49:I49) -> 5929.21 | K49: PAID | L49: EARLY 1Y | M49: SA | N49: 47331 | O49: =SUMIFS(J$2:J$1009, F$2:F$1009, ">=" & DATE(YEAR(N49), MONTH(N49), 1), F$2:F$1009, "<=" & EOMONTH(N49, 0)) -> 0
E50: 27 | F50: 46238 | H50: 5000 | I50: 1526.69 | J50: =SUM(H50:I50) -> 6526.69 | K50: =IF(F50<=TODAY(),"Check!","Waiting") -> Waiting | N50: 47362 | O50: =SUMIFS(J$2:J$1009, F$2:F$1009, ">=" & DATE(YEAR(N50), MONTH(N50), 1), F$2:F$1009, "<=" & EOMONTH(N50, 0)) -> 0
E51: 12 | G51: 45774 | H51: 5000 | I51: 554.86 | J51: =SUM(H51:I51) -> 5554.86 | K51: PAID | N51: 47392 | O51: =SUMIFS(J$2:J$1009, F$2:F$1009, ">=" & DATE(YEAR(N51), MONTH(N51), 1), F$2:F$1009, "<=" & EOMONTH(N51, 0)) -> 0
E52: 27 | F52: 46243 | H52: 10000 | I52: 3161.22 | J52: =SUM(H52:I52) -> 13161.22 | K52: =IF(F52<=TODAY(),"Check!","Waiting") -> Waiting | N52: 47423 | O52: =SUMIFS(J$2:J$1009, F$2:F$1009, ">=" & DATE(YEAR(N52), MONTH(N52), 1), F$2:F$1009, "<=" & EOMONTH(N52, 0)) -> 0
E53: 48 | F53: 46880 | H53: 5000 | I53: 2441.19 | J53: =SUM(H53:I53) -> 7441.19 | K53: =IF(F53<=TODAY(),"Check!","Waiting") -> Waiting | N53: 47453 | O53: =SUMIFS(J$2:J$1009, F$2:F$1009, ">=" & DATE(YEAR(N53), MONTH(N53), 1), F$2:F$1009, "<=" & EOMONTH(N53, 0)) -> 0
E54: 40 | F54: 46642 | H54: 10000 | I54: 3216.12 | J54: =SUM(H54:I54) -> 13216.12 | K54: =IF(F54<=TODAY(),"Check!","Waiting") -> Waiting | N54: 47484 | O54: =SUMIFS(J$2:J$1009, F$2:F$1009, ">=" & DATE(YEAR(N54), MONTH(N54), 1), F$2:F$1009, "<=" & EOMONTH(N54, 0)) -> 0
E55: 26 | F55: 46216 | H55: 5000 | I55: 1485.95 | J55: =SUM(H55:I55) -> 6485.95 | K55: =IF(F55<=TODAY(),"Check!","Waiting") -> Waiting | N55: 47515 | O55: =SUMIFS(J$2:J$1009, F$2:F$1009, ">=" & DATE(YEAR(N55), MONTH(N55), 1), F$2:F$1009, "<=" & EOMONTH(N55, 0)) -> 0
A56: المأشرات | E56: 23 | F56: 46125 | H56: 20000 | I56: 3213.15 | J56: =SUM(H56:I56) -> 23213.15 | K56: =IF(F56<=TODAY(),"Check!","Waiting") -> Waiting | N56: 47543 | O56: =SUMIFS(J$2:J$1009, F$2:F$1009, ">=" & DATE(YEAR(N56), MONTH(N56), 1), F$2:F$1009, "<=" & EOMONTH(N56, 0)) -> 0
A57: القيمة الأسمية | B57: صافي الأرباح | C57: عدد الأستثمارات | E57: 8 | G57: 45648 | H57: 5000 | I57: 402.57 | J57: =SUM(H57:I57) -> 5402.57 | K57: PAID | N57: 47574 | O57: =SUMIFS(J$2:J$1009, F$2:F$1009, ">=" & DATE(YEAR(N57), MONTH(N57), 1), F$2:F$1009, "<=" & EOMONTH(N57, 0)) -> 0
A58: =SUMIFS(H2:H509,F2:F509,"<>") -> 515000 | B58: =SUMIFS(I2:I509,F2:F509,"<>") -> 122894.36 | C58: =COUNT(J2:J509, "?*") -> 325 | E58: 32 | F58: 46404 | H58: 5000 | I58: 1547.1 | J58: =SUM(H58:I58) -> 6547.1 | K58: =IF(F58<=TODAY(),"Check!","Waiting") -> Waiting | N58: 47604 | O58: =SUMIFS(J$2:J$1009, F$2:F$1009, ">=" & DATE(YEAR(N58), MONTH(N58), 1), F$2:F$1009, "<=" & EOMONTH(N58, 0)) -> 0
A59: العائد السنوي ( APR ) الدقيق | B59: العائد على الاستثمار ( ROI ) | C59: متوسط المدة ( بالشهر ) | E59: 10 | G59: 45725 | H59: 5000 | I59: 569.17 | J59: =SUM(H59:I59) -> 5569.17 | K59: PAID | N59: 47635 | O59: =SUMIFS(J$2:J$1009, F$2:F$1009, ">=" & DATE(YEAR(N59), MONTH(N59), 1), F$2:F$1009, "<=" & EOMONTH(N59, 0)) -> 0
A60: =(B60*100/C60)*12 -> 23.284429 | B60: =TEXT(B58/A58, "0.00%") -> 23.86% | C60: =SUMPRODUCT(H2:H509, E2:E509) / SUM(H2:H509) -> 12.29663 | E60: 12 | G60: 45652 | H60: 5000 | I60: 330.21 | J60: =SUM(H60:I60) -> 5330.21 | K60: PAID | N60: 47665 | O60: =SUMIFS(J$2:J$1009, F$2:F$1009, ">=" & DATE(YEAR(N60), MONTH(N60), 1), F$2:F$1009, "<=" & EOMONTH(N60, 0)) -> 0
A61: الفرص المتأخرة | B61: الفرص النشطة | C61: الفرص المكتملة | E61: 26 | F61: 46453 | H61: 5000 | I61: 1493.99 | J61: =SUM(H61:I61) -> 6493.99 | K61: =IF(F61<=TODAY(),"Check!","Waiting") -> Waiting | N61: 47696 | O61: =SUMIFS(J$2:J$1009, F$2:F$1009, ">=" & DATE(YEAR(N61), MONTH(N61), 1), F$2:F$1009, "<=" & EOMONTH(N61, 0)) -> 0
A62: =COUNTIF(K2:K509, "CHECK!") -> 14 | B62: =COUNTIF(K2:K509, "WAITING") -> 48 | C62: =COUNTIF(K2:K509, "PAID") -> 263 | E62: 28 | F62: 46519 | H62: 5000 | I62: 1429.23 | J62: =SUM(H62:I62) -> 6429.23 | K62: =IF(F62<=TODAY(),"Check!","Waiting") -> Waiting | N62: 47727 | O62: =SUMIFS(J$2:J$1009, F$2:F$1009, ">=" & DATE(YEAR(N62), MONTH(N62), 1), F$2:F$1009, "<=" & EOMONTH(N62, 0)) -> 0
E63: 34 | F63: 46803 | H63: 10000 | I63: 3760.06 | J63: =SUM(H63:I63) -> 13760.06 | K63: =IF(F63<=TODAY(),"Check!","Waiting") -> Waiting | N63: 47757 | O63: =SUMIFS(J$2:J$1009, F$2:F$1009, ">=" & DATE(YEAR(N63), MONTH(N63), 1), F$2:F$1009, "<=" & EOMONTH(N63, 0)) -> 0
A64: الحالة | B64: العدد | C64: النسبة | E64: 34 | F64: 46824 | H64: 20000 | I64: 8035.65 | J64: =SUM(H64:I64) -> 28035.65 | K64: =IF(F64<=TODAY(),"Check!","Waiting") -> Waiting | N64: 47788 | O64: =SUMIFS(J$2:J$1009, F$2:F$1009, ">=" & DATE(YEAR(N64), MONTH(N64), 1), F$2:F$1009, "<=" & EOMONTH(N64, 0)) -> 0
A65: مكتملة | B65: =COUNTIF(K2:K509, "PAID") -> 263 | C65: =B65/SUM($B$65:$B$67)*100 -> 80.923077 | E65: 4 | G65: 45456 | H65: 1000 | I65: 12.56 | J65: =SUM(H65:I65) -> 1012.56 | K65: PAID | L65: EARLY | M65: M | N65: 47818 | O65: =SUMIFS(J$2:J$1009, F$2:F$1009, ">=" & DATE(YEAR(N65), MONTH(N65), 1), F$2:F$1009, "<=" & EOMONTH(N65, 0)) -> 0
A66: نشطة | B66: =COUNTIF(K2:K509, "WAITING") -> 48 | C66: =B66/SUM($B$65:$B$67)*100 -> 14.769231 | E66: 5 | G66: 45484 | H66: 1000 | I66: 21.91 | J66: =SUM(H66:I66) -> 1021.91 | K66: PAID | L66: EARLY | M66: M | N66: 47757 | O66: =SUMIFS(J$2:J$1009, F$2:F$1009, ">=" & DATE(YEAR(N66), MONTH(N66), 1), F$2:F$1009, "<=" & EOMONTH(N66, 0)) -> 0
A67: متأخرة | B67: =COUNTIF(K2:K509, "CHECK!") -> 14 | C67: =B67/SUM($B$65:$B$67)*100 -> 4.3076923 | E67: 4 | G67: 45489 | H67: 1000 | I67: 10.35 | J67: =SUM(H67:I67) -> 1010.35 | K67: PAID | L67: EARLY | M67: M | N67: 47788 | O67: =SUMIFS(J$2:J$1009, F$2:F$1009, ">=" & DATE(YEAR(N67), MONTH(N67), 1), F$2:F$1009, "<=" & EOMONTH(N67, 0)) -> 0
E68: 4 | G68: 45495 | H68: 1000 | I68: 23.74 | J68: =SUM(H68:I68) -> 1023.74 | K68: PAID | L68: EARLY | M68: M | N68: 47818 | O68: =SUMIFS(J$2:J$1009, F$2:F$1009, ">=" & DATE(YEAR(N68), MONTH(N68), 1), F$2:F$1009, "<=" & EOMONTH(N68, 0)) -> 0
A69: المنصة | B69: القيمة | C69: النسبة من المحفظة | E69: 4 | G69: 45522 | H69: 1000 | I69: 35.5 | J69: =SUM(H69:I69) -> 1035.5 | K69: PAID | L69: EARLY | M69: M
A70: صكوك | B70: =Sukuk!A2 -> 400586.87 | C70: =B70/SUM($B$70:$B$75)*100 -> 60.447057 | E70: 4 | G70: 45532 | H70: 1000 | I70: 35.89 | J70: =SUM(H70:I70) -> 1035.89 | K70: PAID | L70: EARLY | M70: M
A71: منافع | B71: =MANAFA!A2 -> 99426.24 | C71: =B71/SUM($B$70:$B$75)*100 -> 15.003047 | E71: 3 | G71: 45536 | H71: 1000 | I71: 28.19 | J71: =SUM(H71:I71) -> 1028.19 | K71: PAID | M71: M
A72: ليندو | B72: =LENDO!A2 -> 27321.49 | C72: =B72/SUM($B$70:$B$75)*100 -> 4.1227104 | E72: 6 | G72: 45537 | H72: 1000 | I72: 37.4 | J72: =SUM(H72:I72) -> 1037.4 | K72: PAID | L72: EARLY | M72: M
A73: تعمييد | B73: =TAMEED!A2 -> 1067.2 | C73: =B73/SUM($B$70:$B$75)*100 -> 0.16103648 | E73: 4 | G73: 45537 | H73: 1000 | I73: 29.9 | J73: =SUM(H73:I73) -> 1029.9 | K73: PAID | L73: EARLY | M73: M
A74: دينار | B74: =DINAR!A2 -> 71925.5 | C74: =B74/SUM($B$70:$B$75)*100 -> 10.853288 | E74: 3 | G74: 45538 | H74: 1000 | I74: 27.42 | J74: =SUM(H74:I74) -> 1027.42 | K74: PAID | M74: M
A75: صفقة | B75: =SAFQA!A2 -> 62379.69 | C75: =B75/SUM($B$70:$B$75)*100 -> 9.4128613 | E75: 4 | G75: 45543 | H75: 1000 | I75: 37.52 | J75: =SUM(H75:I75) -> 1037.52 | K75: PAID | L75: EARLY | M75: M
A76: ترميز | B76: =TARMEEZ!A2 -> 0 | C76: =B76/SUM($B$70:$B$75)*100 -> 0 | E76: 4 | G76: 45552 | H76: 1000 | I76: 31.25 | J76: =SUM(H76:I76) -> 1031.25 | K76: PAID | L76: EARLY | M76: M
A77: أجمالي الأصول | B77: أسهم | C77: كاش الطوارئ | E77: 5 | G77: 45564 | H77: 1000 | I77: 43.7 | J77: =SUM(H77:I77) -> 1043.7 | K77: PAID | L77: EARLY | M77: M
A78: =SUM(B78:C78)+B2 -> 844787.09 | B78: 27449.65 | C78: 145000 | E78: 4 | G78: 45565 | H78: 1000 | I78: 75.16 | J78: =SUM(H78:I78) -> 1075.16 | K78: PAID | L78: EARLY | M78: M
E79: 5 | G79: 45565 | H79: 2000 | I79: 46.6 | J79: =SUM(H79:I79) -> 2046.6 | K79: PAID | M79: M
A80: الأهداف | E80: 5 | G80: 45566 | H80: 1000 | I80: 47.5 | J80: =SUM(H80:I80) -> 1047.5 | K80: PAID | M80: M
A81: رفع حصة : ( ترميز / صفقة / تعمييد ) | E81: 5 | G81: 45566 | H81: 1000 | I81: 37.1 | J81: =SUM(H81:I81) -> 1037.1 | K81: PAID | L81: EARLY | M81: M
E82: 6 | G82: 45578 | H82: 1000 | I82: 43.69 | J82: =SUM(H82:I82) -> 1043.69 | K82: PAID | L82: EARLY | M82: M
E83: 6 | G83: 45585 | H83: 1000 | I83: 55.98 | J83: =SUM(H83:I83) -> 1055.98 | K83: PAID | L83: EARLY | M83: M
A84: تدفقات نقدية 0 | E84: 4 | G84: 45586 | H84: 1000 | I84: 34.19 | J84: =SUM(H84:I84) -> 1034.19 | K84: PAID | M84: M
E85: 6 | G85: 45592 | H85: 1000 | I85: 52.56 | J85: =SUM(H85:I85) -> 1052.56 | K85: PAID | L85: EARLY | M85: M
A86: سبتمبر 26 ( 10 اشهر ) | E86: 5 | G86: 45593 | H86: 5000 | I86: 200.2 | J86: =SUM(H86:I86) -> 5200.2 | K86: PAID | M86: M
A87: فبراير 27 ( 15 شهر ) | E87: 5 | G87: 45593 | H87: 1000 | I87: 40.4 | J87: =SUM(H87:I87) -> 1040.4 | K87: PAID | M87: M
A88: أكتوبر 27 ( 23 شهر ) | E88: 5 | G88: 45595 | H88: 1000 | I88: 46.97 | J88: =SUM(H88:I88) -> 1046.97 | K88: PAID | M88: M
A89: يناير 28 ( 26 اشهر ) | E89: 3 | G89: 45596 | H89: 1000 | I89: 48.77 | J89: =SUM(H89:I89) -> 1048.77 | K89: PAID | L89: EARLY | M89: M
A90: ابريل 28 ( 29 شهر ) | E90: 7 | G90: 45596 | H90: 1000 | I90: 47.3 | J90: =SUM(H90:I90) -> 1047.3 | K90: PAID | L90: EARLY | M90: M
A91: يونيو 28 ( 31 شهر وما بعده ) > | E91: 6 | G91: 45596 | H91: 2000 | I91: 46.94 | J91: =SUM(H91:I91) -> 2046.94 | K91: PAID | L91: EARLY | M91: M
E92: 4 | G92: 45600 | H92: 5000 | I92: 151.96 | J92: =SUM(H92:I92) -> 5151.96 | K92: PAID | L92: EARLY | M92: M
A93: تدفقات نقدية قليلة / 13 , 14 , 17 , 19 , 30 | E93: 5 | G93: 45601 | H93: 1000 | I93: 45.75 | J93: =SUM(H93:I93) -> 1045.75 | K93: PAID | L93: EARLY | M93: M
E94: 6 | G94: 45602 | H94: 1000 | I94: 51.9 | J94: =SUM(H94:I94) -> 1051.9 | K94: PAID | M94: M
E95: 5 | G95: 45606 | H95: 1000 | I95: 82.56 | J95: =SUM(H95:I95) -> 1082.56 | K95: PAID | L95: EARLY | M95: M
E96: 7 | G96: 45627 | H96: 1000 | I96: 52.42 | J96: =SUM(H96:I96) -> 1052.42 | K96: PAID | L96: EARLY | M96: M
E97: 5 | G97: 45606 | H97: 2000 | I97: 82.56 | J97: =SUM(H97:I97) -> 2082.56 | K97: PAID | M97: M
E98: 4 | G98: 45606 | H98: 4000 | I98: 128.2 | J98: =SUM(H98:I98) -> 4128.2 | K98: PAID | M98: M
E99: 5 | G99: 45609 | H99: 1000 | I99: 46.13 | J99: =SUM(H99:I99) -> 1046.13 | K99: PAID | M99: M
E100: 4 | G100: 45615 | H100: 10000 | I100: 318.2 | J100: =SUM(H100:I100) -> 10318.2 | K100: PAID | M100: M
...

Sheet Sukuk
A1: قيمة المحفظة | C1: 31586.18 | E1: المدة | F1: تاريخ الأستحقاق | G1: تاريخ السداد | H1: القيمة الأسمية | I1: صافي الربح | J1: الدفعة | K1: الحالة | L1: C | M1: أسم الصك | N1: النسبة السنوية | P1: الشهر | Q1: التدفقات | R1: CHECKLIST
A2: =SUMIFS(J2:J300,F2:F300,"<>")+B19+A19+C1+C2 -> 400586.87 | C2: 2856.9 | E2: 16 | G2: 45484 | H2: 5000 | I2: 976.19 | J2: =SUM(H2:I2) -> 5976.19 | K2: PAID | M2: 001-02623 2# | N2: 16 | P2: 45778 | Q2: =SUMIFS(J$2:J$1000, F$2:F$1000, ">=" & DATE(YEAR(P2), MONTH(P2), 1), F$2:F$1000, "<=" & EOMONTH(P2, 0)) -> 5610.29
E3: 18 | G3: 45551 | H3: 5000 | I3: 1122.66 | J3: =SUM(H3:I3) -> 6122.66 | K3: PAID | M3: 001-02623 4# | N3: 16.2 | P3: 45809 | Q3: =SUMIFS(J$2:J$1000, F$2:F$1000, ">=" & DATE(YEAR(P3), MONTH(P3), 1), F$2:F$1000, "<=" & EOMONTH(P3, 0)) -> 0 | R3: بداية الأستثمار
A4: الملاحظات | E4: 20 | G4: 45575 | H4: 10000 | I4: 2378.56 | J4: =SUM(H4:I4) -> 12378.56 | K4: PAID | M4: 001-02623 5# | N4: 16.4 | P4: 45839 | Q4: =SUMIFS(J$2:J$1000, F$2:F$1000, ">=" & DATE(YEAR(P4), MONTH(P4), 1), F$2:F$1000, "<=" & EOMONTH(P4, 0)) -> 0 | R4: اضف معلومات الاستثمار
E5: 9 | G5: 45286 | H5: 5000 | I5: 459 | J5: =SUM(H5:I5) -> 5459 | K5: PAID | M5: 001-4059 | N5: 13.5 | P5: 45870 | Q5: =SUMIFS(J$2:J$1000, F$2:F$1000, ">=" & DATE(YEAR(P5), MONTH(P5), 1), F$2:F$1000, "<=" & EOMONTH(P5, 0)) -> 0 | R5: اخصم المبلغ من الكاش
A6: الفرص ذات التوزيعات 28 | E6: 12 | G6: 45286 | H6: 5000 | I6: 607.05 | J6: =SUM(H6:I6) -> 5607.05 | K6: PAID | M6: 001-2834 | N6: 13.3 | P6: 45901 | Q6: =SUMIFS(J$2:J$1000, F$2:F$1000, ">=" & DATE(YEAR(P6), MONTH(P6), 1), F$2:F$1000, "<=" & EOMONTH(P6, 0)) -> 0 | R6: انسخة كاملة السطر الى ALL
E7: 9 | G7: 45413 | H7: 20000 | I7: 1963.57 | J7: =SUM(H7:I7) -> 21963.57 | K7: PAID | L7: LATE | M7: 001-3926 | N7: 14.2 | P7: 45931 | Q7: =SUMIFS(J$2:J$1000, F$2:F$1000, ">=" & DATE(YEAR(P7), MONTH(P7), 1), F$2:F$1000, "<=" & EOMONTH(P7, 0)) -> 0 | R7: تحقق من التدفقات
E8: 4 | G8: 45351 | H8: 20000 | I8: 826.52 | J8: =SUM(H8:I8) -> 20826.52 | K8: PAID | M8: 001-4381 | N8: 14.2 | P8: 45962 | Q8: =SUMIFS(J$2:J$1000, F$2:F$1000, ">=" & DATE(YEAR(P8), MONTH(P8), 1), F$2:F$1000, "<=" & EOMONTH(P8, 0)) -> 0
E9: 9 | G9: 45519 | H9: 10000 | I9: 953.2 | J9: =SUM(H9:I9) -> 10953.2 | K9: PAID | L9: LATE | M9: 001-7936 | N9: 13.9 | P9: 45992 | Q9: =SUMIFS(J$2:J$1000, F$2:F$1000, ">=" & DATE(YEAR(P9), MONTH(P9), 1), F$2:F$1000, "<=" & EOMONTH(P9, 0)) -> 10729.61
A10: جميع الأرقام تم التأكد منها | E10: 17 | G10: 45742 | H10: 20000 | I10: 3744.86 | J10: =SUM(H10:I10) -> 23744.86 | K10: PAID | M10: 002-0535 | N10: 14.8 | P10: 46023 | Q10: =SUMIFS(J$2:J$1000, F$2:F$1000, ">=" & DATE(YEAR(P10), MONTH(P10), 1), F$2:F$1000, "<=" & EOMONTH(P10, 0)) -> 0 | R10: نهاية الأستثمار
A11: جميع التأخر والتعثر تم التأكد منها | E11: 28 | F11: 46147 | H11: 5000 | I11: 1652.77 | J11: =SUM(H11:I11) -> 6652.77 | K11: =IF(F11<=TODAY(),"Check!","Waiting") -> Waiting | M11: 001-08010 | N11: 15.2 | P11: 46054 | Q11: =SUMIFS(J$2:J$1000, F$2:F$1000, ">=" & DATE(YEAR(P11), MONTH(P11), 1), F$2:F$1000, "<=" & EOMONTH(P11, 0)) -> 0 | R11: PAID
A12: مطلوب : التأكد من جميع السداد المبكر | E12: 9 | G12: 45592 | H12: 5000 | I12: 463.86 | J12: =SUM(H12:I12) -> 5463.86 | K12: PAID | M12: 001-09127 | N12: 13.5 | P12: 46082 | Q12: =SUMIFS(J$2:J$1000, F$2:F$1000, ">=" & DATE(YEAR(P12), MONTH(P12), 1), F$2:F$1000, "<=" & EOMONTH(P12, 0)) -> 17190.89 | R12: غير مكان تاريخ الاستحقاق الى تاريخ السداد
E13: 14 | G13: 45683 | H13: 5000 | I13: 631.95 | J13: =SUM(H13:I13) -> 5631.95 | K13: PAID | M13: 001-7215 | N13: 13.8 | P13: 46113 | Q13: =SUMIFS(J$2:J$1000, F$2:F$1000, ">=" & DATE(YEAR(P13), MONTH(P13), 1), F$2:F$1000, "<=" & EOMONTH(P13, 0)) -> 29364.49 | R13: غير صافي الربح
E14: 38 | F14: 46481 | H14: 5000 | I14: 2055.02 | J14: =SUM(H14:I14) -> 7055.02 | K14: =IF(F14<=TODAY(),"Check!","Waiting") -> Waiting | M14: 001-1101 | N14: 14.1 | P14: 46143 | Q14: =SUMIFS(J$2:J$1000, F$2:F$1000, ">=" & DATE(YEAR(P14), MONTH(P14), 1), F$2:F$1000, "<=" & EOMONTH(P14, 0)) -> 18578.03 | R14: اكتب / EARLY OR LATE OR DEF
E15: 24 | G15: 45452 | H15: 5000 | I15: 205.51 | J15: =SUM(H15:I15) -> 5205.51 | K15: PAID | M15: النايفية العقارية | N15: 13.1 | P15: 46174 | Q15: =SUMIFS(J$2:J$1000, F$2:F$1000, ">=" & DATE(YEAR(P15), MONTH(P15), 1), F$2:F$1000, "<=" & EOMONTH(P15, 0)) -> 22154.87 | R15: اضف مبلغ الدفعة الى الكاش
E16: 16 | G16: 45812 | H16: 5000 | I16: 713.33 | J16: =SUM(H16:I16) -> 5713.33 | K16: PAID | L16: EARLY 7 | M16: 001-0523 | N16: 11.8 | P16: 46204 | Q16: =SUMIFS(J$2:J$1000, F$2:F$1000, ">=" & DATE(YEAR(P16), MONTH(P16), 1), F$2:F$1000, "<=" & EOMONTH(P16, 0)) -> 6485.95 | R16: انسخ كامل السطر الى ALL
E17: 6 | G17: 45512 | H17: 10000 | I17: 569.01 | J17: =SUM(H17:I17) -> 10569.01 | K17: PAID | M17: 001-5171 | N17: 13.2 | P17: 46235 | Q17: =SUMIFS(J$2:J$1000, F$2:F$1000, ">=" & DATE(YEAR(P17), MONTH(P17), 1), F$2:F$1000, "<=" & EOMONTH(P17, 0)) -> 19687.91
A18: تم التأكد من جمييييع الأرقام مع قيمة المحفظة ك كل 700,948 | E18: 9 | G18: 45600 | H18: 5000 | I18: 390.38 | J18: =SUM(H18:I18) -> 5390.38 | K18: PAID | M18: 001-5243 | N18: 12.3 | P18: 46266 | Q18: =SUMIFS(J$2:J$1000, F$2:F$1000, ">=" & DATE(YEAR(P18), MONTH(P18), 1), F$2:F$1000, "<=" & EOMONTH(P18, 0)) -> 0
A19: 0.7 | B19: 0.41 | C19: تصحيح الفواصل | E19: 10 | G19: 45669 | H19: 5000 | I19: 428.76 | J19: =SUM(H19:I19) -> 5428.76 | K19: PAID | M19: تالة العقارية | N19: 11.4 | P19: 46296 | Q19: =SUMIFS(J$2:J$1000, F$2:F$1000, ">=" & DATE(YEAR(P19), MONTH(P19), 1), F$2:F$1000, "<=" & EOMONTH(P19, 0)) -> 0
E20: 6 | G20: 45561 | H20: 5000 | I20: 300.25 | J20: =SUM(H20:I20) -> 5300.25 | K20: PAID | M20: 001-101472 1# | N20: 13.2 | P20: 46327 | Q20: =SUMIFS(J$2:J$1000, F$2:F$1000, ">=" & DATE(YEAR(P20), MONTH(P20), 1), F$2:F$1000, "<=" & EOMONTH(P20, 0)) -> 12083.62
A21: المأشرات | E21: 9 | G21: 45655 | H21: 5000 | I21: 458.24 | J21: =SUM(H21:I21) -> 5458.24 | K21: PAID | M21: 001-101472 2# | N21: 13.4 | P21: 46357 | Q21: =SUMIFS(J$2:J$1000, F$2:F$1000, ">=" & DATE(YEAR(P21), MONTH(P21), 1), F$2:F$1000, "<=" & EOMONTH(P21, 0)) -> 0
A22: القيمة الأسمية | B22: صافي الأرباح | C22: عدد الأستثمارات | E22: 6 | G22: 45565 | H22: 5000 | I22: 280 | J22: =SUM(H22:I22) -> 5280 | K22: PAID | M22: 001-010589 1# | N22: 12.3 | P22: 46388 | Q22: =SUMIFS(J$2:J$1000, F$2:F$1000, ">=" & DATE(YEAR(P22), MONTH(P22), 1), F$2:F$1000, "<=" & EOMONTH(P22, 0)) -> 6547.1
A23: =SUMIFS(H2:H300,F2:F300,"<>") -> 282000 | B23: =SUMIFS(I2:I300,F2:F300,"<>") -> 84142.68 | C23: =COUNT(N2:N300, "?*") -> 67 | E23: 9 | G23: 45649 | H23: 5000 | I23: 431.37 | J23: =SUM(H23:I23) -> 5431.37 | K23: PAID | M23: 001-10536 | N23: 13 | P23: 46419 | Q23: =SUMIFS(J$2:J$1000, F$2:F$1000, ">=" & DATE(YEAR(P23), MONTH(P23), 1), F$2:F$1000, "<=" & EOMONTH(P23, 0)) -> 0
A24: العائد السنوي ( APR ) | B24: العائد على الاستثمار ( ROI ) | C24: متوسط المدة ( بالشهر ) | E24: 13 | F24: 45792 | H24: 5000 | I24: 610.29 | J24: =SUM(H24:I24) -> 5610.29 | K24: =IF(F24<=TODAY(),"Check!","Waiting") -> Check! | L24: LATE | M24: 003-0728 | N24: 14.7 | P24: 46447 | Q24: =SUMIFS(J$2:J$1000, F$2:F$1000, ">=" & DATE(YEAR(P24), MONTH(P24), 1), F$2:F$1000, "<=" & EOMONTH(P24, 0)) -> 25596.38
A25: =AVERAGE(N2:N500) -> 14.016567 | B25: =TEXT(B23/A23, "0.00%") -> 29.84% | C25: =SUMPRODUCT(H2:H500, E2:E500) / SUM(H2:H500) -> 10.611111 | E25: 24 | G25: 45705 | H25: 5000 | I25: 481.39 | J25: =SUM(H25:I25) -> 5481.39 | K25: PAID | M25: النايفية ريزدنس 10 | N25: 12.9 | P25: 46478 | Q25: =SUMIFS(J$2:J$1000, F$2:F$1000, ">=" & DATE(YEAR(P25), MONTH(P25), 1), F$2:F$1000, "<=" & EOMONTH(P25, 0)) -> 7055.02
A26: الفرص المتأخرة | B26: الفرص النشطة | C26: الفرص المكتملة | E26: 24 | F26: 46140 | H26: 5000 | I26: 1151.34 | J26: =SUM(H26:I26) -> 6151.34 | K26: =IF(F26<=TODAY(),"Check!","Waiting") -> Waiting | M26: الرضا السكني | N26: 12.7 | P26: 46508 | Q26: =SUMIFS(J$2:J$1000, F$2:F$1000, ">=" & DATE(YEAR(P26), MONTH(P26), 1), F$2:F$1000, "<=" & EOMONTH(P26, 0)) -> 6429.23
A27: =COUNTIF(K2:K300, "CHECK!") -> 1 | B27: =COUNTIF(K2:K300, "WAITING") -> 31 | C27: =COUNTIF(K2:K300, "PAID") -> 35 | E27: 17 | G27: 45922 | H27: 5000 | I27: 936.94 | J27: =SUM(H27:I27) -> 5936.94 | K27: PAID | M27: 003-350 | N27: 14.4 | P27: 46539 | Q27: =SUMIFS(J$2:J$1000, F$2:F$1000, ">=" & DATE(YEAR(P27), MONTH(P27), 1), F$2:F$1000, "<=" & EOMONTH(P27, 0)) -> 0
E28: 17 | G28: 45931 | H28: 5000 | I28: 843.34 | J28: =SUM(H28:I28) -> 5843.34 | K28: PAID | M28: 001-010589 | N28: 13.1 | P28: 46569 | Q28: =SUMIFS(J$2:J$1000, F$2:F$1000, ">=" & DATE(YEAR(P28), MONTH(P28), 1), F$2:F$1000, "<=" & EOMONTH(P28, 0)) -> 42606.08
E29: 13 | G29: 45811 | H29: 5000 | I29: 622.41 | J29: =SUM(H29:I29) -> 5622.41 | K29: PAID | L29: EARLY 12 | M29: 002-01207 | N29: 12.4 | P29: 46600 | Q29: =SUMIFS(J$2:J$1000, F$2:F$1000, ">=" & DATE(YEAR(P29), MONTH(P29), 1), F$2:F$1000, "<=" & EOMONTH(P29, 0)) -> 0
A30: القيمة الأسمية المدفوعة | B30: صافي الأرباح المدفوع | C30: المجموع | E30: 24 | F30: 46145 | H30: 5000 | I30: 1251.93 | J30: =SUM(H30:I30) -> 6251.93 | K30: =IF(F30<=TODAY(),"Check!","Waiting") -> Waiting | M30: بيان 3 | N30: 13.7 | P30: 46631 | Q30: =SUMIFS(J$2:J$1000, F$2:F$1000, ">=" & DATE(YEAR(P30), MONTH(P30), 1), F$2:F$1000, "<=" & EOMONTH(P30, 0)) -> 13216.12
A31: =SUMIFS(H2:H167,G2:G167,"<>") -> 240000 | B31: =SUMIFS(I2:I167,G2:G167,"<>") -> 29150.26 | C31: =A31+B31 -> 269150.26 | E31: 9 | G31: 45753 | H31: 5000 | I31: 341.49 | J31: =SUM(H31:I31) -> 5341.49 | K31: PAID | M31: 001-6495 | N31: 14.6 | P31: 46661 | Q31: =SUMIFS(J$2:J$1000, F$2:F$1000, ">=" & DATE(YEAR(P31), MONTH(P31), 1), F$2:F$1000, "<=" & EOMONTH(P31, 0)) -> 0
A32: المجموع | E32: 18 | F32: 46196 | H32: 20000 | I32: 2154.87 | J32: =SUM(H32:I32) -> 22154.87 | K32: =IF(F32<=TODAY(),"Check!","Waiting") -> Waiting | M32: محمد بانعبم للتجارة | N32: 14.3 | P32: 46692 | Q32: =SUMIFS(J$2:J$1000, F$2:F$1000, ">=" & DATE(YEAR(P32), MONTH(P32), 1), F$2:F$1000, "<=" & EOMONTH(P32, 0)) -> 26053.94
A33: HOW TO USE: | E33: 30 | F33: 46110 | H33: 8000 | I33: 2571.94 | J33: =SUM(H33:I33) -> 10571.94 | K33: =IF(F33<=TODAY(),"Check!","Waiting") -> Waiting | M33: 001-11286 | N33: 14 | P33: 46722 | Q33: =SUMIFS(J$2:J$1000, F$2:F$1000, ">=" & DATE(YEAR(P33), MONTH(P33), 1), F$2:F$1000, "<=" & EOMONTH(P33, 0)) -> 13045.67
A34: In the Due culum, when the date come it will change to red | E34: 12 | F34: 46021 | H34: 4000 | I34: 396.34 | J34: =SUM(H34:I34) -> 4396.34 | K34: =IF(F34<=TODAY(),"Check!","Waiting") -> Waiting | M34: 001-12791 | N34: 11.1 | P34: 46753 | Q34: =SUMIFS(J$2:J$1000, F$2:F$1000, ">=" & DATE(YEAR(P34), MONTH(P34), 1), F$2:F$1000, "<=" & EOMONTH(P34, 0)) -> 0
A35: if its PAID, then type the Paiment date = this will compute the profits | E35: 9 | G35: 45901 | H35: 5000 | I35: 532.94 | J35: =SUM(H35:I35) -> 5532.94 | K35: PAID | L35: ERLY 30 / بيع ارض | M35: 001-14552 | N35: 18.3 | P35: 46784 | Q35: =SUMIFS(J$2:J$1000, F$2:F$1000, ">=" & DATE(YEAR(P35), MONTH(P35), 1), F$2:F$1000, "<=" & EOMONTH(P35, 0)) -> 13760.06
A36: automatically in the portfolio value | E36: 26 | F36: 46453 | H36: 5000 | I36: 1518.87 | J36: =SUM(H36:I36) -> 6518.87 | K36: =IF(F36<=TODAY(),"Check!","Waiting") -> Waiting | M36: يامن للتطوير العقاري | N36: 15.2 | P36: 46813 | Q36: =SUMIFS(J$2:J$1000, F$2:F$1000, ">=" & DATE(YEAR(P36), MONTH(P36), 1), F$2:F$1000, "<=" & EOMONTH(P36, 0)) -> 34726.23
A37: then type (PAID) to change to green | E37: 23 | F37: 46448 | H37: 10000 | I37: 2583.52 | J37: =SUM(H37:I37) -> 12583.52 | K37: =IF(F37<=TODAY(),"Check!","Waiting") -> Waiting | M37: الراسيات ريزدينس 27# | N37: 14.6 | P37: 46844 | Q37: =SUMIFS(J$2:J$1000, F$2:F$1000, ">=" & DATE(YEAR(P37), MONTH(P37), 1), F$2:F$1000, "<=" & EOMONTH(P37, 0)) -> 0
E38: 13 | F38: 46145 | H38: 5000 | I38: 673.33 | J38: =SUM(H38:I38) -> 5673.33 | K38: =IF(F38<=TODAY(),"Check!","Waiting") -> Waiting | M38: الدرر للمقاولات | N38: 13.6 | P38: 46874 | Q38: =SUMIFS(J$2:J$1000, F$2:F$1000, ">=" & DATE(YEAR(P38), MONTH(P38), 1), F$2:F$1000, "<=" & EOMONTH(P38, 0)) -> 7441.19
A39: Note | E39: 27 | F39: 46575 | H39: 10000 | I39: 2885.89 | J39: =SUM(H39:I39) -> 12885.89 | K39: =IF(F39<=TODAY(),"Check!","Waiting") -> Waiting | M39: بدء 41 | N39: 14 | P39: 46905 | Q39: =SUMIFS(J$2:J$1000, F$2:F$1000, ">=" & DATE(YEAR(P39), MONTH(P39), 1), F$2:F$1000, "<=" & EOMONTH(P39, 0)) -> 0
A40: Cash sum and subtract until cell 300. update if needed | E40: 19 | F40: 46348 | H40: 10000 | I40: 2083.62 | J40: =SUM(H40:I40) -> 12083.62 | K40: =IF(F40<=TODAY(),"Check!","Waiting") -> Waiting | M40: الراسيات ريزدينس 35# | N40: 14.2 | P40: 46935 | Q40: =SUMIFS(J$2:J$1000, F$2:F$1000, ">=" & DATE(YEAR(P40), MONTH(P40), 1), F$2:F$1000, "<=" & EOMONTH(P40, 0)) -> 0
A41: المجموع | E41: 31 | F41: 46729 | H41: 10000 | I41: 3045.67 | J41: =SUM(H41:I41) -> 13045.67 | K41: =IF(F41<=TODAY(),"Check!","Waiting") -> Waiting | M41: نمو هوم حطين | N41: 12.9 | P41: 46966 | Q41: =SUMIFS(J$2:J$1000, F$2:F$1000, ">=" & DATE(YEAR(P41), MONTH(P41), 1), F$2:F$1000, "<=" & EOMONTH(P41, 0)) -> 0
A42: المجموع | E42: 24 | F42: 46700 | H42: 10000 | I42: 2804.06 | J42: =SUM(H42:I42) -> 12804.06 | K42: =IF(F42<=TODAY(),"Check!","Waiting") -> Waiting | M42: خيال رايز | N42: 15.17 | P42: 46997 | Q42: =SUMIFS(J$2:J$1000, F$2:F$1000, ">=" & DATE(YEAR(P42), MONTH(P42), 1), F$2:F$1000, "<=" & EOMONTH(P42, 0)) -> 27780
E43: 34 | F43: 47008 | H43: 20000 | I43: 7780 | J43: =SUM(H43:I43) -> 27780 | K43: =IF(F43<=TODAY(),"Check!","Waiting") -> Waiting | M43: رفيعة 3 | N43: 14.9 | P43: 47027 | Q43: =SUMIFS(J$2:J$1000, F$2:F$1000, ">=" & DATE(YEAR(P43), MONTH(P43), 1), F$2:F$1000, "<=" & EOMONTH(P43, 0)) -> 0
P44: 47058 | Q44: =SUMIFS(J$2:J$1000, F$2:F$1000, ">=" & DATE(YEAR(P44), MONTH(P44), 1), F$2:F$1000, "<=" & EOMONTH(P44, 0)) -> 0
P45: 47088 | Q45: =SUMIFS(J$2:J$1000, F$2:F$1000, ">=" & DATE(YEAR(P45), MONTH(P45), 1), F$2:F$1000, "<=" & EOMONTH(P45, 0)) -> 0
P46: 47119 | Q46: =SUMIFS(J$2:J$1000, F$2:F$1000, ">=" & DATE(YEAR(P46), MONTH(P46), 1), F$2:F$1000, "<=" & EOMONTH(P46, 0)) -> 0
P47: 47150 | Q47: =SUMIFS(J$2:J$1000, F$2:F$1000, ">=" & DATE(YEAR(P47), MONTH(P47), 1), F$2:F$1000, "<=" & EOMONTH(P47, 0)) -> 0
P48: 47178 | Q48: =SUMIFS(J$2:J$1000, F$2:F$1000, ">=" & DATE(YEAR(P48), MONTH(P48), 1), F$2:F$1000, "<=" & EOMONTH(P48, 0)) -> 0
P49: 47209 | Q49: =SUMIFS(J$2:J$1000, F$2:F$1000, ">=" & DATE(YEAR(P49), MONTH(P49), 1), F$2:F$1000, "<=" & EOMONTH(P49, 0)) -> 0
P50: 47239 | Q50: =SUMIFS(J$2:J$1000, F$2:F$1000, ">=" & DATE(YEAR(P50), MONTH(P50), 1), F$2:F$1000, "<=" & EOMONTH(P50, 0)) -> 0
P51: 47270 | Q51: =SUMIFS(J$2:J$1000, F$2:F$1000, ">=" & DATE(YEAR(P51), MONTH(P51), 1), F$2:F$1000, "<=" & EOMONTH(P51, 0)) -> 0
P52: 47300 | Q52: =SUMIFS(J$2:J$1000, F$2:F$1000, ">=" & DATE(YEAR(P52), MONTH(P52), 1), F$2:F$1000, "<=" & EOMONTH(P52, 0)) -> 0
P53: 47331 | Q53: =SUMIFS(J$2:J$1000, F$2:F$1000, ">=" & DATE(YEAR(P53), MONTH(P53), 1), F$2:F$1000, "<=" & EOMONTH(P53, 0)) -> 0
P54: 47362 | Q54: =SUMIFS(J$2:J$1000, F$2:F$1000, ">=" & DATE(YEAR(P54), MONTH(P54), 1), F$2:F$1000, "<=" & EOMONTH(P54, 0)) -> 0
P55: 47392 | Q55: =SUMIFS(J$2:J$1000, F$2:F$1000, ">=" & DATE(YEAR(P55), MONTH(P55), 1), F$2:F$1000, "<=" & EOMONTH(P55, 0)) -> 0
... P69: 47818 | Q69: =SUMIFS(J$2:J$1000, F$2:F$1000, ">=" & DATE(YEAR(P69), MONTH(P69), 1), F$2:F$1000, "<=" & EOMONTH(P69, 0)) -> 0
H99: =SUM(H2:H98) -> 327000 | I99: =SUM(I2:I98)+A19 -> 56882.94 | J99: =SUM(H99:I99) -> 383882.94
I100: 2# | J100: حساب :
E101: المدة | F101: التاريخ | G101: تاريخ الأستحقاق | H101: القيمة الأسمية | I101: صافي الربح | J101: الدفعة | K101: الحالة | L101: C | M101: أسم الصك | N101: النسبة السنوية
E102: 43 | F102: 46573 | H102: 20000 | I102: 9720.19 | J102: =SUM(H102:I102) -> 29720.19 | K102: =IF(F102<=TODAY(),"Check!","Waiting") -> Waiting | M102: 001-4401 | N102: 14.7
E103: 21 | G103: 45900 | H103: 5000 | I103: 1153.08 | J103: =SUM(H103:I103) -> 6153.08 | K103: PAID | L103: EARLY 4 | M103: 002-1009 5# | N103: 14.3
E104: 24 | F104: 45998 | H104: 5000 | I104: 1333.27 | J104: =SUM(H104:I104) -> 6333.27 | K104: =IF(F104<=TODAY(),"Check!","Waiting") -> Waiting | M104: 002-1009 6# | N104: 14.5
E105: 27 | F105: 46089 | H105: 5000 | I105: 1618.95 | J105: =SUM(H105:I105) -> 6618.95 | K105: =IF(F105<=TODAY(),"Check!","Waiting") -> Waiting | M105: 001-7887 7# | N105: 15.6
E106: 18 | G106: 45796 | H106: 5000 | I106: 1007.84 | J106: =SUM(H106:I106) -> 6007.84 | K106: PAID | L106: EARLY 17 | M106: 001-7887 4# | N106: 14.9
E107: 24 | G107: 45916 | H107: 5000 | I107: 915.69 | J107: =SUM(H107:I107) -> 5915.69 | K107: PAID | L107: EARLY 4m | M107: أسس العقاري | N107: 12
E108: 15 | G108: 45761 | H108: 10000 | I108: 1624.85 | J108: =SUM(H108:I108) -> 11624.85 | K108: PAID | M108: 001-4059 | N108: 14.2
E109: 27 | G109: 45911 | H109: 5000 | I109: 929.21 | J109: =SUM(H109:I109) -> 5929.21 | K109: PAID | L109: EARLY 1Y | M109: بناءات 1 2# | N109: 14.7
E110: 27 | F110: 46238 | H110: 5000 | I110: 1526.69 | J110: =SUM(H110:I110) -> 6526.69 | K110: =IF(F110<=TODAY(),"Check!","Waiting") -> Waiting | M110: بناءات 1 3# | N110: 14.7
E111: 12 | G111: 45774 | H111: 5000 | I111: 554.86 | J111: =SUM(H111:I111) -> 5554.86 | K111: PAID | M111: 002-446 | N111: 12.3
E112: 27 | F112: 46243 | H112: 10000 | I112: 3161.22 | J112: =SUM(H112:I112) -> 13161.22 | K112: =IF(F112<=TODAY(),"Check!","Waiting") -> Waiting | M112: مساكن قرة 1 | N112: 15.2
E113: 48 | F113: 46880 | H113: 5000 | I113: 2441.19 | J113: =SUM(H113:I113) -> 7441.19 | K113: =IF(F113<=TODAY(),"Check!","Waiting") -> Waiting | M113: 001-8877 | N113: 13.4
E114: 40 | F114: 46642 | H114: 10000 | I114: 3216.12 | J114: =SUM(H114:I114) -> 13216.12 | K114: =IF(F114<=TODAY(),"Check!","Waiting") -> Waiting | M114: 001-0989 | N114: 14.4
E115: 26 | F115: 46216 | H115: 5000 | I115: 1485.95 | J115: =SUM(H115:I115) -> 6485.95 | K115: =IF(F115<=TODAY(),"Check!","Waiting") -> Waiting | M115: 001-3336 | N115: 14.9
E116: 23 | F116: 46125 | H116: 20000 | I116: 3213.15 | J116: =SUM(H116:I116) -> 23213.15 | K116: =IF(F116<=TODAY(),"Check!","Waiting") -> Waiting | M116: 001-010699 | N116: 13.1
E117: 8 | G117: 45648 | H117: 5000 | I117: 402.57 | J117: =SUM(H117:I117) -> 5402.57 | K117: PAID | M117: 001-9495 | N117: 14.1
E118: 32 | F118: 46404 | H118: 5000 | I118: 1547.1 | J118: =SUM(H118:I118) -> 6547.1 | K118: =IF(F118<=TODAY(),"Check!","Waiting") -> Waiting | M118: 001-9177 | N118: 12.8
E119: 10 | G119: 45725 | H119: 5000 | I119: 569.17 | J119: =SUM(H119:I119) -> 5569.17 | K119: PAID | M119: 001-7891 | N119: 15.3
E120: 12 | G120: 45652 | H120: 5000 | I120: 330.21 | J120: =SUM(H120:I120) -> 5330.21 | K120: PAID | M120: 001-11449 | N120: 12.6
E121: 26 | F121: 46453 | H121: 5000 | I121: 1493.99 | J121: =SUM(H121:I121) -> 6493.99 | K121: =IF(F121<=TODAY(),"Check!","Waiting") -> Waiting | M121: ناطحة العقارية | N121: 14.9
E122: 28 | F122: 46519 | H122: 5000 | I122: 1429.23 | J122: =SUM(H122:I122) -> 6429.23 | K122: =IF(F122<=TODAY(),"Check!","Waiting") -> Waiting | M122: 002-1093 | N122: 13.4
E123: 34 | F123: 46803 | H123: 10000 | I123: 3760.06 | J123: =SUM(H123:I123) -> 13760.06 | K123: =IF(F123<=TODAY(),"Check!","Waiting") -> Waiting | M123: مدى السكن العقاري 4# | N123: 14.4
E124: 34 | F124: 46824 | H124: 20000 | I124: 8035.65 | J124: =SUM(H124:I124) -> 28035.65 | K124: =IF(F124<=TODAY(),"Check!","Waiting") -> Waiting | M124: رحيب 1-2 | N124: 15.3
E125: 30 | F125: 46712 | H125: 10000 | I125: 3249.88 | J125: =SUM(H125:I125) -> 13249.88 | K125: =IF(F125<=TODAY(),"Check!","Waiting") -> Waiting | M125: مدى السكن العقاري 9# | N125: 14.2
E126: 28 | F126: 46813 | H126: 5000 | I126: 1690.58 | J126: =SUM(H126:I126) -> 6690.58 | K126: =IF(F126<=TODAY(),"Check!","Waiting") -> Waiting | M126: رحيب 4 | N126: 15.64
H146: =SUM(H102:H145) -> 195000 | I146: =SUM(I102:I145)+B19 -> 56411.11 | J146: =SUM(H146:I146) -> 251411.11

Sheet MANAFA
A1: قيمة المحفظة | C1: الكاش | E1: المدة | F1: تاريخ الأستحقاق | G1: تاريخ السداد | H1: القيمة الأسمية | I1: صافي الربح | J1: الدفعة | K1: الحالة | L1: C | M1: أسم الصك | N1: النسبة السنوية | P1: الشهر | Q1: التدفقات | R1: CHECKLIST
A2: =SUMIFS(J2:J300,F2:F300,"<>")+B19+A19+C2 -> 99426.24 | C2: 0 | E2: 4 | G2: 45456 | H2: 1000 | I2: 12.56 | J2: =SUM(H2:I2) -> 1012.56 | K2: PAID | L2: EARLY | M2: 4873-3983 | N2: 14.1 | P2: 45778 | Q2: =SUMIFS(J$2:J$1000, F$2:F$1000, ">=" & DATE(YEAR(P2), MONTH(P2), 1), F$2:F$1000, "<=" & EOMONTH(P2, 0)) -> 0
E3: 5 | G3: 45484 | H3: 1000 | I3: 21.91 | J3: =SUM(H3:I3) -> 1021.91 | K3: PAID | L3: EARLY | M3: / | N3: 14.3 | P3: 45809 | Q3: =SUMIFS(J$2:J$1000, F$2:F$1000, ">=" & DATE(YEAR(P3), MONTH(P3), 1), F$2:F$1000, "<=" & EOMONTH(P3, 0)) -> 0 | R3: بداية الأستثمار
A4: الملاحظات | E4: 4 | G4: 45489 | H4: 1000 | I4: 10.35 | J4: =SUM(H4:I4) -> 1010.35 | K4: PAID | L4: EARLY | M4: / | N4: 13.65 | P4: 45839 | Q4: =SUMIFS(J$2:J$1000, F$2:F$1000, ">=" & DATE(YEAR(P4), MONTH(P4), 1), F$2:F$1000, "<=" & EOMONTH(P4, 0)) -> 0 | R4: اضف معلومات الاستثمار
E5: 4 | G5: 45495 | H5: 1000 | I5: 23.74 | J5: =SUM(H5:I5) -> 1023.74 | K5: PAID | L5: EARLY | M5: / | N5: 14.04 | P5: 45870 | Q5: =SUMIFS(J$2:J$1000, F$2:F$1000, ">=" & DATE(YEAR(P5), MONTH(P5), 1), F$2:F$1000, "<=" & EOMONTH(P5, 0)) -> 0 | R5: اخصم المبلغ من الكاش
E6: 4 | G6: 45522 | H6: 1000 | I6: 35.5 | J6: =SUM(H6:I6) -> 1035.5 | K6: PAID | L6: EARLY | M6: / | N6: 14.67 | P6: 45901 | Q6: =SUMIFS(J$2:J$1000, F$2:F$1000, ">=" & DATE(YEAR(P6), MONTH(P6), 1), F$2:F$1000, "<=" & EOMONTH(P6, 0)) -> 0 | R6: انسخة كاملة السطر الى ALL
E7: 4 | G7: 45532 | H7: 1000 | I7: 35.89 | J7: =SUM(H7:I7) -> 1035.89 | K7: PAID | L7: EARLY | M7: / | N7: 14.49 | P7: 45931 | Q7: =SUMIFS(J$2:J$1000, F$2:F$1000, ">=" & DATE(YEAR(P7), MONTH(P7), 1), F$2:F$1000, "<=" & EOMONTH(P7, 0)) -> 0 | R7: تحقق من التدفقات
E8: 3 | G8: 45536 | H8: 1000 | I8: 28.19 | J8: =SUM(H8:I8) -> 1028.19 | K8: PAID | M8: / | N8: 14.64 | P8: 45962 | Q8: =SUMIFS(J$2:J$1000, F$2:F$1000, ">=" & DATE(YEAR(P8), MONTH(P8), 1), F$2:F$1000, "<=" & EOMONTH(P8, 0)) -> 10280.28
E9: 6 | G9: 45537 | H9: 1000 | I9: 37.4 | J9: =SUM(H9:I9) -> 1037.4 | K9: PAID | L9: EARLY | M9: / | N9: 14.08 | P9: 45992 | Q9: =SUMIFS(J$2:J$1000, F$2:F$1000, ">=" & DATE(YEAR(P9), MONTH(P9), 1), F$2:F$1000, "<=" & EOMONTH(P9, 0)) -> 0
E10: 4 | G10: 45537 | H10: 1000 | I10: 29.9 | J10: =SUM(H10:I10) -> 1029.9 | K10: PAID | L10: EARLY | M10: / | N10: 14.67 | P10: 46023 | Q10: =SUMIFS(J$2:J$1000, F$2:F$1000, ">=" & DATE(YEAR(P10), MONTH(P10), 1), F$2:F$1000, "<=" & EOMONTH(P10, 0)) -> 10463.54 | R10: نهاية الأستثمار
A11: جميع الأرقام تم التأكد منها | E11: 3 | G11: 45538 | H11: 1000 | I11: 27.42 | J11: =SUM(H11:I11) -> 1027.42 | K11: PAID | M11: / | N11: 14.24 | P11: 46054 | Q11: =SUMIFS(J$2:J$1000, F$2:F$1000, ">=" & DATE(YEAR(P11), MONTH(P11), 1), F$2:F$1000, "<=" & EOMONTH(P11, 0)) -> 42216.06 | R11: PAID
A12: تم التأكد من السداد المبكر | E12: 4 | G12: 45543 | H12: 1000 | I12: 37.52 | J12: =SUM(H12:I12) -> 1037.52 | K12: PAID | L12: EARLY | M12: / | N12: 15.06 | P12: 46082 | Q12: =SUMIFS(J$2:J$1000, F$2:F$1000, ">=" & DATE(YEAR(P12), MONTH(P12), 1), F$2:F$1000, "<=" & EOMONTH(P12, 0)) -> 0 | R12: غير مكان تاريخ الاستحقاق الى تاريخ السداد
A13: مطلوب : التأكد من جميع التأخيرات | E13: 4 | G13: 45552 | H13: 1000 | I13: 31.25 | J13: =SUM(H13:I13) -> 1031.25 | K13: PAID | L13: EARLY | M13: / | N13: 12.9 | P13: 46113 | Q13: =SUMIFS(J$2:J$1000, F$2:F$1000, ">=" & DATE(YEAR(P13), MONTH(P13), 1), F$2:F$1000, "<=" & EOMONTH(P13, 0)) -> 0 | R13: غير صافي الربح
E14: 5 | G14: 45564 | H14: 1000 | I14: 43.7 | J14: =SUM(H14:I14) -> 1043.7 | K14: PAID | L14: EARLY | M14: / | N14: 13.8 | P14: 46143 | Q14: =SUMIFS(J$2:J$1000, F$2:F$1000, ">=" & DATE(YEAR(P14), MONTH(P14), 1), F$2:F$1000, "<=" & EOMONTH(P14, 0)) -> 0 | R14: اكتب / EARLY OR LATE OR DEF
E15: 4 | G15: 45565 | H15: 1000 | I15: 75.16 | J15: =SUM(H15:I15) -> 1075.16 | K15: PAID | L15: EARLY | M15: / | N15: 14.64 | P15: 46174 | Q15: =SUMIFS(J$2:J$1000, F$2:F$1000, ">=" & DATE(YEAR(P15), MONTH(P15), 1), F$2:F$1000, "<=" & EOMONTH(P15, 0)) -> 0 | R15: اضف مبلغ الدفعة الى الكاش
E16: 5 | G16: 45565 | H16: 2000 | I16: 46.6 | J16: =SUM(H16:I16) -> 2046.6 | K16: PAID | M16: / | N16: 14.54 | P16: 46204 | Q16: =SUMIFS(J$2:J$1000, F$2:F$1000, ">=" & DATE(YEAR(P16), MONTH(P16), 1), F$2:F$1000, "<=" & EOMONTH(P16, 0)) -> 0 | R16: انسخ كامل السطر الى ALL
E17: 5 | G17: 45566 | H17: 1000 | I17: 47.5 | J17: =SUM(H17:I17) -> 1047.5 | K17: PAID | M17: / | N17: 14.66 | P17: 46235 | Q17: =SUMIFS(J$2:J$1000, F$2:F$1000, ">=" & DATE(YEAR(P17), MONTH(P17), 1), F$2:F$1000, "<=" & EOMONTH(P17, 0)) -> 0
E18: 5 | G18: 45566 | H18: 1000 | I18: 37.1 | J18: =SUM(H18:I18) -> 1037.1 | K18: PAID | L18: EARLY | M18: / | N18: 14.23 | P18: 46266 | Q18: =SUMIFS(J$2:J$1000, F$2:F$1000, ">=" & DATE(YEAR(P18), MONTH(P18), 1), F$2:F$1000, "<=" & EOMONTH(P18, 0)) -> 0
A19: 0 | B19: -1.64 | C19: تصحيح الفواصل | E19: 6 | G19: 45578 | H19: 1000 | I19: 43.69 | J19: =SUM(H19:I19) -> 1043.69 | K19: PAID | L19: EARLY | M19: / | N19: 12.44 | P19: 46296 | Q19: =SUMIFS(J$2:J$1000, F$2:F$1000, ">=" & DATE(YEAR(P19), MONTH(P19), 1), F$2:F$1000, "<=" & EOMONTH(P19, 0)) -> 0
E20: 6 | G20: 45585 | H20: 1000 | I20: 55.98 | J20: =SUM(H20:I20) -> 1055.98 | K20: PAID | L20: EARLY | M20: / | N20: 14.7 | P20: 46327 | Q20: =SUMIFS(J$2:J$1000, F$2:F$1000, ">=" & DATE(YEAR(P20), MONTH(P20), 1), F$2:F$1000, "<=" & EOMONTH(P20, 0)) -> 0
A21: المأشرات | E21: 4 | G21: 45586 | H21: 1000 | I21: 34.19 | J21: =SUM(H21:I21) -> 1034.19 | K21: PAID | M21: / | N21: 13.32 | P21: 46357 | Q21: =SUMIFS(J$2:J$1000, F$2:F$1000, ">=" & DATE(YEAR(P21), MONTH(P21), 1), F$2:F$1000, "<=" & EOMONTH(P21, 0)) -> 0
A22: القيمة الأسمية | B22: صافي الأرباح | C22: عدد الأستثمارات | E22: 6 | G22: 45592 | H22: 1000 | I22: 52.56 | J22: =SUM(H22:I22) -> 1052.56 | K22: PAID | L22: EARLY | M22: / | N22: 13.8 | P22: 46388 | Q22: =SUMIFS(J$2:J$1000, F$2:F$1000, ">=" & DATE(YEAR(P22), MONTH(P22), 1), F$2:F$1000, "<=" & EOMONTH(P22, 0)) -> 0
A23: =SUMIFS(H2:H300,F2:F300,"<>") -> 90000 | B23: =SUMIFS(I2:I300,F2:F300,"<>") -> 9427.88 | C23: =COUNT(N2:N300, "?*") -> 107 | E23: 5 | G23: 45593 | H23: 5000 | I23: 200.2 | J23: =SUM(H23:I23) -> 5200.2 | K23: PAID | M23: / | N23: 12.48 | P23: 46419 | Q23: =SUMIFS(J$2:J$1000, F$2:F$1000, ">=" & DATE(YEAR(P23), MONTH(P23), 1), F$2:F$1000, "<=" & EOMONTH(P23, 0)) -> 0
A24: العائد السنوي ( APR ) | B24: العائد على الاستثمار ( ROI ) | C24: متوسط المدة ( بالشهر ) | E24: 5 | G24: 45593 | H24: 1000 | I24: 40.4 | J24: =SUM(H24:I24) -> 1040.4 | K24: PAID | M24: / | N24: 12.48 | P24: 46447 | Q24: =SUMIFS(J$2:J$1000, F$2:F$1000, ">=" & DATE(YEAR(P24), MONTH(P24), 1), F$2:F$1000, "<=" & EOMONTH(P24, 0)) -> 0
A25: =AVERAGE(N2:N500) -> 14.123364 | B25: =TEXT(B23/A23, "0.00%") -> 10.48% | C25: =SUMPRODUCT(H2:H500, E2:E500) / SUM(H2:H500) -> 5.7829314 | E25: 5 | G25: 45595 | H25: 1000 | I25: 46.97 | J25: =SUM(H25:I25) -> 1046.97 | K25: PAID | M25: / | N25: 14.64 | P25: 46478 | Q25: =SUMIFS(J$2:J$1000, F$2:F$1000, ">=" & DATE(YEAR(P25), MONTH(P25), 1), F$2:F$1000, "<=" & EOMONTH(P25, 0)) -> 0
A26: الفرص المتأخرة | B26: الفرص النشطة | C26: الفرص المكتملة | E26: 3 | G26: 45596 | H26: 1000 | I26: 48.77 | J26: =SUM(H26:I26) -> 1048.77 | K26: PAID | L26: EARLY | M26: / | N26: 13.24 | P26: 46508 | Q26: =SUMIFS(J$2:J$1000, F$2:F$1000, ">=" & DATE(YEAR(P26), MONTH(P26), 1), F$2:F$1000, "<=" & EOMONTH(P26, 0)) -> 0
A27: =COUNTIF(K2:K300, "CHECK!") -> 0 | B27: =COUNTIF(K2:K300, "WAITING") -> 8 | C27: =COUNTIF(K2:K300, "PAID") -> 99 | E27: 7 | G27: 45596 | H27: 1000 | I27: 47.3 | J27: =SUM(H27:I27) -> 1047.3 | K27: PAID | L27: EARLY | M27: / | N27: 14.66 | P27: 46539 | Q27: =SUMIFS(J$2:J$1000, F$2:F$1000, ">=" & DATE(YEAR(P27), MONTH(P27), 1), F$2:F$1000, "<=" & EOMONTH(P27, 0)) -> 0
E28: 6 | G28: 45596 | H28: 2000 | I28: 46.94 | J28: =SUM(H28:I28) -> 2046.94 | K28: PAID | L28: EARLY | M28: / | N28: 14.66 | P28: 46569 | Q28: =SUMIFS(J$2:J$1000, F$2:F$1000, ">=" & DATE(YEAR(P28), MONTH(P28), 1), F$2:F$1000, "<=" & EOMONTH(P28, 0)) -> 0
E29: 4 | G29: 45600 | H29: 5000 | I29: 151.96 | J29: =SUM(H29:I29) -> 5151.96 | K29: PAID | L29: EARLY | M29: / | N29: 13.74 | P29: 46600 | Q29: =SUMIFS(J$2:J$1000, F$2:F$1000, ">=" & DATE(YEAR(P29), MONTH(P29), 1), F$2:F$1000, "<=" & EOMONTH(P29, 0)) -> 36468
A30: القيمة الأسمية المدفوعة | B30: صافي الأرباح المدفوع | C30: المجموع | E30: 5 | G30: 45601 | H30: 1000 | I30: 45.75 | J30: =SUM(H30:I30) -> 1045.75 | K30: PAID | L30: EARLY | M30: / | N30: 14.74 | P30: 46631 | Q30: =SUMIFS(J$2:J$1000, F$2:F$1000, ">=" & DATE(YEAR(P30), MONTH(P30), 1), F$2:F$1000, "<=" & EOMONTH(P30, 0)) -> 0
A31: =SUMIFS(H2:H167,G2:G167,"<>") -> 449000 | B31: =SUMIFS(I2:I167,G2:G167,"<>") -> 18578.66 | C31: =A31+B31 -> 467578.66 | E31: 6 | G31: 45602 | H31: 1000 | I31: 51.9 | J31: =SUM(H31:I31) -> 1051.9 | K31: PAID | M31: / | N31: 13.48 | P31: 46661 | Q31: =SUMIFS(J$2:J$1000, F$2:F$1000, ">=" & DATE(YEAR(P31), MONTH(P31), 1), F$2:F$1000, "<=" & EOMONTH(P31, 0)) -> 0
A32: المجموع | E32: 5 | G32: 45606 | H32: 1000 | I32: 82.56 | J32: =SUM(H32:I32) -> 1082.56 | K32: PAID | L32: EARLY | M32: / | N32: 12.86 | P32: 46692 | Q32: =SUMIFS(J$2:J$1000, F$2:F$1000, ">=" & DATE(YEAR(P32), MONTH(P32), 1), F$2:F$1000, "<=" & EOMONTH(P32, 0)) -> 0
A33: HOW TO USE: | E33: 7 | G33: 45627 | H33: 1000 | I33: 52.42 | J33: =SUM(H33:I33) -> 1052.42 | K33: PAID | L33: EARLY | M33: / | N33: 12.93 | P33: 46722 | Q33: =SUMIFS(J$2:J$1000, F$2:F$1000, ">=" & DATE(YEAR(P33), MONTH(P33), 1), F$2:F$1000, "<=" & EOMONTH(P33, 0)) -> 0
A34: In the Due culum, when the date come it will change to red | E34: 5 | G34: 45606 | H34: 2000 | I34: 82.56 | J34: =SUM(H34:I34) -> 2082.56 | K34: PAID | M34: / | N34: 12.86 | P34: 46753 | Q34: =SUMIFS(J$2:J$1000, F$2:F$1000, ">=" & DATE(YEAR(P34), MONTH(P34), 1), F$2:F$1000, "<=" & EOMONTH(P34, 0)) -> 0
A35: if its PAID, then type the Paiment date = this will compute the profits | E35: 4 | G35: 45606 | H35: 4000 | I35: 128.2 | J35: =SUM(H35:I35) -> 4128.2 | K35: PAID | M35: / | N35: 14.04 | P35: 46784 | Q35: =SUMIFS(J$2:J$1000, F$2:F$1000, ">=" & DATE(YEAR(P35), MONTH(P35), 1), F$2:F$1000, "<=" & EOMONTH(P35, 0)) -> 0
A36: automatically in the portfolio value | E36: 5 | G36: 45609 | H36: 1000 | I36: 46.13 | J36: =SUM(H36:I36) -> 1046.13 | K36: PAID | M36: / | N36: 14.38 | P36: 46813 | Q36: =SUMIFS(J$2:J$1000, F$2:F$1000, ">=" & DATE(YEAR(P36), MONTH(P36), 1), F$2:F$1000, "<=" & EOMONTH(P36, 0)) -> 0
A37: then type (PAID) to change to green | E37: 4 | G37: 45615 | H37: 10000 | I37: 318.2 | J37: =SUM(H37:I37) -> 10318.2 | K37: PAID | M37: / | N37: 12.39 | P37: 46844 | Q37: =SUMIFS(J$2:J$1000, F$2:F$1000, ">=" & DATE(YEAR(P37), MONTH(P37), 1), F$2:F$1000, "<=" & EOMONTH(P37, 0)) -> 0
E38: 3 | G38: 45624 | H38: 5000 | I38: 119.24 | J38: =SUM(H38:I38) -> 5119.24 | K38: PAID | L38: EARLY | M38: / | N38: 12.8 | P38: 46874 | Q38: =SUMIFS(J$2:J$1000, F$2:F$1000, ">=" & DATE(YEAR(P38), MONTH(P38), 1), F$2:F$1000, "<=" & EOMONTH(P38, 0)) -> 0
A39: Note | E39: 6 | G39: 45627 | H39: 1000 | I39: 52.27 | J39: =SUM(H39:I39) -> 1052.27 | K39: PAID | L39: EARLY | M39: / | N39: 13.8 | P39: 46905 | Q39: =SUMIFS(J$2:J$1000, F$2:F$1000, ">=" & DATE(YEAR(P39), MONTH(P39), 1), F$2:F$1000, "<=" & EOMONTH(P39, 0)) -> 0
A40: Cash sum and subtract until cell 300. update if needed | E40: 5 | G40: 45628 | H40: 5000 | I40: 212.8 | J40: =SUM(H40:I40) -> 5212.8 | K40: PAID | L40: EARLY | M40: / | N40: 14.5 | P40: 46935 | Q40: =SUMIFS(J$2:J$1000, F$2:F$1000, ">=" & DATE(YEAR(P40), MONTH(P40), 1), F$2:F$1000, "<=" & EOMONTH(P40, 0)) -> 0
A41: المجموع | E41: 6 | G41: 45628 | H41: 2000 | I41: 109.5 | J41: =SUM(H41:I41) -> 2109.5 | K41: PAID | M41: / | N41: 14.22 | P41: 46966 | Q41: =SUMIFS(J$2:J$1000, F$2:F$1000, ">=" & DATE(YEAR(P41), MONTH(P41), 1), F$2:F$1000, "<=" & EOMONTH(P41, 0)) -> 0
A42: المجموع | E42: 4 | G42: 45635 | H42: 1000 | I42: 34.4 | J42: =SUM(H42:I42) -> 1034.4 | K42: PAID | M42: / | N42: 13.26 | P42: 46997 | Q42: =SUMIFS(J$2:J$1000, F$2:F$1000, ">=" & DATE(YEAR(P42), MONTH(P42), 1), F$2:F$1000, "<=" & EOMONTH(P42, 0)) -> 0
E43: 6 | G43: 45637 | H43: 1000 | I43: 50.79 | J43: =SUM(H43:I43) -> 1050.79 | K43: PAID | L43: EARLY | M43: / | N43: 13.26 | P43: 47027 | Q43: =SUMIFS(J$2:J$1000, F$2:F$1000, ">=" & DATE(YEAR(P43), MONTH(P43), 1), F$2:F$1000, "<=" & EOMONTH(P43, 0)) -> 0
E44: 8 | G44: 45642 | H44: 1000 | I44: 65.18 | J44: =SUM(H44:I44) -> 1065.18 | K44: PAID | L44: EARLY | M44: / | N44: 13.47 | P44: 47058 | Q44: =SUMIFS(J$2:J$1000, F$2:F$1000, ">=" & DATE(YEAR(P44), MONTH(P44), 1), F$2:F$1000, "<=" & EOMONTH(P44, 0)) -> 0
E45: 4 | G45: 45656 | H45: 5000 | I45: 164.78 | J45: =SUM(H45:I45) -> 5164.78 | K45: PAID | M45: / | N45: 12.84 | P45: 47088 | Q45: =SUMIFS(J$2:J$1000, F$2:F$1000, ">=" & DATE(YEAR(P45), MONTH(P45), 1), F$2:F$1000, "<=" & EOMONTH(P45, 0)) -> 0
E46: 4 | G46: 45657 | H46: 5000 | I46: 189.4 | J46: =SUM(H46:I46) -> 5189.4 | K46: PAID | M46: / | N46: 14.73 | P46: 47119 | Q46: =SUMIFS(J$2:J$1000, F$2:F$1000, ">=" & DATE(YEAR(P46), MONTH(P46), 1), F$2:F$1000, "<=" & EOMONTH(P46, 0)) -> 0
E47: 5 | G47: 45662 | H47: 1000 | I47: 47.59 | J47: =SUM(H47:I47) -> 1047.59 | K47: PAID | M47: / | N47: 14.83 | P47: 47150 | Q47: =SUMIFS(J$2:J$1000, F$2:F$1000, ">=" & DATE(YEAR(P47), MONTH(P47), 1), F$2:F$1000, "<=" & EOMONTH(P47, 0)) -> 0
E48: 3 | G48: 45662 | H48: 5000 | I48: 144.33 | J48: =SUM(H48:I48) -> 5144.33 | K48: PAID | M48: / | N48: 15.72 | P48: 47178 | Q48: =SUMIFS(J$2:J$1000, F$2:F$1000, ">=" & DATE(YEAR(P48), MONTH(P48), 1), F$2:F$1000, "<=" & EOMONTH(P48, 0)) -> 0
E49: 4 | G49: 45666 | H49: 1000 | I49: 34.4 | J49: =SUM(H49:I49) -> 1034.4 | K49: PAID | M49: / | N49: 13.26 | P49: 47209 | Q49: =SUMIFS(J$2:J$1000, F$2:F$1000, ">=" & DATE(YEAR(P49), MONTH(P49), 1), F$2:F$1000, "<=" & EOMONTH(P49, 0)) -> 0
E50: 5 | G50: 45678 | H50: 6000 | I50: 282.74 | J50: =SUM(H50:I50) -> 6282.74 | K50: PAID | L50: EARLY | M50: / | N50: 14.78 | P50: 47239 | Q50: =SUMIFS(J$2:J$1000, F$2:F$1000, ">=" & DATE(YEAR(P50), MONTH(P50), 1), F$2:F$1000, "<=" & EOMONTH(P50, 0)) -> 0
E51: 6 | G51: 45679 | H51: 1000 | I51: 47.92 | J51: =SUM(H51:I51) -> 1047.92 | K51: PAID | L51: EARLY | M51: / | N51: 12.72 | P51: 47270 | Q51: =SUMIFS(J$2:J$1000, F$2:F$1000, ">=" & DATE(YEAR(P51), MONTH(P51), 1), F$2:F$1000, "<=" & EOMONTH(P51, 0)) -> 0
E52: 5 | G52: 45680 | H52: 5000 | I52: 221.52 | J52: =SUM(H52:I52) -> 5221.52 | K52: PAID | L52: EARLY | M52: / | N52: 14.09 | P52: 47300 | Q52: =SUMIFS(J$2:J$1000, F$2:F$1000, ">=" & DATE(YEAR(P52), MONTH(P52), 1), F$2:F$1000, "<=" & EOMONTH(P52, 0)) -> 0
E53: 5 | G53: 45685 | H53: 5000 | I53: 246.2 | J53: =SUM(H53:I53) -> 5246.2 | K53: PAID | M53: / | N53: 15.34 | P53: 47331 | Q53: =SUMIFS(J$2:J$1000, F$2:F$1000, ">=" & DATE(YEAR(P53), MONTH(P53), 1), F$2:F$1000, "<=" & EOMONTH(P53, 0)) -> 0
E54: 5 | G54: 45690 | H54: 6000 | I54: 273.51 | J54: =SUM(H54:I54) -> 6273.51 | K54: PAID | M54: / | N54: 14.21 | P54: 47362 | Q54: =SUMIFS(J$2:J$1000, F$2:F$1000, ">=" & DATE(YEAR(P54), MONTH(P54), 1), F$2:F$1000, "<=" & EOMONTH(P54, 0)) -> 0
E55: 5 | G55: 45690 | H55: 2000 | I55: 82.55 | J55: =SUM(H55:I55) -> 2082.55 | K55: PAID | M55: / | N55: 12.86 | P55: 47392 | Q55: =SUMIFS(J$2:J$1000, F$2:F$1000, ">=" & DATE(YEAR(P55), MONTH(P55), 1), F$2:F$1000, "<=" & EOMONTH(P55, 0)) -> 0
E56: 6 | G56: 45697 | H56: 5000 | I56: 234.32 | J56: =SUM(H56:I56) -> 5234.32 | K56: PAID | L56: EARLY | M56: / | N56: 13.5 | P56: 47423 | Q56: =SUMIFS(J$2:J$1000, F$2:F$1000, ">=" & DATE(YEAR(P56), MONTH(P56), 1), F$2:F$1000, "<=" & EOMONTH(P56, 0)) -> 0
E57: 6 | G57: 45701 | H57: 2000 | I57: 114.27 | J57: =SUM(H57:I57) -> 2114.27 | K57: PAID | M57: / | N57: 14.84 | P57: 47453 | Q57: =SUMIFS(J$2:J$1000, F$2:F$1000, ">=" & DATE(YEAR(P57), MONTH(P57), 1), F$2:F$1000, "<=" & EOMONTH(P57, 0)) -> 0
E58: 3 | G58: 45714 | H58: 5000 | I58: 141.3 | J58: =SUM(H58:I58) -> 5141.3 | K58: PAID | M58: / | N58: 14.7 | P58: 47484 | Q58: =SUMIFS(J$2:J$1000, F$2:F$1000, ">=" & DATE(YEAR(P58), MONTH(P58), 1), F$2:F$1000, "<=" & EOMONTH(P58, 0)) -> 0
E59: 3 | G59: 45718 | H59: 5000 | I59: 128.98 | J59: =SUM(H59:I59) -> 5128.98 | K59: PAID | M59: / | N59: 13.4 | P59: 47515 | Q59: =SUMIFS(J$2:J$1000, F$2:F$1000, ">=" & DATE(YEAR(P59), MONTH(P59), 1), F$2:F$1000, "<=" & EOMONTH(P59, 0)) -> 0
E60: 6 | G60: 45718 | H60: 5000 | I60: 264.88 | J60: =SUM(H60:I60) -> 5264.88 | K60: PAID | M60: / | N60: 13.76 | P60: 47543 | Q60: =SUMIFS(J$2:J$1000, F$2:F$1000, ">=" & DATE(YEAR(P60), MONTH(P60), 1), F$2:F$1000, "<=" & EOMONTH(P60, 0)) -> 0
E61: 3 | G61: 45719 | H61: 1000 | I61: 17.56 | J61: =SUM(H61:I61) -> 1017.56 | K61: PAID | L61: EARLY | M61: / | N61: 14.55 | P61: 47574 | Q61: =SUMIFS(J$2:J$1000, F$2:F$1000, ">=" & DATE(YEAR(P61), MONTH(P61), 1), F$2:F$1000, "<=" & EOMONTH(P61, 0)) -> 0
E62: 3 | G62: 45726 | H62: 5000 | I62: 144.76 | J62: =SUM(H62:I62) -> 5144.76 | K62: PAID | M62: / | N62: 15.03 | P62: 47604 | Q62: =SUMIFS(J$2:J$1000, F$2:F$1000, ">=" & DATE(YEAR(P62), MONTH(P62), 1), F$2:F$1000, "<=" & EOMONTH(P62, 0)) -> 0
E63: 3 | G63: 45728 | H63: 5000 | I63: 133.87 | J63: =SUM(H63:I63) -> 5133.87 | K63: PAID | L63: EARLY | M63: / | N63: 15.08 | P63: 47635 | Q63: =SUMIFS(J$2:J$1000, F$2:F$1000, ">=" & DATE(YEAR(P63), MONTH(P63), 1), F$2:F$1000, "<=" & EOMONTH(P63, 0)) -> 0
E64: 3 | G64: 45736 | H64: 5000 | I64: 132.11 | J64: =SUM(H64:I64) -> 5132.11 | K64: PAID | L64: EARLY | M64: / | N64: 15.43 | P64: 47665 | Q64: =SUMIFS(J$2:J$1000, F$2:F$1000, ">=" & DATE(YEAR(P64), MONTH(P64), 1), F$2:F$1000, "<=" & EOMONTH(P64, 0)) -> 0
E65: 4 | G65: 45743 | H65: 5000 | I65: 181.7 | J65: =SUM(H65:I65) -> 5181.7 | K65: PAID | L65: EARLY | M65: / | N65: 14.83 | P65: 47696 | Q65: =SUMIFS(J$2:J$1000, F$2:F$1000, ">=" & DATE(YEAR(P65), MONTH(P65), 1), F$2:F$1000, "<=" & EOMONTH(P65, 0)) -> 0
E66: 4 | G66: 45754 | H66: 20000 | I66: 726.99 | J66: =SUM(H66:I66) -> 20726.99 | K66: PAID | L66: EARLY | M66: / | N66: 14.41 | P66: 47727 | Q66: =SUMIFS(J$2:J$1000, F$2:F$1000, ">=" & DATE(YEAR(P66), MONTH(P66), 1), F$2:F$1000, "<=" & EOMONTH(P66, 0)) -> 0
E67: 4 | G67: 45754 | H67: 10000 | I67: 319.9 | J67: =SUM(H67:I67) -> 10319.9 | K67: PAID | L67: EARLY | M67: / | N67: 12.78 | P67: 47757 | Q67: =SUMIFS(J$2:J$1000, F$2:F$1000, ">=" & DATE(YEAR(P67), MONTH(P67), 1), F$2:F$1000, "<=" & EOMONTH(P67, 0)) -> 0
E68: 3 | G68: 45757 | H68: 5000 | I68: 146.3 | J68: =SUM(H68:I68) -> 5146.3 | K68: PAID | M68: / | N68: 15.2 | P68: 47788 | Q68: =SUMIFS(J$2:J$1000, F$2:F$1000, ">=" & DATE(YEAR(P68), MONTH(P68), 1), F$2:F$1000, "<=" & EOMONTH(P68, 0)) -> 0
E69: 4 | G69: 45762 | H69: 5000 | I69: 182.14 | J69: =SUM(H69:I69) -> 5182.14 | K69: PAID | L69: EARLY | M69: / | N69: 14.8
E70: 4 | G70: 45783 | H70: 5000 | I70: 198.6 | J70: =SUM(H70:I70) -> 5198.6 | K70: PAID | M70: / | N70: 14.41
E71: 5 | G71: 45811 | H71: 1000 | I71: 42.04 | J71: =SUM(H71:I71) -> 1042.04 | K71: PAID | L71: LATE | M71: / | N71: 13.11
E72: 4 | G72: 45824 | H72: 5000 | I72: 184.8 | J72: =SUM(H72:I72) -> 5184.8 | K72: PAID | L72: LATE | M72: / | N72: 14.4
E73: 3 | G73: 45818 | H73: 5000 | I73: 130.9 | J73: =SUM(H73:I73) -> 5130.9 | K73: PAID | M73: / | N73: 13.6
E74: 4 | G74: 45819 | H74: 5000 | I74: 188.65 | J74: =SUM(H74:I74) -> 5188.65 | K74: PAID | M74: / | N74: 14.69
E75: 3 | G75: 45848 | H75: 5000 | I75: 126.28 | J75: =SUM(H75:I75) -> 5126.28 | K75: PAID | L75: LATE | M75: / | N75: 13.11
E76: 3 | G76: 45784 | H76: 10000 | I76: 135.6 | J76: =SUM(H76:I76) -> 10135.6 | K76: PAID | L76: EARLY | M76: / | N76: 14.38
E77: 4 | G77: 45832 | H77: 20000 | I77: 808.89 | J77: =SUM(H77:I77) -> 20808.89 | K77: PAID | M77: / | N77: 13.7
E78: 4 | G78: 45838 | H78: 5000 | I78: 206.65 | J78: =SUM(H78:I78) -> 5206.65 | K78: PAID | M78: / | N78: 14.02
E79: 4 | G79: 45840 | H79: 5000 | I79: 220.81 | J79: =SUM(H79:I79) -> 5220.81 | K79: PAID | M79: / | N79: 14.98
E80: 4 | G80: 45858 | H80: 5000 | I80: 170.94 | J80: =SUM(H80:I80) -> 5170.94 | K80: PAID | L80: LATE | M80: / | N80: 13.32
E81: 4 | G81: 45848 | H81: 5000 | I81: 185.19 | J81: =SUM(H81:I81) -> 5185.19 | K81: PAID | M81: / | N81: 14.44
E82: 12 | G82: 45882 | H82: 2000 | I82: 222.7 | J82: =SUM(H82:I82) -> 2222.7 | K82: PAID | L82: LATE 10 | M82: / | N82: 14.42
E83: 4 | G83: 45879 | H83: 10000 | I83: 383.46 | J83: =SUM(H83:I83) -> 10383.46 | K83: PAID | M83: / | N83: 14.94
E84: 6 | G84: 45882 | H84: 5000 | I84: 266.81 | J84: =SUM(H84:I84) -> 5266.81 | K84: PAID | M84: / | N84: 14.86
E85: 4 | G85: 45886 | H85: 10000 | I85: 369 | J85: =SUM(H85:I85) -> 10369 | K85: PAID | L85: EARLY | M85: / | N85: 15.12
E86: 4 | G86: 45887 | H86: 10000 | I86: 380.38 | J86: =SUM(H86:I86) -> 10380.38 | K86: PAID | M86: / | N86: 14.82
E87: 4 | G87: 45893 | H87: 5000 | I87: 162.71 | J87: =SUM(H87:I87) -> 5162.71 | K87: PAID | L87: EARLY | M87: / | N87: 14.72
E88: 5 | G88: 45894 | H88: 10000 | I88: 457.38 | J88: =SUM(H88:I88) -> 10457.38 | K88: PAID | M88: / | N88: 14.26
E89: 6 | G89: 45920 | H89: 6000 | I89: 372.23 | J89: =SUM(H89:I89) -> 6372.23 | K89: PAID | L89: LATE | M89: / | N89: 14.02
E90: 5 | G90: 45904 | H90: 10000 | I90: 453.07 | J90: =SUM(H90:I90) -> 10453.07 | K90: PAID | L90: EARLY 2 | M90: / | N90: 14.4
E91: 5 | G91: 45920 | H91: 10000 | I91: 475.86 | J91: =SUM(H91:I91) -> 10475.86 | K91: PAID | L91: LATE | M91: / | N91: 14.83
E92: 5 | G92: 45914 | H92: 10000 | I92: 519.5 | J92: =SUM(H92:I92) -> 10519.5 | K92: PAID | M92: / | N92: 14.08
E93: 6 | G93: 45924 | H93: 5000 | I93: 269.5 | J93: =SUM(H93:I93) -> 5269.5 | K93: PAID | M93: / | N93: 14
E94: 6 | G94: 45937 | H94: 10000 | I94: 570.53 | J94: =SUM(H94:I94) -> 10570.53 | K94: PAID | L94: EARLY 1 | M94: / | N94: 14.9
E95: 6 | G95: 45945 | H95: 15000 | I95: 904.37 | J95: =SUM(H95:I95) -> 15904.37 | K95: PAID | M95: / | N95: 15.65
E96: 6 | G96: 45946 | H96: 10000 | I96: 612.42 | J96: =SUM(H96:I96) -> 10612.42 | K96: PAID | L96: LATE 20 | M96: 9840-6281 | N96: 13.83
E97: 6 | G97: 45953 | H97: 10000 | I97: 613.69 | J97: =SUM(H97:I97) -> 10613.69 | K97: PAID | L97: EARLY 3 | M97: / | N97: 15.95
E98: 6 | G98: 45946 | H98: 10000 | I98: 543.33 | J98: =SUM(H98:I98) -> 10543.33 | K98: PAID | L98: EARLY 10 | M98: / | N98: 12.98
E99: 6 | G99: 45965 | H99: 15000 | I99: 808.5 | J99: =SUM(H99:I99) -> 15808.5 | K99: PAID | L99: Late 6 | M99: 9849-3080 | N99: 14
E100: 7 | F100: 46061 | H100: 10000 | I100: 560.56 | J100: =SUM(H100:I100) -> 10560.56 | K100: =IF(F100<=TODAY(),"Check!","Waiting") -> Waiting | M100: 5100-1863 | N100: 14.55
...

Sheet DINAR
A1: قيمة المحفظة | C1: الكاش | E1: المدة | F1: تاريخ الأستحقاق | G1: تاريخ السداد | H1: القيمة الأسمية | I1: صافي الربح | J1: الدفعة | K1: الحالة | L1: C | M1: أسم الصك | N1: النسبة السنوية | P1: الشهر | Q1: التدفقات | R1: CHECKLIST
A2: =SUMIFS(J2:J300,F2:F300,"<>")+B19+A19+C2 -> 71925.5 | C2: 0 | E2: 9 | F2: 45716 | H2: 5000 | I2: 585 | J2: =SUM(H2:I2) -> 5585 | K2: =IF(F2<=TODAY(),"Check!","Waiting") -> Check! | L2: DEFF | M2: 0522-236 | N2: 15.6 | P2: 45778 | Q2: =SUMIFS(J$2:J$1000, F$2:F$1000, ">=" & DATE(YEAR(P2), MONTH(P2), 1), F$2:F$1000, "<=" & EOMONTH(P2, 0)) -> 0
E3: 30 | F3: 46374 | H3: 5000 | I3: 2297.5 | J3: =SUM(H3:I3) -> 7297.5 | K3: =IF(F3<=TODAY(),"Check!","Waiting") -> Waiting | M3: 1901-230 | N3: 18.38 | P3: 45809 | Q3: =SUMIFS(J$2:J$1000, F$2:F$1000, ">=" & DATE(YEAR(P3), MONTH(P3), 1), F$2:F$1000, "<=" & EOMONTH(P3, 0)) -> 0 | R3: بداية الأستثمار
A4: الملاحظات | E4: 9 | G4: 45763 | H4: 5000 | I4: 622.5 | J4: =SUM(H4:I4) -> 5622.5 | K4: PAID | M4: 0110-250 | N4: 16.6 | P4: 45839 | Q4: =SUMIFS(J$2:J$1000, F$2:F$1000, ">=" & DATE(YEAR(P4), MONTH(P4), 1), F$2:F$1000, "<=" & EOMONTH(P4, 0)) -> 0 | R4: اضف معلومات الاستثمار
E5: 6 | G5: 45678 | H5: 5000 | I5: 401.5 | J5: =SUM(H5:I5) -> 5401.5 | K5: PAID | M5: 0201-283 | N5: 16.06 | P5: 45870 | Q5: =SUMIFS(J$2:J$1000, F$2:F$1000, ">=" & DATE(YEAR(P5), MONTH(P5), 1), F$2:F$1000, "<=" & EOMONTH(P5, 0)) -> 0 | R5: اخصم المبلغ من الكاش
E6: 15 | F6: 46093 | H6: 5000 | I6: 937.5 | J6: =SUM(H6:I6) -> 5937.5 | K6: =IF(F6<=TODAY(),"Check!","Waiting") -> Waiting | M6: 0401-296 | N6: 15 | P6: 45901 | Q6: =SUMIFS(J$2:J$1000, F$2:F$1000, ">=" & DATE(YEAR(P6), MONTH(P6), 1), F$2:F$1000, "<=" & EOMONTH(P6, 0)) -> 0 | R6: انسخة كاملة السطر الى ALL
B7: تأخر الفرص | E7: 18 | F7: 46198 | H7: 5000 | I7: 1183.5 | J7: =SUM(H7:I7) -> 6183.5 | K7: =IF(F7<=TODAY(),"Check!","Waiting") -> Waiting | M7: 0522-327 | N7: 15.78 | P7: 45931 | Q7: =SUMIFS(J$2:J$1000, F$2:F$1000, ">=" & DATE(YEAR(P7), MONTH(P7), 1), F$2:F$1000, "<=" & EOMONTH(P7, 0)) -> 0 | R7: تحقق من التدفقات
B8: التطبيق سيء | E8: 21 | F8: 46541 | H8: 10000 | I8: 287 | J8: =SUM(H8:I8) -> 10287 | K8: =IF(F8<=TODAY(),"Check!","Waiting") -> Waiting | M8: محمد الحرفي للمقاولات | N8: 16.4 | P8: 45962 | Q8: =SUMIFS(J$2:J$1000, F$2:F$1000, ">=" & DATE(YEAR(P8), MONTH(P8), 1), F$2:F$1000, "<=" & EOMONTH(P8, 0)) -> 0
A9: مطلوب : التأكد من جميع التأخيرات | E9: 18 | F9: 46513 | H9: 10000 | I9: 2415 | J9: =SUM(H9:I9) -> 12415 | K9: =IF(F9<=TODAY(),"Check!","Waiting") -> Waiting | M9: معدل للتصميم | N9: 16.1 | P9: 45992 | Q9: =SUMIFS(J$2:J$1000, F$2:F$1000, ">=" & DATE(YEAR(P9), MONTH(P9), 1), F$2:F$1000, "<=" & EOMONTH(P9, 0)) -> 0
A10: مطلوب : التأكد من جميع السداد المبكر | E10: 15 | F10: 46429 | H10: 20000 | I10: 4220 | J10: =SUM(H10:I10) -> 24220 | K10: =IF(F10<=TODAY(),"Check!","Waiting") -> Waiting | M10: الهيثم للتعدين | N10: 16.88 | P10: 46023 | Q10: =SUMIFS(J$2:J$1000, F$2:F$1000, ">=" & DATE(YEAR(P10), MONTH(P10), 1), F$2:F$1000, "<=" & EOMONTH(P10, 0)) -> 0 | R10: نهاية الأستثمار
B11: مزكاه | P11: 46054 | Q11: =SUMIFS(J$2:J$1000, F$2:F$1000, ">=" & DATE(YEAR(P11), MONTH(P11), 1), F$2:F$1000, "<=" & EOMONTH(P11, 0)) -> 0 | R11: PAID
P12: 46082 | Q12: =SUMIFS(J$2:J$1000, F$2:F$1000, ">=" & DATE(YEAR(P12), MONTH(P12), 1), F$2:F$1000, "<=" & EOMONTH(P12, 0)) -> 5937.5 | R12: غير مكان تاريخ الاستحقاق الى تاريخ السداد
A13: جميع الأرقام تم التأكد منها | P13: 46113 | Q13: =SUMIFS(J$2:J$1000, F$2:F$1000, ">=" & DATE(YEAR(P13), MONTH(P13), 1), F$2:F$1000, "<=" & EOMONTH(P13, 0)) -> 0 | R13: غير صافي الربح
A14: ولاكن تم توزيع 1276.5 وهي غير مذكورة في صافي الربح | P14: 46143 | Q14: =SUMIFS(J$2:J$1000, F$2:F$1000, ">=" & DATE(YEAR(P14), MONTH(P14), 1), F$2:F$1000, "<=" & EOMONTH(P14, 0)) -> 0 | R14: اكتب / EARLY OR LATE OR DEF
P15: 46174 | Q15: =SUMIFS(J$2:J$1000, F$2:F$1000, ">=" & DATE(YEAR(P15), MONTH(P15), 1), F$2:F$1000, "<=" & EOMONTH(P15, 0)) -> 6183.5 | R15: اضف مبلغ الدفعة الى الكاش
P16: 46204 | Q16: =SUMIFS(J$2:J$1000, F$2:F$1000, ">=" & DATE(YEAR(P16), MONTH(P16), 1), F$2:F$1000, "<=" & EOMONTH(P16, 0)) -> 0 | R16: انسخ كامل السطر الى ALL
P17: 46235 | Q17: =SUMIFS(J$2:J$1000, F$2:F$1000, ">=" & DATE(YEAR(P17), MONTH(P17), 1), F$2:F$1000, "<=" & EOMONTH(P17, 0)) -> 0
P18: 46266 | Q18: =SUMIFS(J$2:J$1000, F$2:F$1000, ">=" & DATE(YEAR(P18), MONTH(P18), 1), F$2:F$1000, "<=" & EOMONTH(P18, 0)) -> 0
A19: 0 | B19: 0 | C19: تصحيح الفواصل | P19: 46296 | Q19: =SUMIFS(J$2:J$1000, F$2:F$1000, ">=" & DATE(YEAR(P19), MONTH(P19), 1), F$2:F$1000, "<=" & EOMONTH(P19, 0)) -> 0
P20: 46327 | Q20: =SUMIFS(J$2:J$1000, F$2:F$1000, ">=" & DATE(YEAR(P20), MONTH(P20), 1), F$2:F$1000, "<=" & EOMONTH(P20, 0)) -> 0
A21: المأشرات | P21: 46357 | Q21: =SUMIFS(J$2:J$1000, F$2:F$1000, ">=" & DATE(YEAR(P21), MONTH(P21), 1), F$2:F$1000, "<=" & EOMONTH(P21, 0)) -> 7297.5
A22: القيمة الأسمية | B22: صافي الأرباح | C22: عدد الأستثمارات | P22: 46388 | Q22: =SUMIFS(J$2:J$1000, F$2:F$1000, ">=" & DATE(YEAR(P22), MONTH(P22), 1), F$2:F$1000, "<=" & EOMONTH(P22, 0)) -> 0
A23: =SUMIFS(H2:H167,F2:F167,"<>") -> 60000 | B23: =SUMIFS(I2:I300,F2:F300,"<>") -> 11925.5 | C23: =COUNT(N2:N300, "?*") -> 9 | P23: 46419 | Q23: =SUMIFS(J$2:J$1000, F$2:F$1000, ">=" & DATE(YEAR(P23), MONTH(P23), 1), F$2:F$1000, "<=" & EOMONTH(P23, 0)) -> 24220
A24: العائد السنوي ( APR ) | B24: العائد على الاستثمار ( ROI ) | C24: متوسط المدة ( بالشهر ) | P24: 46447 | Q24: =SUMIFS(J$2:J$1000, F$2:F$1000, ">=" & DATE(YEAR(P24), MONTH(P24), 1), F$2:F$1000, "<=" & EOMONTH(P24, 0)) -> 0
A25: =AVERAGE(N2:N500) -> 16.311111 | B25: =TEXT(B23/A23, "0.00%") -> 19.88% | C25: =SUMPRODUCT(H2:H500, E2:E500) / SUM(H2:H500) -> 16.071429 | P25: 46478 | Q25: =SUMIFS(J$2:J$1000, F$2:F$1000, ">=" & DATE(YEAR(P25), MONTH(P25), 1), F$2:F$1000, "<=" & EOMONTH(P25, 0)) -> 0
A26: الفرص المتأخرة | B26: الفرص النشطة | C26: الفرص المكتملة | P26: 46508 | Q26: =SUMIFS(J$2:J$1000, F$2:F$1000, ">=" & DATE(YEAR(P26), MONTH(P26), 1), F$2:F$1000, "<=" & EOMONTH(P26, 0)) -> 12415
A27: =COUNTIF(K2:K300, "CHECK!") -> 1 | B27: =COUNTIF(K2:K300, "WAITING") -> 6 | C27: =COUNTIF(K2:K300, "Paid") -> 2 | P27: 46539 | Q27: =SUMIFS(J$2:J$1000, F$2:F$1000, ">=" & DATE(YEAR(P27), MONTH(P27), 1), F$2:F$1000, "<=" & EOMONTH(P27, 0)) -> 10287
P28: 46569 | Q28: =SUMIFS(J$2:J$1000, F$2:F$1000, ">=" & DATE(YEAR(P28), MONTH(P28), 1), F$2:F$1000, "<=" & EOMONTH(P28, 0)) -> 0
P29: 46600 | Q29: =SUMIFS(J$2:J$1000, F$2:F$1000, ">=" & DATE(YEAR(P29), MONTH(P29), 1), F$2:F$1000, "<=" & EOMONTH(P29, 0)) -> 0
A30: القيمة الأسمية المدفوعة | B30: صافي الأرباح المدفوع | C30: المجموع | P30: 46631 | Q30: =SUMIFS(J$2:J$1000, F$2:F$1000, ">=" & DATE(YEAR(P30), MONTH(P30), 1), F$2:F$1000, "<=" & EOMONTH(P30, 0)) -> 0
A31: =SUMIFS(H2:H167,G2:G167,"<>") -> 10000 | B31: =SUMIFS(I2:I167,G2:G167,"<>") -> 1024 | C31: =A31+B31 -> 11024 | P31: 46661 | Q31: =SUMIFS(J$2:J$1000, F$2:F$1000, ">=" & DATE(YEAR(P31), MONTH(P31), 1), F$2:F$1000, "<=" & EOMONTH(P31, 0)) -> 0
A32: المجموع | P32: 46692 | Q32: =SUMIFS(J$2:J$1000, F$2:F$1000, ">=" & DATE(YEAR(P32), MONTH(P32), 1), F$2:F$1000, "<=" & EOMONTH(P32, 0)) -> 0
A33: HOW TO USE: | P33: 46722 | Q33: =SUMIFS(J$2:J$1000, F$2:F$1000, ">=" & DATE(YEAR(P33), MONTH(P33), 1), F$2:F$1000, "<=" & EOMONTH(P33, 0)) -> 0
A34: In the Due culum, when the date come it will change to red | P34: 46753 | Q34: =SUMIFS(J$2:J$1000, F$2:F$1000, ">=" & DATE(YEAR(P34), MONTH(P34), 1), F$2:F$1000, "<=" & EOMONTH(P34, 0)) -> 0
A35: if its Paid, then type the Paiment date = this will compute the profits | P35: 46784 | Q35: =SUMIFS(J$2:J$1000, F$2:F$1000, ">=" & DATE(YEAR(P35), MONTH(P35), 1), F$2:F$1000, "<=" & EOMONTH(P35, 0)) -> 0
A36: automatically in the portfolio value | P36: 46813 | Q36: =SUMIFS(J$2:J$1000, F$2:F$1000, ">=" & DATE(YEAR(P36), MONTH(P36), 1), F$2:F$1000, "<=" & EOMONTH(P36, 0)) -> 0
A37: then type (Paid) to change to green | P37: 46844 | Q37: =SUMIFS(J$2:J$1000, F$2:F$1000, ">=" & DATE(YEAR(P37), MONTH(P37), 1), F$2:F$1000, "<=" & EOMONTH(P37, 0)) -> 0
P38: 46874 | Q38: =SUMIFS(J$2:J$1000, F$2:F$1000, ">=" & DATE(YEAR(P38), MONTH(P38), 1), F$2:F$1000, "<=" & EOMONTH(P38, 0)) -> 0
A39: Note | P39: 46905 | Q39: =SUMIFS(J$2:J$1000, F$2:F$1000, ">=" & DATE(YEAR(P39), MONTH(P39), 1), F$2:F$1000, "<=" & EOMONTH(P39, 0)) -> 0
A40: Cash sum and subtract until cell 300. update if needed | P40: 46935 | Q40: =SUMIFS(J$2:J$1000, F$2:F$1000, ">=" & DATE(YEAR(P40), MONTH(P40), 1), F$2:F$1000, "<=" & EOMONTH(P40, 0)) -> 0
A41: المجموع | P41: 46966 | Q41: =SUMIFS(J$2:J$1000, F$2:F$1000, ">=" & DATE(YEAR(P41), MONTH(P41), 1), F$2:F$1000, "<=" & EOMONTH(P41, 0)) -> 0
A42: المجموع | P42: 46997 | Q42: =SUMIFS(J$2:J$1000, F$2:F$1000, ">=" & DATE(YEAR(P42), MONTH(P42), 1), F$2:F$1000, "<=" & EOMONTH(P42, 0)) -> 0
P43: 47027 | Q43: =SUMIFS(J$2:J$1000, F$2:F$1000, ">=" & DATE(YEAR(P43), MONTH(P43), 1), F$2:F$1000, "<=" & EOMONTH(P43, 0)) -> 0
P44: 47058 | Q44: =SUMIFS(J$2:J$1000, F$2:F$1000, ">=" & DATE(YEAR(P44), MONTH(P44), 1), F$2:F$1000, "<=" & EOMONTH(P44, 0)) -> 0
P45: 47088 | Q45: =SUMIFS(J$2:J$1000, F$2:F$1000, ">=" & DATE(YEAR(P45), MONTH(P45), 1), F$2:F$1000, "<=" & EOMONTH(P45, 0)) -> 0
P46: 47119 | Q46: =SUMIFS(J$2:J$1000, F$2:F$1000, ">=" & DATE(YEAR(P46), MONTH(P46), 1), F$2:F$1000, "<=" & EOMONTH(P46, 0)) -> 0
P47: 47150 | Q47: =SUMIFS(J$2:J$1000, F$2:F$1000, ">=" & DATE(YEAR(P47), MONTH(P47), 1), F$2:F$1000, "<=" & EOMONTH(P47, 0)) -> 0
P48: 47178 | Q48: =SUMIFS(J$2:J$1000, F$2:F$1000, ">=" & DATE(YEAR(P48), MONTH(P48), 1), F$2:F$1000, "<=" & EOMONTH(P48, 0)) -> 0
P49: 47209 | Q49: =SUMIFS(J$2:J$1000, F$2:F$1000, ">=" & DATE(YEAR(P49), MONTH(P49), 1), F$2:F$1000, "<=" & EOMONTH(P49, 0)) -> 0
P50: 47239 | Q50: =SUMIFS(J$2:J$1000, F$2:F$1000, ">=" & DATE(YEAR(P50), MONTH(P50), 1), F$2:F$1000, "<=" & EOMONTH(P50, 0)) -> 0
P51: 47270 | Q51: =SUMIFS(J$2:J$1000, F$2:F$1000, ">=" & DATE(YEAR(P51), MONTH(P51), 1), F$2:F$1000, "<=" & EOMONTH(P51, 0)) -> 0
P52: 47300 | Q52: =SUMIFS(J$2:J$1000, F$2:F$1000, ">=" & DATE(YEAR(P52), MONTH(P52), 1), F$2:F$1000, "<=" & EOMONTH(P52, 0)) -> 0
P53: 47331 | Q53: =SUMIFS(J$2:J$1000, F$2:F$1000, ">=" & DATE(YEAR(P53), MONTH(P53), 1), F$2:F$1000, "<=" & EOMONTH(P53, 0)) -> 0
P54: 47362 | Q54: =SUMIFS(J$2:J$1000, F$2:F$1000, ">=" & DATE(YEAR(P54), MONTH(P54), 1), F$2:F$1000, "<=" & EOMONTH(P54, 0)) -> 0
... P68: 47788 | Q68: =SUMIFS(J$2:J$1000, F$2:F$1000, ">=" & DATE(YEAR(P68), MONTH(P68), 1), F$2:F$1000, "<=" & EOMONTH(P68, 0)) -> 0

Sheet LENDO
A1: قيمة المحفظة | C1: الكاش | E1: المدة | F1: تاريخ الأستحقاق | G1: تاريخ السداد | H1: القيمة الأسمية | I1: صافي الربح | J1: الدفعة | K1: الحالة | L1: C | M1: أسم الصك | N1: النسبة السنوية | P1: الشهر | Q1: التدفقات | R1: CHECKLIST
A2: =SUMIFS(J2:J300,F2:F300,"<>")+B19+A19+C2 -> 27321.49 | C2: 0 | E2: 3 | G2: 45479 | H2: 1000 | I2: 30.8 | J2: =SUM(H2:I2) -> 1030.8 | K2: PAID | M2: LN5301 | N2: 16 | P2: 45778 | Q2: =SUMIFS(J$2:J$1000, F$2:F$1000, ">=" & DATE(YEAR(P2), MONTH(P2), 1), F$2:F$1000, "<=" & EOMONTH(P2, 0)) -> 0
E3: 3 | G3: 45479 | H3: 1000 | I3: 21.17 | J3: =SUM(H3:I3) -> 1021.17 | K3: PAID | M3: / | N3: 11 | P3: 45809 | Q3: =SUMIFS(J$2:J$1000, F$2:F$1000, ">=" & DATE(YEAR(P3), MONTH(P3), 1), F$2:F$1000, "<=" & EOMONTH(P3, 0)) -> 1077 | R3: بداية الأستثمار
A4: الملاحظات | E4: 2 | G4: 45484 | H4: 1000 | I4: 19.25 | J4: =SUM(H4:I4) -> 1019.25 | K4: PAID | M4: / | N4: 15 | P4: 45839 | Q4: =SUMIFS(J$2:J$1000, F$2:F$1000, ">=" & DATE(YEAR(P4), MONTH(P4), 1), F$2:F$1000, "<=" & EOMONTH(P4, 0)) -> 0 | R4: اضف معلومات الاستثمار
E5: 4 | G5: 45509 | H5: 1000 | I5: 28.24 | J5: =SUM(H5:I5) -> 1028.24 | K5: PAID | M5: / | N5: 11 | P5: 45870 | Q5: =SUMIFS(J$2:J$1000, F$2:F$1000, ">=" & DATE(YEAR(P5), MONTH(P5), 1), F$2:F$1000, "<=" & EOMONTH(P5, 0)) -> 0 | R5: اخصم المبلغ من الكاش
E6: 3 | G6: 45525 | H6: 1000 | I6: 25.02 | J6: =SUM(H6:I6) -> 1025.02 | K6: PAID | M6: / | N6: 13 | P6: 45901 | Q6: =SUMIFS(J$2:J$1000, F$2:F$1000, ">=" & DATE(YEAR(P6), MONTH(P6), 1), F$2:F$1000, "<=" & EOMONTH(P6, 0)) -> 0 | R6: انسخة كاملة السطر الى ALL
A7: الفرص تتأخر دائما | B7: فرص سيءه جداا | E7: 5 | G7: 45546 | H7: 1000 | I7: 38.5 | J7: =SUM(H7:I7) -> 1038.5 | K7: PAID | M7: / | N7: 12 | P7: 45931 | Q7: =SUMIFS(J$2:J$1000, F$2:F$1000, ">=" & DATE(YEAR(P7), MONTH(P7), 1), F$2:F$1000, "<=" & EOMONTH(P7, 0)) -> 0 | R7: تحقق من التدفقات
A8: قلل من الأستثمار في المنصة | E8: 5 | G8: 45549 | H8: 5000 | I8: 224.59 | J8: =SUM(H8:I8) -> 5224.59 | K8: PAID | M8: / | N8: 14 | P8: 45962 | Q8: =SUMIFS(J$2:J$1000, F$2:F$1000, ">=" & DATE(YEAR(P8), MONTH(P8), 1), F$2:F$1000, "<=" & EOMONTH(P8, 0)) -> 0
E9: 5 | G9: 45554 | H9: 5000 | I9: 224.59 | J9: =SUM(H9:I9) -> 5224.59 | K9: PAID | M9: / | N9: 14 | P9: 45992 | Q9: =SUMIFS(J$2:J$1000, F$2:F$1000, ">=" & DATE(YEAR(P9), MONTH(P9), 1), F$2:F$1000, "<=" & EOMONTH(P9, 0)) -> 0
A10: القيمة الاسمية تم التأكد منها | E10: 5 | G10: 45554 | H10: 5000 | I10: 224.59 | J10: =SUM(H10:I10) -> 5224.59 | K10: PAID | M10: / | N10: 14 | P10: 46023 | Q10: =SUMIFS(J$2:J$1000, F$2:F$1000, ">=" & DATE(YEAR(P10), MONTH(P10), 1), F$2:F$1000, "<=" & EOMONTH(P10, 0)) -> 0 | R10: نهاية الأستثمار
A11: الأرباح فيه اختلاف بمقدار 423.4 | E11: 2 | G11: 45556 | H11: 1000 | I11: 19.25 | J11: =SUM(H11:I11) -> 1019.25 | K11: PAID | M11: / | N11: 15 | P11: 46054 | Q11: =SUMIFS(J$2:J$1000, F$2:F$1000, ">=" & DATE(YEAR(P11), MONTH(P11), 1), F$2:F$1000, "<=" & EOMONTH(P11, 0)) -> 0 | R11: PAID
A12: غالبا يرجع الى الفرص المسدده جزئيا | E12: 3 | G12: 45565 | H12: 1000 | I12: 26.95 | J12: =SUM(H12:I12) -> 1026.95 | K12: PAID | M12: / | N12: 14 | P12: 46082 | Q12: =SUMIFS(J$2:J$1000, F$2:F$1000, ">=" & DATE(YEAR(P12), MONTH(P12), 1), F$2:F$1000, "<=" & EOMONTH(P12, 0)) -> 0 | R12: غير مكان تاريخ الاستحقاق الى تاريخ السداد
E13: 6 | G13: 45569 | H13: 1000 | I13: 61.6 | J13: =SUM(H13:I13) -> 1061.6 | K13: PAID | M13: / | N13: 16 | P13: 46113 | Q13: =SUMIFS(J$2:J$1000, F$2:F$1000, ">=" & DATE(YEAR(P13), MONTH(P13), 1), F$2:F$1000, "<=" & EOMONTH(P13, 0)) -> 0 | R13: غير صافي الربح
A14: مطلوب : التأكد من جميع التأخيرات | E14: 4 | G14: 45572 | H14: 1000 | I14: 56.67 | J14: =SUM(H14:I14) -> 1056.67 | K14: PAID | M14: / | N14: 17 | P14: 46143 | Q14: =SUMIFS(J$2:J$1000, F$2:F$1000, ">=" & DATE(YEAR(P14), MONTH(P14), 1), F$2:F$1000, "<=" & EOMONTH(P14, 0)) -> 0 | R14: اكتب / EARLY OR LATE OR DEF
A15: مطلوب : التأكد من جميع السداد المبكر | E15: 2 | G15: 45577 | H15: 2000 | I15: 53.9 | J15: =SUM(H15:I15) -> 2053.9 | K15: PAID | M15: / | N15: 21 | P15: 46174 | Q15: =SUMIFS(J$2:J$1000, F$2:F$1000, ">=" & DATE(YEAR(P15), MONTH(P15), 1), F$2:F$1000, "<=" & EOMONTH(P15, 0)) -> 0 | R15: اضف مبلغ الدفعة الى الكاش
E16: 6 | G16: 45580 | H16: 1000 | I16: 63.52 | J16: =SUM(H16:I16) -> 1063.52 | K16: PAID | M16: / | N16: 16.5 | P16: 46204 | Q16: =SUMIFS(J$2:J$1000, F$2:F$1000, ">=" & DATE(YEAR(P16), MONTH(P16), 1), F$2:F$1000, "<=" & EOMONTH(P16, 0)) -> 0 | R16: انسخ كامل السطر الى ALL
E17: 6 | G17: 45584 | H17: 1000 | I17: 61.6 | J17: =SUM(H17:I17) -> 1061.6 | K17: PAID | L17: LATE | M17: / | N17: 16 | P17: 46235 | Q17: =SUMIFS(J$2:J$1000, F$2:F$1000, ">=" & DATE(YEAR(P17), MONTH(P17), 1), F$2:F$1000, "<=" & EOMONTH(P17, 0)) -> 0
E18: 3 | G18: 45586 | H18: 1000 | I18: 34.65 | J18: =SUM(H18:I18) -> 1034.65 | K18: PAID | M18: / | N18: 18 | P18: 46266 | Q18: =SUMIFS(J$2:J$1000, F$2:F$1000, ">=" & DATE(YEAR(P18), MONTH(P18), 1), F$2:F$1000, "<=" & EOMONTH(P18, 0)) -> 0
A19: 0 | B19: 0 | C19: تصحيح الفواصل | E19: 6 | G19: 45589 | H19: 1000 | I19: 57.75 | J19: =SUM(H19:I19) -> 1057.75 | K19: PAID | L19: LATE | M19: / | N19: 15 | P19: 46296 | Q19: =SUMIFS(J$2:J$1000, F$2:F$1000, ">=" & DATE(YEAR(P19), MONTH(P19), 1), F$2:F$1000, "<=" & EOMONTH(P19, 0)) -> 0
E20: 6 | G20: 45592 | H20: 1000 | I20: 53.9 | J20: =SUM(H20:I20) -> 1053.9 | K20: PAID | M20: / | N20: 14 | P20: 46327 | Q20: =SUMIFS(J$2:J$1000, F$2:F$1000, ">=" & DATE(YEAR(P20), MONTH(P20), 1), F$2:F$1000, "<=" & EOMONTH(P20, 0)) -> 0
A21: المأشرات | E21: 6 | G21: 45593 | H21: 1000 | I21: 53.9 | J21: =SUM(H21:I21) -> 1053.9 | K21: PAID | M21: / | N21: 14 | P21: 46357 | Q21: =SUMIFS(J$2:J$1000, F$2:F$1000, ">=" & DATE(YEAR(P21), MONTH(P21), 1), F$2:F$1000, "<=" & EOMONTH(P21, 0)) -> 0
A22: القيمة الأسمية | B22: صافي الأرباح | C22: عدد الأستثمارات | E22: 4 | G22: 45593 | H22: 1000 | I22: 41.06 | J22: =SUM(H22:I22) -> 1041.06 | K22: PAID | M22: / | N22: 16 | P22: 46388 | Q22: =SUMIFS(J$2:J$1000, F$2:F$1000, ">=" & DATE(YEAR(P22), MONTH(P22), 1), F$2:F$1000, "<=" & EOMONTH(P22, 0)) -> 0
A23: =SUMIFS(H2:H300,F2:F300,"<>") -> 26000 | B23: =SUMIFS(I2:I300,F2:F300,"<>") -> 1321.49 | C23: =COUNT(N2:N300, "?*") -> 87 | E23: 2 | G23: 45593 | H23: 3000 | I23: 53.9 | J23: =SUM(H23:I23) -> 3053.9 | K23: PAID | M23: / | N23: 14 | P23: 46419 | Q23: =SUMIFS(J$2:J$1000, F$2:F$1000, ">=" & DATE(YEAR(P23), MONTH(P23), 1), F$2:F$1000, "<=" & EOMONTH(P23, 0)) -> 0
A24: العائد السنوي ( APR ) | B24: العائد على الاستثمار ( ROI ) | C24: متوسط المدة ( بالشهر ) | E24: 2 | G24: 45593 | H24: 2000 | I24: 51.34 | J24: =SUM(H24:I24) -> 2051.34 | K24: PAID | L24: LATE | M24: / | N24: 20 | P24: 46447 | Q24: =SUMIFS(J$2:J$1000, F$2:F$1000, ">=" & DATE(YEAR(P24), MONTH(P24), 1), F$2:F$1000, "<=" & EOMONTH(P24, 0)) -> 0
B25: =TEXT(B23/A23, "0.00%") -> 5.08% | C25: =SUMPRODUCT(H2:H500, E2:E500) / SUM(H2:H500) -> 3.6864654 | E25: 6 | G25: 45594 | H25: 1000 | I25: 53.9 | J25: =SUM(H25:I25) -> 1053.9 | K25: PAID | M25: / | N25: 14 | P25: 46478 | Q25: =SUMIFS(J$2:J$1000, F$2:F$1000, ">=" & DATE(YEAR(P25), MONTH(P25), 1), F$2:F$1000, "<=" & EOMONTH(P25, 0)) -> 0
A26: الفرص المتأخرة | B26: الفرص النشطة | C26: الفرص المكتملة | E26: 3 | G26: 45598 | H26: 1000 | I26: 32.72 | J26: =SUM(H26:I26) -> 1032.72 | K26: PAID | M26: / | N26: 17 | P26: 46508 | Q26: =SUMIFS(J$2:J$1000, F$2:F$1000, ">=" & DATE(YEAR(P26), MONTH(P26), 1), F$2:F$1000, "<=" & EOMONTH(P26, 0)) -> 0
A27: =COUNTIF(K2:K300, "CHECK!") -> 11 | B27: =COUNTIF(K2:K300, "WAITING") -> 0 | C27: =COUNTIF(K2:K300, "Paid") -> 76 | E27: 3 | G27: 45599 | H27: 1000 | I27: 40.42 | J27: =SUM(H27:I27) -> 1040.42 | K27: PAID | M27: / | N27: 21 | P27: 46539 | Q27: =SUMIFS(J$2:J$1000, F$2:F$1000, ">=" & DATE(YEAR(P27), MONTH(P27), 1), F$2:F$1000, "<=" & EOMONTH(P27, 0)) -> 0
E28: 3 | G28: 45601 | H28: 3000 | I28: 103.95 | J28: =SUM(H28:I28) -> 3103.95 | K28: PAID | M28: / | N28: 18 | P28: 46569 | Q28: =SUMIFS(J$2:J$1000, F$2:F$1000, ">=" & DATE(YEAR(P28), MONTH(P28), 1), F$2:F$1000, "<=" & EOMONTH(P28, 0)) -> 0
E29: 2 | G29: 45605 | H29: 1000 | I29: 32.65 | J29: =SUM(H29:I29) -> 1032.65 | K29: PAID | M29: / | N29: 18 | P29: 46600 | Q29: =SUMIFS(J$2:J$1000, F$2:F$1000, ">=" & DATE(YEAR(P29), MONTH(P29), 1), F$2:F$1000, "<=" & EOMONTH(P29, 0)) -> 0
A30: القيمة الأسمية المدفوعة | B30: صافي الأرباح المدفوع | C30: المجموع | E30: 3 | G30: 45607 | H30: 2000 | I30: 57.75 | J30: =SUM(H30:I30) -> 2057.75 | K30: PAID | M30: / | N30: 15 | P30: 46631 | Q30: =SUMIFS(J$2:J$1000, F$2:F$1000, ">=" & DATE(YEAR(P30), MONTH(P30), 1), F$2:F$1000, "<=" & EOMONTH(P30, 0)) -> 0
A31: =SUMIFS(H2:H167,G2:G167,"<>") -> 179400 | B31: =SUMIFS(I2:I167,G2:G167,"<>") -> 7155.9 | C31: =A31+B31 -> 186555.9 | E31: 3 | G31: 45608 | H31: 1400 | I31: 48.51 | J31: =SUM(H31:I31) -> 1448.51 | K31: PAID | M31: / | N31: 18 | P31: 46661 | Q31: =SUMIFS(J$2:J$1000, F$2:F$1000, ">=" & DATE(YEAR(P31), MONTH(P31), 1), F$2:F$1000, "<=" & EOMONTH(P31, 0)) -> 0
A32: المجموع | E32: 4 | G32: 45608 | H32: 1000 | I32: 38.5 | J32: =SUM(H32:I32) -> 1038.5 | K32: PAID | M32: / | N32: 15 | P32: 46692 | Q32: =SUMIFS(J$2:J$1000, F$2:F$1000, ">=" & DATE(YEAR(P32), MONTH(P32), 1), F$2:F$1000, "<=" & EOMONTH(P32, 0)) -> 0
A33: HOW TO USE: | E33: 4 | G33: 45610 | H33: 1000 | I33: 48.76 | J33: =SUM(H33:I33) -> 1048.76 | K33: PAID | M33: / | N33: 19 | P33: 46722 | Q33: =SUMIFS(J$2:J$1000, F$2:F$1000, ">=" & DATE(YEAR(P33), MONTH(P33), 1), F$2:F$1000, "<=" & EOMONTH(P33, 0)) -> 0
A34: In the Due culum, when the date come it will change to red | E34: 4 | G34: 45610 | H34: 1000 | I34: 41.06 | J34: =SUM(H34:I34) -> 1041.06 | K34: PAID | M34: / | N34: 16 | P34: 46753 | Q34: =SUMIFS(J$2:J$1000, F$2:F$1000, ">=" & DATE(YEAR(P34), MONTH(P34), 1), F$2:F$1000, "<=" & EOMONTH(P34, 0)) -> 0
A35: if its Paid, then type the Paiment date = this will compute the profits | E35: 3 | G35: 45610 | H35: 5000 | I35: 225 | J35: =SUM(H35:I35) -> 5225 | K35: PAID | M35: / | N35: 18 | P35: 46784 | Q35: =SUMIFS(J$2:J$1000, F$2:F$1000, ">=" & DATE(YEAR(P35), MONTH(P35), 1), F$2:F$1000, "<=" & EOMONTH(P35, 0)) -> 0
A36: automatically in the portfolio value | E36: 3 | G36: 45613 | H36: 2000 | I36: 85 | J36: =SUM(H36:I36) -> 2085 | K36: PAID | M36: / | N36: 17 | P36: 46813 | Q36: =SUMIFS(J$2:J$1000, F$2:F$1000, ">=" & DATE(YEAR(P36), MONTH(P36), 1), F$2:F$1000, "<=" & EOMONTH(P36, 0)) -> 0
A37: then type (Paid) to change to green | E37: 3 | G37: 45623 | H37: 5000 | I37: 144.38 | J37: =SUM(H37:I37) -> 5144.38 | K37: PAID | M37: / | N37: 15 | P37: 46844 | Q37: =SUMIFS(J$2:J$1000, F$2:F$1000, ">=" & DATE(YEAR(P37), MONTH(P37), 1), F$2:F$1000, "<=" & EOMONTH(P37, 0)) -> 0
E38: 6 | G38: 45625 | H38: 1000 | I38: 53.9 | J38: =SUM(H38:I38) -> 1053.9 | K38: PAID | M38: / | N38: 14 | P38: 46874 | Q38: =SUMIFS(J$2:J$1000, F$2:F$1000, ">=" & DATE(YEAR(P38), MONTH(P38), 1), F$2:F$1000, "<=" & EOMONTH(P38, 0)) -> 0
A39: Note | E39: 5 | G39: 45632 | H39: 1000 | I39: 67.37 | J39: =SUM(H39:I39) -> 1067.37 | K39: PAID | M39: / | N39: 21 | P39: 46905 | Q39: =SUMIFS(J$2:J$1000, F$2:F$1000, ">=" & DATE(YEAR(P39), MONTH(P39), 1), F$2:F$1000, "<=" & EOMONTH(P39, 0)) -> 0
A40: Cash sum and subtract until cell 300. update if needed | E40: 5 | G40: 45632 | H40: 1000 | I40: 48.12 | J40: =SUM(H40:I40) -> 1048.12 | K40: PAID | M40: / | N40: 15 | P40: 46935 | Q40: =SUMIFS(J$2:J$1000, F$2:F$1000, ">=" & DATE(YEAR(P40), MONTH(P40), 1), F$2:F$1000, "<=" & EOMONTH(P40, 0)) -> 0
A41: المجموع | E41: 4 | G41: 45632 | H41: 1000 | I41: 57.75 | J41: =SUM(H41:I41) -> 1057.75 | K41: PAID | M41: / | N41: 18 | P41: 46966 | Q41: =SUMIFS(J$2:J$1000, F$2:F$1000, ">=" & DATE(YEAR(P41), MONTH(P41), 1), F$2:F$1000, "<=" & EOMONTH(P41, 0)) -> 0
A42: المجموع | E42: 3 | G42: 45634 | H42: 1000 | I42: 28.87 | J42: =SUM(H42:I42) -> 1028.87 | K42: PAID | M42: / | N42: 15 | P42: 46997 | Q42: =SUMIFS(J$2:J$1000, F$2:F$1000, ">=" & DATE(YEAR(P42), MONTH(P42), 1), F$2:F$1000, "<=" & EOMONTH(P42, 0)) -> 0
E43: 4 | G43: 45638 | H43: 2000 | I43: 107.8 | J43: =SUM(H43:I43) -> 2107.8 | K43: PAID | M43: / | N43: 21 | P43: 47027 | Q43: =SUMIFS(J$2:J$1000, F$2:F$1000, ">=" & DATE(YEAR(P43), MONTH(P43), 1), F$2:F$1000, "<=" & EOMONTH(P43, 0)) -> 0
E44: 5 | G44: 45640 | H44: 1000 | I44: 38.5 | J44: =SUM(H44:I44) -> 1038.5 | K44: PAID | M44: / | N44: 12 | P44: 47058 | Q44: =SUMIFS(J$2:J$1000, F$2:F$1000, ">=" & DATE(YEAR(P44), MONTH(P44), 1), F$2:F$1000, "<=" & EOMONTH(P44, 0)) -> 0
E45: 4 | G45: 45640 | H45: 1000 | I45: 48.12 | J45: =SUM(H45:I45) -> 1048.12 | K45: PAID | L45: LATE | M45: / | N45: 15 | P45: 47088 | Q45: =SUMIFS(J$2:J$1000, F$2:F$1000, ">=" & DATE(YEAR(P45), MONTH(P45), 1), F$2:F$1000, "<=" & EOMONTH(P45, 0)) -> 0
E46: 4 | G46: 45643 | H46: 2000 | I46: 120 | J46: =SUM(H46:I46) -> 2120 | K46: PAID | M46: / | N46: 18 | P46: 47119 | Q46: =SUMIFS(J$2:J$1000, F$2:F$1000, ">=" & DATE(YEAR(P46), MONTH(P46), 1), F$2:F$1000, "<=" & EOMONTH(P46, 0)) -> 0
E47: 4 | G47: 45643 | H47: 2000 | I47: 100 | J47: =SUM(H47:I47) -> 2100 | K47: PAID | M47: / | N47: 15 | P47: 47150 | Q47: =SUMIFS(J$2:J$1000, F$2:F$1000, ">=" & DATE(YEAR(P47), MONTH(P47), 1), F$2:F$1000, "<=" & EOMONTH(P47, 0)) -> 0
E48: 3 | G48: 45645 | H48: 1000 | I48: 51.78 | J48: =SUM(H48:I48) -> 1051.78 | K48: PAID | M48: / | N48: 21 | P48: 47178 | Q48: =SUMIFS(J$2:J$1000, F$2:F$1000, ">=" & DATE(YEAR(P48), MONTH(P48), 1), F$2:F$1000, "<=" & EOMONTH(P48, 0)) -> 0
E49: 4 | G49: 45649 | H49: 2000 | I49: 80 | J49: =SUM(H49:I49) -> 2080 | K49: PAID | M49: / | N49: 12 | P49: 47209 | Q49: =SUMIFS(J$2:J$1000, F$2:F$1000, ">=" & DATE(YEAR(P49), MONTH(P49), 1), F$2:F$1000, "<=" & EOMONTH(P49, 0)) -> 0
E50: 4 | G50: 45649 | H50: 2000 | I50: 80 | J50: =SUM(H50:I50) -> 2080 | K50: PAID | L50: LATE | M50: / | N50: 12 | P50: 47239 | Q50: =SUMIFS(J$2:J$1000, F$2:F$1000, ">=" & DATE(YEAR(P50), MONTH(P50), 1), F$2:F$1000, "<=" & EOMONTH(P50, 0)) -> 0
E51: 4 | G51: 45653 | H51: 2000 | I51: 61.6 | J51: =SUM(H51:I51) -> 2061.6 | K51: PAID | M51: / | N51: 12 | P51: 47270 | Q51: =SUMIFS(J$2:J$1000, F$2:F$1000, ">=" & DATE(YEAR(P51), MONTH(P51), 1), F$2:F$1000, "<=" & EOMONTH(P51, 0)) -> 0
E52: 6 | G52: 45655 | H52: 1000 | I52: 53.9 | J52: =SUM(H52:I52) -> 1053.9 | K52: PAID | M52: / | N52: 14 | P52: 47300 | Q52: =SUMIFS(J$2:J$1000, F$2:F$1000, ">=" & DATE(YEAR(P52), MONTH(P52), 1), F$2:F$1000, "<=" & EOMONTH(P52, 0)) -> 0
E53: 6 | G53: 45660 | H53: 2000 | I53: 115.5 | J53: =SUM(H53:I53) -> 2115.5 | K53: PAID | M53: / | N53: 15 | P53: 47331 | Q53: =SUMIFS(J$2:J$1000, F$2:F$1000, ">=" & DATE(YEAR(P53), MONTH(P53), 1), F$2:F$1000, "<=" & EOMONTH(P53, 0)) -> 0
E54: 6 | G54: 45667 | H54: 1000 | I54: 57.75 | J54: =SUM(H54:I54) -> 1057.75 | K54: PAID | M54: / | N54: 15 | P54: 47362 | Q54: =SUMIFS(J$2:J$1000, F$2:F$1000, ">=" & DATE(YEAR(P54), MONTH(P54), 1), F$2:F$1000, "<=" & EOMONTH(P54, 0)) -> 0
E55: 5 | G55: 45668 | H55: 2000 | I55: 109.09 | J55: =SUM(H55:I55) -> 2109.09 | K55: PAID | M55: / | N55: 17 | P55: 47392 | Q55: =SUMIFS(J$2:J$1000, F$2:F$1000, ">=" & DATE(YEAR(P55), MONTH(P55), 1), F$2:F$1000, "<=" & EOMONTH(P55, 0)) -> 0
E56: 5 | G56: 45673 | H56: 4000 | I56: 233.33 | J56: =SUM(H56:I56) -> 4233.33 | K56: PAID | M56: / | N56: 14 | P56: 47423 | Q56: =SUMIFS(J$2:J$1000, F$2:F$1000, ">=" & DATE(YEAR(P56), MONTH(P56), 1), F$2:F$1000, "<=" & EOMONTH(P56, 0)) -> 0
E57: 2 | G57: 45676 | H57: 1000 | I57: 24.39 | J57: =SUM(H57:I57) -> 1024.39 | K57: PAID | M57: / | N57: 19 | P57: 47453 | Q57: =SUMIFS(J$2:J$1000, F$2:F$1000, ">=" & DATE(YEAR(P57), MONTH(P57), 1), F$2:F$1000, "<=" & EOMONTH(P57, 0)) -> 0
E58: 4 | G58: 45679 | H58: 2000 | I58: 100 | J58: =SUM(H58:I58) -> 2100 | K58: PAID | M58: / | N58: 12 | P58: 47484 | Q58: =SUMIFS(J$2:J$1000, F$2:F$1000, ">=" & DATE(YEAR(P58), MONTH(P58), 1), F$2:F$1000, "<=" & EOMONTH(P58, 0)) -> 0
E59: 2 | G59: 45682 | H59: 10000 | I59: 192.5 | J59: =SUM(H59:I59) -> 10192.5 | K59: PAID | M59: / | N59: 15 | P59: 47515 | Q59: =SUMIFS(J$2:J$1000, F$2:F$1000, ">=" & DATE(YEAR(P59), MONTH(P59), 1), F$2:F$1000, "<=" & EOMONTH(P59, 0)) -> 0
E60: 2 | G60: 45682 | H60: 12000 | I60: 277.2 | J60: =SUM(H60:I60) -> 12277.2 | K60: PAID | M60: / | N60: 18 | P60: 47543 | Q60: =SUMIFS(J$2:J$1000, F$2:F$1000, ">=" & DATE(YEAR(P60), MONTH(P60), 1), F$2:F$1000, "<=" & EOMONTH(P60, 0)) -> 0
E61: 4 | G61: 45683 | H61: 5000 | I61: 240.63 | J61: =SUM(H61:I61) -> 5240.63 | K61: PAID | M61: / | N61: 15 | P61: 47574 | Q61: =SUMIFS(J$2:J$1000, F$2:F$1000, ">=" & DATE(YEAR(P61), MONTH(P61), 1), F$2:F$1000, "<=" & EOMONTH(P61, 0)) -> 0
E62: 4 | G62: 45683 | H62: 5000 | I62: 288.75 | J62: =SUM(H62:I62) -> 5288.75 | K62: PAID | M62: / | N62: 18 | P62: 47604 | Q62: =SUMIFS(J$2:J$1000, F$2:F$1000, ">=" & DATE(YEAR(P62), MONTH(P62), 1), F$2:F$1000, "<=" & EOMONTH(P62, 0)) -> 0
... E68: 6 | G68: 45696 | H68: 2000 | I68: 115.5 | J68: =SUM(H68:I68) -> 2115.5 | K68: PAID | M68: / | N68: 15 | P68: 47788 | Q68: =SUMIFS(J$2:J$1000, F$2:F$1000, ">=" & DATE(YEAR(P68), MONTH(P68), 1), F$2:F$1000, "<=" & EOMONTH(P68, 0)) -> 0
E69: 2 | G69: 45697 | H69: 10000 | I69: 192.5 | J69: =SUM(H69:I69) -> 10192.5 | K69: PAID | M69: / | N69: 15
E70: 2 | G70: 45704 | H70: 4000 | I70: 92.4 | J70: =SUM(H70:I70) -> 4092.4 | K70: PAID | M70: / | N70: 18
E71: 6 | G71: 45709 | H71: 1000 | I71: 80 | J71: =SUM(H71:I71) -> 1080 | K71: PAID | M71: / | N71: 16
E72: 3 | G72: 45736 | H72: 5000 | I72: 235.66 | J72: =SUM(H72:I72) -> 5235.66 | K72: PAID | M72: / | N72: 21
E73: 3 | G73: 45738 | H73: 5000 | I73: 134.75 | J73: =SUM(H73:I73) -> 5134.75 | K73: PAID | M73: / | N73: 14
E74: 4 | G74: 45747 | H74: 2000 | I74: 123.9 | J74: =SUM(H74:I74) -> 2123.9 | K74: PAID | M74: / | N74: 21
E75: 4 | G75: 45756 | H75: 1000 | I75: 53.9 | J75: =SUM(H75:I75) -> 1053.9 | K75: PAID | M75: / | N75: 21
E76: 6 | F76: 45584 | H76: 1000 | I76: 57.75 | J76: =SUM(H76:I76) -> 1057.75 | K76: =IF(F76<=TODAY(),"Check!","Waiting") -> Check! | L76: DEF | M76: / | N76: 15
E77: 5 | F77: 45588 | H77: 1000 | I77: 57.75 | J77: =SUM(H77:I77) -> 1057.75 | K77: =IF(F77<=TODAY(),"Check!","Waiting") -> Check! | L77: DEF | M77: / | N77: 18
E78: 6 | F78: 45614 | H78: 1000 | I78: 69.3 | J78: =SUM(H78:I78) -> 1069.3 | K78: =IF(F78<=TODAY(),"Check!","Waiting") -> Check! | L78: DEF | M78: / | N78: 18
E79: 6 | F79: 45622 | H79: 1000 | I79: 69.3 | J79: =SUM(H79:I79) -> 1069.3 | K79: =IF(F79<=TODAY(),"Check!","Waiting") -> Check! | L79: DEF | M79: / | N79: 18
E80: 6 | G80: 45960 | H80: 1000 | I80: 61.6 | J80: =SUM(H80:I80) -> 1061.6 | K80: PAID | L80: DEF 9.5m | M80: / | N80: 16
E81: 6 | F81: 45678 | H81: 1000 | I81: 69.3 | J81: =SUM(H81:I81) -> 1069.3 | K81: =IF(F81<=TODAY(),"Check!","Waiting") -> Check! | L81: DEF | M81: / | N81: 18
E82: 5 | F82: 45679 | H82: 2000 | I82: 100 | J82: =SUM(H82:I82) -> 2100 | K82: =IF(F82<=TODAY(),"Check!","Waiting") -> Check! | L82: DEF | M82: / | N82: 12
E83: 5 | F83: 45682 | H83: 4000 | I83: 192.5 | J83: =SUM(H83:I83) -> 4192.5 | K83: =IF(F83<=TODAY(),"Check!","Waiting") -> Check! | L83: DEF | M83: / | N83: 15
E84: 5 | F84: 45685 | H84: 2000 | I84: 134.75 | J84: =SUM(H84:I84) -> 2134.75 | K84: =IF(F84<=TODAY(),"Check!","Waiting") -> Check! | L84: DEF | M84: / | N84: 21
E85: 2 | F85: 45703 | H85: 2000 | I85: 51.34 | J85: =SUM(H85:I85) -> 2051.34 | K85: =IF(F85<=TODAY(),"Check!","Waiting") -> Check! | L85: DEF | M85: / | N85: 20
E86: 3 | F86: 45715 | H86: 10000 | I86: 442.5 | J86: =SUM(H86:I86) -> 10442.5 | K86: =IF(F86<=TODAY(),"Check!","Waiting") -> Check! | L86: DEF | M86: / | N86: 20
E87: 4 | G87: 45909 | H87: 5000 | I87: 295 | J87: =SUM(H87:I87) -> 5295 | K87: PAID | L87: DEF 5m | M87: / | N87: 20
E88: 6 | F88: 45825 | H88: 1000 | I88: 77 | J88: =SUM(H88:I88) -> 1077 | K88: =IF(F88<=TODAY(),"Check!","Waiting") -> Check! | L88: DEF | M88: / | N88: 20

Sheet SAFQA
A1: قيمة المحفظة | C1: الكاش | E1: المدة | F1: تاريخ الأستحقاق | G1: تاريخ السداد | H1: القيمة الأسمية | I1: صافي الربح | J1: الدفعة | K1: الحالة | L1: C | M1: أسم الصك | N1: النسبة السنوية | P1: الشهر | Q1: التدفقات | R1: CHECKLIST
A2: =SUMIFS(J2:J300,F2:F300,"<>")+B19+A19+C2 -> 62379.69 | C2: 0 | E2: 17 | F2: 46312 | H2: 20000 | I2: 4086 | J2: =SUM(H2:I2) -> 24086 | K2: =IF(F2<=TODAY(),"Check!","Waiting") -> Waiting | M2: العجلان ريزدنت | N2: 14.42 | P2: 45778 | Q2: =SUMIFS(J$2:J$1000, F$2:F$1000, ">=" & DATE(YEAR(P2), MONTH(P2), 1), F$2:F$1000, "<=" & EOMONTH(P2, 0)) -> 0
E3: 19 | F3: 46474 | H3: 10000 | I3: 2076.13 | J3: =SUM(H3:I3) -> 12076.13 | K3: =IF(F3<=TODAY(),"Check!","Waiting") -> Waiting | M3: سيتي قيت | N3: 14.26 | P3: 45809 | Q3: =SUMIFS(J$2:J$1000, F$2:F$1000, ">=" & DATE(YEAR(P3), MONTH(P3), 1), F$2:F$1000, "<=" & EOMONTH(P3, 0)) -> 0 | R3: بداية الأستثمار
A4: الملاحظات | E4: 26 | F4: 46735 | H4: 20000 | I4: 6217.56 | J4: =SUM(H4:I4) -> 26217.56 | K4: =IF(F4<=TODAY(),"Check!","Waiting") -> Waiting | M4: بارك ليفينق | N4: 15.5 | P4: 45839 | Q4: =SUMIFS(J$2:J$1000, F$2:F$1000, ">=" & DATE(YEAR(P4), MONTH(P4), 1), F$2:F$1000, "<=" & EOMONTH(P4, 0)) -> 0 | R4: اضف معلومات الاستثمار
P5: 45870 | Q5: =SUMIFS(J$2:J$1000, F$2:F$1000, ">=" & DATE(YEAR(P5), MONTH(P5), 1), F$2:F$1000, "<=" & EOMONTH(P5, 0)) -> 0 | R5: اخصم المبلغ من الكاش
P6: 45901 | Q6: =SUMIFS(J$2:J$1000, F$2:F$1000, ">=" & DATE(YEAR(P6), MONTH(P6), 1), F$2:F$1000, "<=" & EOMONTH(P6, 0)) -> 0 | R6: انسخة كاملة السطر الى ALL
A7: التعثرات 0 | P7: 45931 | Q7: =SUMIFS(J$2:J$1000, F$2:F$1000, ">=" & DATE(YEAR(P7), MONTH(P7), 1), F$2:F$1000, "<=" & EOMONTH(P7, 0)) -> 0 | R7: تحقق من التدفقات
P8: 45962 | Q8: =SUMIFS(J$2:J$1000, F$2:F$1000, ">=" & DATE(YEAR(P8), MONTH(P8), 1), F$2:F$1000, "<=" & EOMONTH(P8, 0)) -> 0
P9: 45992 | Q9: =SUMIFS(J$2:J$1000, F$2:F$1000, ">=" & DATE(YEAR(P9), MONTH(P9), 1), F$2:F$1000, "<=" & EOMONTH(P9, 0)) -> 0
P10: 46023 | Q10: =SUMIFS(J$2:J$1000, F$2:F$1000, ">=" & DATE(YEAR(P10), MONTH(P10), 1), F$2:F$1000, "<=" & EOMONTH(P10, 0)) -> 0 | R10: نهاية الأستثمار
P11: 46054 | Q11: =SUMIFS(J$2:J$1000, F$2:F$1000, ">=" & DATE(YEAR(P11), MONTH(P11), 1), F$2:F$1000, "<=" & EOMONTH(P11, 0)) -> 0 | R11: PAID
P12: 46082 | Q12: =SUMIFS(J$2:J$1000, F$2:F$1000, ">=" & DATE(YEAR(P12), MONTH(P12), 1), F$2:F$1000, "<=" & EOMONTH(P12, 0)) -> 0 | R12: غير مكان تاريخ الاستحقاق الى تاريخ السداد
P13: 46113 | Q13: =SUMIFS(J$2:J$1000, F$2:F$1000, ">=" & DATE(YEAR(P13), MONTH(P13), 1), F$2:F$1000, "<=" & EOMONTH(P13, 0)) -> 0 | R13: غير صافي الربح
P14: 46143 | Q14: =SUMIFS(J$2:J$1000, F$2:F$1000, ">=" & DATE(YEAR(P14), MONTH(P14), 1), F$2:F$1000, "<=" & EOMONTH(P14, 0)) -> 0 | R14: اكتب / EARLY OR LATE OR DEF
P15: 46174 | Q15: =SUMIFS(J$2:J$1000, F$2:F$1000, ">=" & DATE(YEAR(P15), MONTH(P15), 1), F$2:F$1000, "<=" & EOMONTH(P15, 0)) -> 0 | R15: اضف مبلغ الدفعة الى الكاش
P16: 46204 | Q16: =SUMIFS(J$2:J$1000, F$2:F$1000, ">=" & DATE(YEAR(P16), MONTH(P16), 1), F$2:F$1000, "<=" & EOMONTH(P16, 0)) -> 0 | R16: انسخ كامل السطر الى ALL
A17: تم التأكد من جميع الأرقام | P17: 46235 | Q17: =SUMIFS(J$2:J$1000, F$2:F$1000, ">=" & DATE(YEAR(P17), MONTH(P17), 1), F$2:F$1000, "<=" & EOMONTH(P17, 0)) -> 0
P18: 46266 | Q18: =SUMIFS(J$2:J$1000, F$2:F$1000, ">=" & DATE(YEAR(P18), MONTH(P18), 1), F$2:F$1000, "<=" & EOMONTH(P18, 0)) -> 0
A19: 0 | B19: 0 | C19: تصحيح الفواصل | P19: 46296 | Q19: =SUMIFS(J$2:J$1000, F$2:F$1000, ">=" & DATE(YEAR(P19), MONTH(P19), 1), F$2:F$1000, "<=" & EOMONTH(P19, 0)) -> 24086
P20: 46327 | Q20: =SUMIFS(J$2:J$1000, F$2:F$1000, ">=" & DATE(YEAR(P20), MONTH(P20), 1), F$2:F$1000, "<=" & EOMONTH(P20, 0)) -> 0
A21: المأشرات | P21: 46357 | Q21: =SUMIFS(J$2:J$1000, F$2:F$1000, ">=" & DATE(YEAR(P21), MONTH(P21), 1), F$2:F$1000, "<=" & EOMONTH(P21, 0)) -> 0
A22: القيمة الأسمية | B22: صافي الأرباح | C22: عدد الأستثمارات | P22: 46388 | Q22: =SUMIFS(J$2:J$1000, F$2:F$1000, ">=" & DATE(YEAR(P22), MONTH(P22), 1), F$2:F$1000, "<=" & EOMONTH(P22, 0)) -> 0
A23: =SUMIFS(H2:H167,F2:F167,"<>") -> 50000 | B23: =SUMIFS(I2:I167,F2:F167,"<>") -> 12379.69 | C23: =COUNT(N2:N300, "?*") -> 3 | P23: 46419 | Q23: =SUMIFS(J$2:J$1000, F$2:F$1000, ">=" & DATE(YEAR(P23), MONTH(P23), 1), F$2:F$1000, "<=" & EOMONTH(P23, 0)) -> 0
A24: العائد السنوي ( APR ) | B24: العائد على الاستثمار ( ROI ) | C24: متوسط المدة ( بالشهر ) | P24: 46447 | Q24: =SUMIFS(J$2:J$1000, F$2:F$1000, ">=" & DATE(YEAR(P24), MONTH(P24), 1), F$2:F$1000, "<=" & EOMONTH(P24, 0)) -> 12076.13
A25: =AVERAGE(N2:N500) -> 14.726667 | B25: =TEXT(B23/A23, "0.00%") -> 24.76% | C25: =SUMPRODUCT(H2:H500, E2:E500) / SUM(H2:H500) -> 21 | P25: 46478 | Q25: =SUMIFS(J$2:J$1000, F$2:F$1000, ">=" & DATE(YEAR(P25), MONTH(P25), 1), F$2:F$1000, "<=" & EOMONTH(P25, 0)) -> 0
A26: الفرص المتأخرة | B26: الفرص النشطة | C26: الفرص المكتملة | P26: 46508 | Q26: =SUMIFS(J$2:J$1000, F$2:F$1000, ">=" & DATE(YEAR(P26), MONTH(P26), 1), F$2:F$1000, "<=" & EOMONTH(P26, 0)) -> 0
A27: =COUNTIF(K2:K300, "CHECK!") -> 0 | B27: =COUNTIF(K2:K300, "WAITING") -> 3 | C27: =COUNTIF(K2:K300, "Paid") -> 0 | P27: 46539 | Q27: =SUMIFS(J$2:J$1000, F$2:F$1000, ">=" & DATE(YEAR(P27), MONTH(P27), 1), F$2:F$1000, "<=" & EOMONTH(P27, 0)) -> 0
P28: 46569 | Q28: =SUMIFS(J$2:J$1000, F$2:F$1000, ">=" & DATE(YEAR(P28), MONTH(P28), 1), F$2:F$1000, "<=" & EOMONTH(P28, 0)) -> 0
P29: 46600 | Q29: =SUMIFS(J$2:J$1000, F$2:F$1000, ">=" & DATE(YEAR(P29), MONTH(P29), 1), F$2:F$1000, "<=" & EOMONTH(P29, 0)) -> 0
A30: القيمة الأسمية المدفوعة | B30: صافي الأرباح المدفوع | C30: المجموع | P30: 46631 | Q30: =SUMIFS(J$2:J$1000, F$2:F$1000, ">=" & DATE(YEAR(P30), MONTH(P30), 1), F$2:F$1000, "<=" & EOMONTH(P30, 0)) -> 0
A31: =SUMIFS(H2:H167,G2:G167,"<>") -> 0 | B31: =SUMIFS(I2:I167,G2:G167,"<>") -> 0 | C31: =A31+B31 -> 0 | P31: 46661 | Q31: =SUMIFS(J$2:J$1000, F$2:F$1000, ">=" & DATE(YEAR(P31), MONTH(P31), 1), F$2:F$1000, "<=" & EOMONTH(P31, 0)) -> 0
A32: المجموع | P32: 46692 | Q32: =SUMIFS(J$2:J$1000, F$2:F$1000, ">=" & DATE(YEAR(P32), MONTH(P32), 1), F$2:F$1000, "<=" & EOMONTH(P32, 0)) -> 0
A33: HOW TO USE: | P33: 46722 | Q33: =SUMIFS(J$2:J$1000, F$2:F$1000, ">=" & DATE(YEAR(P33), MONTH(P33), 1), F$2:F$1000, "<=" & EOMONTH(P33, 0)) -> 26217.56
A34: In the Due culum, when the date come it will change to red | P34: 46753 | Q34: =SUMIFS(J$2:J$1000, F$2:F$1000, ">=" & DATE(YEAR(P34), MONTH(P34), 1), F$2:F$1000, "<=" & EOMONTH(P34, 0)) -> 0
A35: if its Paid, then type the Paiment date = this will compute the profits | P35: 46784 | Q35: =SUMIFS(J$2:J$1000, F$2:F$1000, ">=" & DATE(YEAR(P35), MONTH(P35), 1), F$2:F$1000, "<=" & EOMONTH(P35, 0)) -> 0
A36: automatically in the portfolio value | P36: 46813 | Q36: =SUMIFS(J$2:J$1000, F$2:F$1000, ">=" & DATE(YEAR(P36), MONTH(P36), 1), F$2:F$1000, "<=" & EOMONTH(P36, 0)) -> 0
A37: then type (Paid) to change to green | P37: 46844 | Q37: =SUMIFS(J$2:J$1000, F$2:F$1000, ">=" & DATE(YEAR(P37), MONTH(P37), 1), F$2:F$1000, "<=" & EOMONTH(P37, 0)) -> 0
P38: 46874 | Q38: =SUMIFS(J$2:J$1000, F$2:F$1000, ">=" & DATE(YEAR(P38), MONTH(P38), 1), F$2:F$1000, "<=" & EOMONTH(P38, 0)) -> 0
A39: Note | P39: 46905 | Q39: =SUMIFS(J$2:J$1000, F$2:F$1000, ">=" & DATE(YEAR(P39), MONTH(P39), 1), F$2:F$1000, "<=" & EOMONTH(P39, 0)) -> 0
A40: Cash sum and subtract until cell 300. update if needed | P40: 46935 | Q40: =SUMIFS(J$2:J$1000, F$2:F$1000, ">=" & DATE(YEAR(P40), MONTH(P40), 1), F$2:F$1000, "<=" & EOMONTH(P40, 0)) -> 0
A41: المجموع | P41: 46966 | Q41: =SUMIFS(J$2:J$1000, F$2:F$1000, ">=" & DATE(YEAR(P41), MONTH(P41), 1), F$2:F$1000, "<=" & EOMONTH(P41, 0)) -> 0
A42: المجموع | P42: 46997 | Q42: =SUMIFS(J$2:J$1000, F$2:F$1000, ">=" & DATE(YEAR(P42), MONTH(P42), 1), F$2:F$1000, "<=" & EOMONTH(P42, 0)) -> 0
P43: 47027 | Q43: =SUMIFS(J$2:J$1000, F$2:F$1000, ">=" & DATE(YEAR(P43), MONTH(P43), 1), F$2:F$1000, "<=" & EOMONTH(P43, 0)) -> 0
P44: 47058 | Q44: =SUMIFS(J$2:J$1000, F$2:F$1000, ">=" & DATE(YEAR(P44), MONTH(P44), 1), F$2:F$1000, "<=" & EOMONTH(P44, 0)) -> 0
P45: 47088 | Q45: =SUMIFS(J$2:J$1000, F$2:F$1000, ">=" & DATE(YEAR(P45), MONTH(P45), 1), F$2:F$1000, "<=" & EOMONTH(P45, 0)) -> 0
P46: 47119 | Q46: =SUMIFS(J$2:J$1000, F$2:F$1000, ">=" & DATE(YEAR(P46), MONTH(P46), 1), F$2:F$1000, "<=" & EOMONTH(P46, 0)) -> 0
P47: 47150 | Q47: =SUMIFS(J$2:J$1000, F$2:F$1000, ">=" & DATE(YEAR(P47), MONTH(P47), 1), F$2:F$1000, "<=" & EOMONTH(P47, 0)) -> 0
P48: 47178 | Q48: =SUMIFS(J$2:J$1000, F$2:F$1000, ">=" & DATE(YEAR(P48), MONTH(P48), 1), F$2:F$1000, "<=" & EOMONTH(P48, 0)) -> 0
P49: 47209 | Q49: =SUMIFS(J$2:J$1000, F$2:F$1000, ">=" & DATE(YEAR(P49), MONTH(P49), 1), F$2:F$1000, "<=" & EOMONTH(P49, 0)) -> 0
P50: 47239 | Q50: =SUMIFS(J$2:J$1000, F$2:F$1000, ">=" & DATE(YEAR(P50), MONTH(P50), 1), F$2:F$1000, "<=" & EOMONTH(P50, 0)) -> 0
P51: 47270 | Q51: =SUMIFS(J$2:J$1000, F$2:F$1000, ">=" & DATE(YEAR(P51), MONTH(P51), 1), F$2:F$1000, "<=" & EOMONTH(P51, 0)) -> 0
P52: 47300 | Q52: =SUMIFS(J$2:J$1000, F$2:F$1000, ">=" & DATE(YEAR(P52), MONTH(P52), 1), F$2:F$1000, "<=" & EOMONTH(P52, 0)) -> 0
P53: 47331 | Q53: =SUMIFS(J$2:J$1000, F$2:F$1000, ">=" & DATE(YEAR(P53), MONTH(P53), 1), F$2:F$1000, "<=" & EOMONTH(P53, 0)) -> 0
P54: 47362 | Q54: =SUMIFS(J$2:J$1000, F$2:F$1000, ">=" & DATE(YEAR(P54), MONTH(P54), 1), F$2:F$1000, "<=" & EOMONTH(P54, 0)) -> 0
... P68: 47788 | Q68: =SUMIFS(J$2:J$1000, F$2:F$1000, ">=" & DATE(YEAR(P68), MONTH(P68), 1), F$2:F$1000, "<=" & EOMONTH(P68, 0)) -> 0

Sheet TARMEEZ
A1: قيمة المحفظة | C1: الكاش | E1: المدة | F1: تاريخ الأستحقاق | G1: تاريخ السداد | H1: القيمة الأسمية | I1: صافي الربح | J1: الدفعة | K1: الحالة | L1: C | M1: أسم الصك | N1: النسبة السنوية | P1: الشهر | Q1: التدفقات | R1: CHECKLIST
A2: =SUMIFS(J2:J300,F2:F300,"<>")+B19+A19+C2 -> 0 | C2: 0 | P2: 45778 | Q2: =SUMIFS(J$2:J$1000, F$2:F$1000, ">=" & DATE(YEAR(P2), MONTH(P2), 1), F$2:F$1000, "<=" & EOMONTH(P2, 0)) -> 0
P3: 45809 | Q3: =SUMIFS(J$2:J$1000, F$2:F$1000, ">=" & DATE(YEAR(P3), MONTH(P3), 1), F$2:F$1000, "<=" & EOMONTH(P3, 0)) -> 0 | R3: بداية الأستثمار
A4: الملاحظات | P4: 45839 | Q4: =SUMIFS(J$2:J$1000, F$2:F$1000, ">=" & DATE(YEAR(P4), MONTH(P4), 1), F$2:F$1000, "<=" & EOMONTH(P4, 0)) -> 0 | R4: اضف معلومات الاستثمار
P5: 45870 | Q5: =SUMIFS(J$2:J$1000, F$2:F$1000, ">=" & DATE(YEAR(P5), MONTH(P5), 1), F$2:F$1000, "<=" & EOMONTH(P5, 0)) -> 0 | R5: اخصم المبلغ من الكاش
P6: 45901 | Q6: =SUMIFS(J$2:J$1000, F$2:F$1000, ">=" & DATE(YEAR(P6), MONTH(P6), 1), F$2:F$1000, "<=" & EOMONTH(P6, 0)) -> 0 | R6: انسخة كاملة السطر الى ALL
A7: لا يوجد أي تعثر | P7: 45931 | Q7: =SUMIFS(J$2:J$1000, F$2:F$1000, ">=" & DATE(YEAR(P7), MONTH(P7), 1), F$2:F$1000, "<=" & EOMONTH(P7, 0)) -> 0 | R7: تحقق من التدفقات
P8: 45962 | Q8: =SUMIFS(J$2:J$1000, F$2:F$1000, ">=" & DATE(YEAR(P8), MONTH(P8), 1), F$2:F$1000, "<=" & EOMONTH(P8, 0)) -> 0
P9: 45992 | Q9: =SUMIFS(J$2:J$1000, F$2:F$1000, ">=" & DATE(YEAR(P9), MONTH(P9), 1), F$2:F$1000, "<=" & EOMONTH(P9, 0)) -> 0
P10: 46023 | Q10: =SUMIFS(J$2:J$1000, F$2:F$1000, ">=" & DATE(YEAR(P10), MONTH(P10), 1), F$2:F$1000, "<=" & EOMONTH(P10, 0)) -> 0 | R10: نهاية الأستثمار
P11: 46054 | Q11: =SUMIFS(J$2:J$1000, F$2:F$1000, ">=" & DATE(YEAR(P11), MONTH(P11), 1), F$2:F$1000, "<=" & EOMONTH(P11, 0)) -> 0 | R11: PAID
P12: 46082 | Q12: =SUMIFS(J$2:J$1000, F$2:F$1000, ">=" & DATE(YEAR(P12), MONTH(P12), 1), F$2:F$1000, "<=" & EOMONTH(P12, 0)) -> 0 | R12: غير مكان تاريخ الاستحقاق الى تاريخ السداد
P13: 46113 | Q13: =SUMIFS(J$2:J$1000, F$2:F$1000, ">=" & DATE(YEAR(P13), MONTH(P13), 1), F$2:F$1000, "<=" & EOMONTH(P13, 0)) -> 0 | R13: غير صافي الربح
P14: 46143 | Q14: =SUMIFS(J$2:J$1000, F$2:F$1000, ">=" & DATE(YEAR(P14), MONTH(P14), 1), F$2:F$1000, "<=" & EOMONTH(P14, 0)) -> 0 | R14: اكتب / EARLY OR LATE OR DEF
P15: 46174 | Q15: =SUMIFS(J$2:J$1000, F$2:F$1000, ">=" & DATE(YEAR(P15), MONTH(P15), 1), F$2:F$1000, "<=" & EOMONTH(P15, 0)) -> 0 | R15: اضف مبلغ الدفعة الى الكاش
P16: 46204 | Q16: =SUMIFS(J$2:J$1000, F$2:F$1000, ">=" & DATE(YEAR(P16), MONTH(P16), 1), F$2:F$1000, "<=" & EOMONTH(P16, 0)) -> 0 | R16: انسخ كامل السطر الى ALL
A17: تم التأكد من جميع الأرقام | P17: 46235 | Q17: =SUMIFS(J$2:J$1000, F$2:F$1000, ">=" & DATE(YEAR(P17), MONTH(P17), 1), F$2:F$1000, "<=" & EOMONTH(P17, 0)) -> 0
P18: 46266 | Q18: =SUMIFS(J$2:J$1000, F$2:F$1000, ">=" & DATE(YEAR(P18), MONTH(P18), 1), F$2:F$1000, "<=" & EOMONTH(P18, 0)) -> 0
A19: 0 | B19: 0 | C19: تصحيح الفواصل | P19: 46296 | Q19: =SUMIFS(J$2:J$1000, F$2:F$1000, ">=" & DATE(YEAR(P19), MONTH(P19), 1), F$2:F$1000, "<=" & EOMONTH(P19, 0)) -> 0
P20: 46327 | Q20: =SUMIFS(J$2:J$1000, F$2:F$1000, ">=" & DATE(YEAR(P20), MONTH(P20), 1), F$2:F$1000, "<=" & EOMONTH(P20, 0)) -> 0
A21: المأشرات | P21: 46357 | Q21: =SUMIFS(J$2:J$1000, F$2:F$1000, ">=" & DATE(YEAR(P21), MONTH(P21), 1), F$2:F$1000, "<=" & EOMONTH(P21, 0)) -> 0
A22: القيمة الأسمية | B22: صافي الأرباح | C22: عدد الأستثمارات | P22: 46388 | Q22: =SUMIFS(J$2:J$1000, F$2:F$1000, ">=" & DATE(YEAR(P22), MONTH(P22), 1), F$2:F$1000, "<=" & EOMONTH(P22, 0)) -> 0
A23: =SUMIFS(H2:H167,F2:F167,"<>") -> 0 | B23: =SUMIFS(I2:I167,F2:F167,"<>") -> 0 | C23: =COUNT(N2:N300, "?*") -> 0 | P23: 46419 | Q23: =SUMIFS(J$2:J$1000, F$2:F$1000, ">=" & DATE(YEAR(P23), MONTH(P23), 1), F$2:F$1000, "<=" & EOMONTH(P23, 0)) -> 0
A24: العائد السنوي ( APR ) | B24: العائد على الاستثمار ( ROI ) | C24: متوسط المدة ( بالشهر ) | P24: 46447 | Q24: =SUMIFS(J$2:J$1000, F$2:F$1000, ">=" & DATE(YEAR(P24), MONTH(P24), 1), F$2:F$1000, "<=" & EOMONTH(P24, 0)) -> 0
A25: =AVERAGE(N2:N500) -> #DIV/0! | B25: =TEXT(B23/A23, "0.00%") -> #DIV/0! | C25: =SUMPRODUCT(H2:H500, E2:E500) / SUM(H2:H500) -> #DIV/0! | P25: 46478 | Q25: =SUMIFS(J$2:J$1000, F$2:F$1000, ">=" & DATE(YEAR(P25), MONTH(P25), 1), F$2:F$1000, "<=" & EOMONTH(P25, 0)) -> 0
A26: الفرص المتأخرة | B26: الفرص النشطة | C26: الفرص المكتملة | P26: 46508 | Q26: =SUMIFS(J$2:J$1000, F$2:F$1000, ">=" & DATE(YEAR(P26), MONTH(P26), 1), F$2:F$1000, "<=" & EOMONTH(P26, 0)) -> 0
A27: =COUNTIF(K2:K300, "CHECK!") -> 0 | B27: =COUNTIF(K2:K300, "WAITING") -> 0 | C27: =COUNTIF(K2:K300, "Paid") -> 0 | P27: 46539 | Q27: =SUMIFS(J$2:J$1000, F$2:F$1000, ">=" & DATE(YEAR(P27), MONTH(P27), 1), F$2:F$1000, "<=" & EOMONTH(P27, 0)) -> 0
P28: 46569 | Q28: =SUMIFS(J$2:J$1000, F$2:F$1000, ">=" & DATE(YEAR(P28), MONTH(P28), 1), F$2:F$1000, "<=" & EOMONTH(P28, 0)) -> 0
P29: 46600 | Q29: =SUMIFS(J$2:J$1000, F$2:F$1000, ">=" & DATE(YEAR(P29), MONTH(P29), 1), F$2:F$1000, "<=" & EOMONTH(P29, 0)) -> 0
A30: القيمة الأسمية المدفوعة | B30: صافي الأرباح المدفوع | C30: المجموع | P30: 46631 | Q30: =SUMIFS(J$2:J$1000, F$2:F$1000, ">=" & DATE(YEAR(P30), MONTH(P30), 1), F$2:F$1000, "<=" & EOMONTH(P30, 0)) -> 0
A31: =SUMIFS(H2:H167,G2:G167,"<>") -> 0 | B31: =SUMIFS(I2:I167,G2:G167,"<>") -> 0 | C31: =A31+B31 -> 0 | P31: 46661 | Q31: =SUMIFS(J$2:J$1000, F$2:F$1000, ">=" & DATE(YEAR(P31), MONTH(P31), 1), F$2:F$1000, "<=" & EOMONTH(P31, 0)) -> 0
A32: المجموع | P32: 46692 | Q32: =SUMIFS(J$2:J$1000, F$2:F$1000, ">=" & DATE(YEAR(P32), MONTH(P32), 1), F$2:F$1000, "<=" & EOMONTH(P32, 0)) -> 0
A33: HOW TO USE: | P33: 46722 | Q33: =SUMIFS(J$2:J$1000, F$2:F$1000, ">=" & DATE(YEAR(P33), MONTH(P33), 1), F$2:F$1000, "<=" & EOMONTH(P33, 0)) -> 0
A34: In the Due culum, when the date come it will change to red | P34: 46753 | Q34: =SUMIFS(J$2:J$1000, F$2:F$1000, ">=" & DATE(YEAR(P34), MONTH(P34), 1), F$2:F$1000, "<=" & EOMONTH(P34, 0)) -> 0
A35: if its Paid, then type the Paiment date = this will compute the profits | P35: 46784 | Q35: =SUMIFS(J$2:J$1000, F$2:F$1000, ">=" & DATE(YEAR(P35), MONTH(P35), 1), F$2:F$1000, "<=" & EOMONTH(P35, 0)) -> 0
A36: automatically in the portfolio value | P36: 46813 | Q36: =SUMIFS(J$2:J$1000, F$2:F$1000, ">=" & DATE(YEAR(P36), MONTH(P36), 1), F$2:F$1000, "<=" & EOMONTH(P36, 0)) -> 0
A37: then type (Paid) to change to green | P37: 46844 | Q37: =SUMIFS(J$2:J$1000, F$2:F$1000, ">=" & DATE(YEAR(P37), MONTH(P37), 1), F$2:F$1000, "<=" & EOMONTH(P37, 0)) -> 0
P38: 46874 | Q38: =SUMIFS(J$2:J$1000, F$2:F$1000, ">=" & DATE(YEAR(P38), MONTH(P38), 1), F$2:F$1000, "<=" & EOMONTH(P38, 0)) -> 0
A39: Note | P39: 46905 | Q39: =SUMIFS(J$2:J$1000, F$2:F$1000, ">=" & DATE(YEAR(P39), MONTH(P39), 1), F$2:F$1000, "<=" & EOMONTH(P39, 0)) -> 0
A40: Cash sum and subtract until cell 300. update if needed | P40: 46935 | Q40: =SUMIFS(J$2:J$1000, F$2:F$1000, ">=" & DATE(YEAR(P40), MONTH(P40), 1), F$2:F$1000, "<=" & EOMONTH(P40, 0)) -> 0
A41: المجموع | P41: 46966 | Q41: =SUMIFS(J$2:J$1000, F$2:F$1000, ">=" & DATE(YEAR(P41), MONTH(P41), 1), F$2:F$1000, "<=" & EOMONTH(P41, 0)) -> 0
A42: المجموع | P42: 46997 | Q42: =SUMIFS(J$2:J$1000, F$2:F$1000, ">=" & DATE(YEAR(P42), MONTH(P42), 1), F$2:F$1000, "<=" & EOMONTH(P42, 0)) -> 0
P43: 47027 | Q43: =SUMIFS(J$2:J$1000, F$2:F$1000, ">=" & DATE(YEAR(P43), MONTH(P43), 1), F$2:F$1000, "<=" & EOMONTH(P43, 0)) -> 0
P44: 47058 | Q44: =SUMIFS(J$2:J$1000, F$2:F$1000, ">=" & DATE(YEAR(P44), MONTH(P44), 1), F$2:F$1000, "<=" & EOMONTH(P44, 0)) -> 0
P45: 47088 | Q45: =SUMIFS(J$2:J$1000, F$2:F$1000, ">=" & DATE(YEAR(P45), MONTH(P45), 1), F$2:F$1000, "<=" & EOMONTH(P45, 0)) -> 0
P46: 47119 | Q46: =SUMIFS(J$2:J$1000, F$2:F$1000, ">=" & DATE(YEAR(P46), MONTH(P46), 1), F$2:F$1000, "<=" & EOMONTH(P46, 0)) -> 0
P47: 47150 | Q47: =SUMIFS(J$2:J$1000, F$2:F$1000, ">=" & DATE(YEAR(P47), MONTH(P47), 1), F$2:F$1000, "<=" & EOMONTH(P47, 0)) -> 0
P48: 47178 | Q48: =SUMIFS(J$2:J$1000, F$2:F$1000, ">=" & DATE(YEAR(P48), MONTH(P48), 1), F$2:F$1000, "<=" & EOMONTH(P48, 0)) -> 0
P49: 47209 | Q49: =SUMIFS(J$2:J$1000, F$2:F$1000, ">=" & DATE(YEAR(P49), MONTH(P49), 1), F$2:F$1000, "<=" & EOMONTH(P49, 0)) -> 0
P50: 47239 | Q50: =SUMIFS(J$2:J$1000, F$2:F$1000, ">=" & DATE(YEAR(P50), MONTH(P50), 1), F$2:F$1000, "<=" & EOMONTH(P50, 0)) -> 0
P51: 47270 | Q51: =SUMIFS(J$2:J$1000, F$2:F$1000, ">=" & DATE(YEAR(P51), MONTH(P51), 1), F$2:F$1000, "<=" & EOMONTH(P51, 0)) -> 0
P52: 47300 | Q52: =SUMIFS(J$2:J$1000, F$2:F$1000, ">=" & DATE(YEAR(P52), MONTH(P52), 1), F$2:F$1000, "<=" & EOMONTH(P52, 0)) -> 0
P53: 47331 | Q53: =SUMIFS(J$2:J$1000, F$2:F$1000, ">=" & DATE(YEAR(P53), MONTH(P53), 1), F$2:F$1000, "<=" & EOMONTH(P53, 0)) -> 0
P54: 47362 | Q54: =SUMIFS(J$2:J$1000, F$2:F$1000, ">=" & DATE(YEAR(P54), MONTH(P54), 1), F$2:F$1000, "<=" & EOMONTH(P54, 0)) -> 0
... P68: 47788 | Q68: =SUMIFS(J$2:J$1000, F$2:F$1000, ">=" & DATE(YEAR(P68), MONTH(P68), 1), F$2:F$1000, "<=" & EOMONTH(P68, 0)) -> 0

Sheet TAMEED
A1: قيمة المحفظة | C1: الكاش | E1: المدة | F1: تاريخ الأستحقاق | G1: تاريخ السداد | H1: القيمة الأسمية | I1: صافي الربح | J1: الدفعة | K1: الحالة | L1: C | M1: أسم الصك | N1: النسبة السنوية | P1: الشهر | Q1: التدفقات | R1: CHECKLIST
A2: =SUMIFS(J2:J300,F2:F300,"<>")+B19+A19+C2 -> 1067.2 | C2: 0 | E2: 3 | G2: 45516 | H2: 2000 | I2: 64.8 | J2: =SUM(H2:I2) -> 2064.8 | K2: PAID | M2: / | N2: 12.96 | P2: 45778 | Q2: =SUMIFS(J$2:J$1000, F$2:F$1000, ">=" & DATE(YEAR(P2), MONTH(P2), 1), F$2:F$1000, "<=" & EOMONTH(P2, 0)) -> 0
E3: 4 | G3: 45577 | H3: 1000 | I3: 48 | J3: =SUM(H3:I3) -> 1048 | K3: PAID | M3: / | N3: 14.4 | P3: 45809 | Q3: =SUMIFS(J$2:J$1000, F$2:F$1000, ">=" & DATE(YEAR(P3), MONTH(P3), 1), F$2:F$1000, "<=" & EOMONTH(P3, 0)) -> 0 | R3: بداية الأستثمار
A4: الملاحظات | E4: 6 | G4: 45603 | H4: 1000 | I4: 64.8 | J4: =SUM(H4:I4) -> 1064.8 | K4: PAID | M4: / | N4: 12.96 | P4: 45839 | Q4: =SUMIFS(J$2:J$1000, F$2:F$1000, ">=" & DATE(YEAR(P4), MONTH(P4), 1), F$2:F$1000, "<=" & EOMONTH(P4, 0)) -> 0 | R4: اضف معلومات الاستثمار
A5: مطلوب : التأكد من جميع التأخيرات | E5: 3 | G5: 45604 | H5: 1000 | I5: 32.4 | J5: =SUM(H5:I5) -> 1032.4 | K5: PAID | M5: / | N5: 12.96 | P5: 45870 | Q5: =SUMIFS(J$2:J$1000, F$2:F$1000, ">=" & DATE(YEAR(P5), MONTH(P5), 1), F$2:F$1000, "<=" & EOMONTH(P5, 0)) -> 0 | R5: اخصم المبلغ من الكاش
A6: مطلوب : التأكد من جميع السداد المبكر | E6: 6 | G6: 45612 | H6: 2000 | I6: 115.2 | J6: =SUM(H6:I6) -> 2115.2 | K6: PAID | M6: / | N6: 11.52 | P6: 45901 | Q6: =SUMIFS(J$2:J$1000, F$2:F$1000, ">=" & DATE(YEAR(P6), MONTH(P6), 1), F$2:F$1000, "<=" & EOMONTH(P6, 0)) -> 0 | R6: انسخة كاملة السطر الى ALL
E7: 4 | G7: 45613 | H7: 1000 | I7: 43.2 | J7: =SUM(H7:I7) -> 1043.2 | K7: PAID | M7: / | N7: 12.96 | P7: 45931 | Q7: =SUMIFS(J$2:J$1000, F$2:F$1000, ">=" & DATE(YEAR(P7), MONTH(P7), 1), F$2:F$1000, "<=" & EOMONTH(P7, 0)) -> 0 | R7: تحقق من التدفقات
A8: تأخر نسبي في الفرص | E8: 4 | G8: 45613 | H8: 1000 | I8: 43.2 | J8: =SUM(H8:I8) -> 1043.2 | K8: PAID | M8: / | N8: 12.96 | P8: 45962 | Q8: =SUMIFS(J$2:J$1000, F$2:F$1000, ">=" & DATE(YEAR(P8), MONTH(P8), 1), F$2:F$1000, "<=" & EOMONTH(P8, 0)) -> 0
A9: التطبيق سيء | E9: 6 | G9: 45615 | H9: 1000 | I9: 69.6 | J9: =SUM(H9:I9) -> 1069.6 | K9: PAID | M9: / | N9: 13.92 | P9: 45992 | Q9: =SUMIFS(J$2:J$1000, F$2:F$1000, ">=" & DATE(YEAR(P9), MONTH(P9), 1), F$2:F$1000, "<=" & EOMONTH(P9, 0)) -> 0
A10: المستثمر الالي يكرر الفرص | E10: 6 | G10: 45615 | H10: 2000 | I10: 139.2 | J10: =SUM(H10:I10) -> 2139.2 | K10: PAID | M10: / | N10: 13.92 | P10: 46023 | Q10: =SUMIFS(J$2:J$1000, F$2:F$1000, ">=" & DATE(YEAR(P10), MONTH(P10), 1), F$2:F$1000, "<=" & EOMONTH(P10, 0)) -> 0 | R10: نهاية الأستثمار
A11: صعوبة الأستثمار اليدوي | E11: 6 | G11: 45624 | H11: 2000 | I11: 115.2 | J11: =SUM(H11:I11) -> 2115.2 | K11: PAID | M11: / | N11: 11.52 | P11: 46054 | Q11: =SUMIFS(J$2:J$1000, F$2:F$1000, ">=" & DATE(YEAR(P11), MONTH(P11), 1), F$2:F$1000, "<=" & EOMONTH(P11, 0)) -> 0 | R11: PAID
E12: 4 | G12: 45624 | H12: 1000 | I12: 40 | J12: =SUM(H12:I12) -> 1040 | K12: PAID | M12: / | N12: 12 | P12: 46082 | Q12: =SUMIFS(J$2:J$1000, F$2:F$1000, ">=" & DATE(YEAR(P12), MONTH(P12), 1), F$2:F$1000, "<=" & EOMONTH(P12, 0)) -> 0 | R12: غير مكان تاريخ الاستحقاق الى تاريخ السداد
A13: القيمة الاسمية و صافي الربح صحيحة | E13: 4 | G13: 45624 | H13: 1000 | I13: 49.6 | J13: =SUM(H13:I13) -> 1049.6 | K13: PAID | M13: / | N13: 14.88 | P13: 46113 | Q13: =SUMIFS(J$2:J$1000, F$2:F$1000, ">=" & DATE(YEAR(P13), MONTH(P13), 1), F$2:F$1000, "<=" & EOMONTH(P13, 0)) -> 0 | R13: غير صافي الربح
A14: ولاكن صافي الأرباح المدفوعة مكتوب بالبرنامج مدفوع 3518.93 | E14: 4 | G14: 45624 | H14: 1000 | I14: 43.2 | J14: =SUM(H14:I14) -> 1043.2 | K14: PAID | M14: / | N14: 12.96 | P14: 46143 | Q14: =SUMIFS(J$2:J$1000, F$2:F$1000, ">=" & DATE(YEAR(P14), MONTH(P14), 1), F$2:F$1000, "<=" & EOMONTH(P14, 0)) -> 0 | R14: اكتب / EARLY OR LATE OR DEF
A15: وعند جمع الأرباح يديويا = 3544.04 يعني الفرق 25.11 | E15: 6 | G15: 45625 | H15: 2000 | I15: 115.2 | J15: =SUM(H15:I15) -> 2115.2 | K15: PAID | M15: / | N15: 11.52 | P15: 46174 | Q15: =SUMIFS(J$2:J$1000, F$2:F$1000, ">=" & DATE(YEAR(P15), MONTH(P15), 1), F$2:F$1000, "<=" & EOMONTH(P15, 0)) -> 0 | R15: اضف مبلغ الدفعة الى الكاش
A16: 0 | B16: 0 | C16: تصحيح الفواصل | E16: 6 | G16: 2024-1130 | H16: 1000 | I16: 74.4 | J16: =SUM(H16:I16) -> 1074.4 | K16: PAID | M16: / | N16: 14.88 | P16: 46204 | Q16: =SUMIFS(J$2:J$1000, F$2:F$1000, ">=" & DATE(YEAR(P16), MONTH(P16), 1), F$2:F$1000, "<=" & EOMONTH(P16, 0)) -> 0 | R16: انسخ كامل السطر الى ALL
E17: 6 | G17: 45628 | H17: 2000 | I17: 120 | J17: =SUM(H17:I17) -> 2120 | K17: PAID | M17: / | N17: 12 | P17: 46235 | Q17: =SUMIFS(J$2:J$1000, F$2:F$1000, ">=" & DATE(YEAR(P17), MONTH(P17), 1), F$2:F$1000, "<=" & EOMONTH(P17, 0)) -> 0
E18: 6 | G18: 45628 | H18: 1000 | I18: 74.4 | J18: =SUM(H18:I18) -> 1074.4 | K18: PAID | M18: / | N18: 14.88 | P18: 46266 | Q18: =SUMIFS(J$2:J$1000, F$2:F$1000, ">=" & DATE(YEAR(P18), MONTH(P18), 1), F$2:F$1000, "<=" & EOMONTH(P18, 0)) -> 0
E19: 6 | G19: 45630 | H19: 1000 | I19: 74.4 | J19: =SUM(H19:I19) -> 1074.4 | K19: PAID | M19: / | N19: 14.88 | P19: 46296 | Q19: =SUMIFS(J$2:J$1000, F$2:F$1000, ">=" & DATE(YEAR(P19), MONTH(P19), 1), F$2:F$1000, "<=" & EOMONTH(P19, 0)) -> 0
E20: 4 | G20: 45633 | H20: 1000 | I20: 48 | J20: =SUM(H20:I20) -> 1048 | K20: PAID | M20: / | N20: 14.4 | P20: 46327 | Q20: =SUMIFS(J$2:J$1000, F$2:F$1000, ">=" & DATE(YEAR(P20), MONTH(P20), 1), F$2:F$1000, "<=" & EOMONTH(P20, 0)) -> 0
A21: المأشرات | E21: 6 | G21: 45635 | H21: 1000 | I21: 72 | J21: =SUM(H21:I21) -> 1072 | K21: PAID | M21: / | N21: 14.4 | P21: 46357 | Q21: =SUMIFS(J$2:J$1000, F$2:F$1000, ">=" & DATE(YEAR(P21), MONTH(P21), 1), F$2:F$1000, "<=" & EOMONTH(P21, 0)) -> 0
A22: القيمة الأسمية | B22: صافي الأرباح | C22: عدد الأستثمارات | E22: 6 | G22: 45636 | H22: 2000 | I22: 124.8 | J22: =SUM(H22:I22) -> 2124.8 | K22: PAID | M22: / | N22: 12.48 | P22: 46388 | Q22: =SUMIFS(J$2:J$1000, F$2:F$1000, ">=" & DATE(YEAR(P22), MONTH(P22), 1), F$2:F$1000, "<=" & EOMONTH(P22, 0)) -> 0
A23: =SUMIFS(H2:H500,F2:F500,"<>") -> 1000 | B23: =SUMIFS(I2:I300,F2:F300,"<>") -> 67.2 | C23: =COUNT(N2:N500, "?*") -> 51 | E23: 6 | G23: 45638 | H23: 2000 | I23: 124.8 | J23: =SUM(H23:I23) -> 2124.8 | K23: PAID | M23: / | N23: 12.48 | P23: 46419 | Q23: =SUMIFS(J$2:J$1000, F$2:F$1000, ">=" & DATE(YEAR(P23), MONTH(P23), 1), F$2:F$1000, "<=" & EOMONTH(P23, 0)) -> 0
A24: العائد السنوي الفعلي | B24: العائد على الاستثمار | C24: متوسط المدة النشط | E24: 6 | G24: 45639 | H24: 2000 | I24: 124.8 | J24: =SUM(H24:I24) -> 2124.8 | K24: PAID | M24: / | N24: 12.48 | P24: 46447 | Q24: =SUMIFS(J$2:J$1000, F$2:F$1000, ">=" & DATE(YEAR(P24), MONTH(P24), 1), F$2:F$1000, "<=" & EOMONTH(P24, 0)) -> 0
A25: =(B25*100/C25)*12 -> 13.44 | B25: =TEXT(B23/A23, "0.00%") -> 6.72% | C25: {=SUMPRODUCT((F2:F500<>"")*H2:H500*E2:E500)/SUMPRODUCT((F2:F500<>"")*H2:H500)} -> 6 | E25: 6 | G25: 45639 | H25: 1000 | I25: 67.2 | J25: =SUM(H25:I25) -> 1067.2 | K25: PAID | M25: / | N25: 13.44 | P25: 46478 | Q25: =SUMIFS(J$2:J$1000, F$2:F$1000, ">=" & DATE(YEAR(P25), MONTH(P25), 1), F$2:F$1000, "<=" & EOMONTH(P25, 0)) -> 0
A26: الفرص المتأخرة | B26: الفرص النشطة | C26: الفرص المكتملة | E26: 5 | G26: 45642 | H26: 1000 | I26: 58 | J26: =SUM(H26:I26) -> 1058 | K26: PAID | M26: / | N26: 13.92 | P26: 46508 | Q26: =SUMIFS(J$2:J$1000, F$2:F$1000, ">=" & DATE(YEAR(P26), MONTH(P26), 1), F$2:F$1000, "<=" & EOMONTH(P26, 0)) -> 0
A27: =COUNTIF(K2:K500, "CHECK!") -> 1 | B27: =COUNTIF(K2:K500, "WAITING") -> 0 | C27: =COUNTIF(K2:K500, "Paid") -> 50 | E27: 5 | G27: 45642 | H27: 1000 | I27: 58 | J27: =SUM(H27:I27) -> 1058 | K27: PAID | M27: / | N27: 13.92 | P27: 46539 | Q27: =SUMIFS(J$2:J$1000, F$2:F$1000, ">=" & DATE(YEAR(P27), MONTH(P27), 1), F$2:F$1000, "<=" & EOMONTH(P27, 0)) -> 0
A28: العائد السنوي البسيط | C28: متوسط المدة الكامل | E28: 7 | G28: 45659 | H28: 2000 | I28: 128.8 | J28: =SUM(H28:I28) -> 2128.8 | K28: PAID | M28: / | N28: 11.4 | P28: 46569 | Q28: =SUMIFS(J$2:J$1000, F$2:F$1000, ">=" & DATE(YEAR(P28), MONTH(P28), 1), F$2:F$1000, "<=" & EOMONTH(P28, 0)) -> 0
A29: =AVERAGE(N2:N500) -> 13.397647 | C29: =SUMPRODUCT(H2:H500, E2:E500) / SUM(H2:H500) -> 6.6526468 | E29: 6 | G29: 45664 | H29: 1950 | I29: 107.64 | J29: =SUM(H29:I29) -> 2057.64 | K29: PAID | M29: / | N29: 11.4 | P29: 46600 | Q29: =SUMIFS(J$2:J$1000, F$2:F$1000, ">=" & DATE(YEAR(P29), MONTH(P29), 1), F$2:F$1000, "<=" & EOMONTH(P29, 0)) -> 0
A30: القيمة الأسمية المدفوعة | B30: صافي الأرباح المدفوع | C30: المجموع | E30: 6 | G30: 45664 | H30: 1000 | I30: 81.6 | J30: =SUM(H30:I30) -> 1081.6 | K30: PAID | M30: / | N30: 16.32 | P30: 46631 | Q30: =SUMIFS(J$2:J$1000, F$2:F$1000, ">=" & DATE(YEAR(P30), MONTH(P30), 1), F$2:F$1000, "<=" & EOMONTH(P30, 0)) -> 0
A31: =SUMIFS(H10:H308,E10:E308,"<>") -> 58950 | B31: =SUMIFS(I10:I308,F10:F308,"<>") -> 67.2 | C31: =SUMIFS(J10:J308,G10:G308,"<>") -> 62417.64 | E31: 6 | G31: 45665 | H31: 2000 | I31: 124.8 | J31: =SUM(H31:I31) -> 2124.8 | K31: PAID | M31: / | N31: 12.48 | P31: 46661 | Q31: =SUMIFS(J$2:J$1000, F$2:F$1000, ">=" & DATE(YEAR(P31), MONTH(P31), 1), F$2:F$1000, "<=" & EOMONTH(P31, 0)) -> 0
A32: المجموع | E32: 6 | G32: 45666 | H32: 1000 | I32: 81.6 | J32: =SUM(H32:I32) -> 1081.6 | K32: PAID | M32: / | N32: 16.32 | P32: 46692 | Q32: =SUMIFS(J$2:J$1000, F$2:F$1000, ">=" & DATE(YEAR(P32), MONTH(P32), 1), F$2:F$1000, "<=" & EOMONTH(P32, 0)) -> 0
A33: HOW TO USE: | E33: 6 | G33: 45674 | H33: 1000 | I33: 69.6 | J33: =SUM(H33:I33) -> 1069.6 | K33: PAID | M33: / | N33: 13.92 | P33: 46722 | Q33: =SUMIFS(J$2:J$1000, F$2:F$1000, ">=" & DATE(YEAR(P33), MONTH(P33), 1), F$2:F$1000, "<=" & EOMONTH(P33, 0)) -> 0
A34: In the Due culum, when the date come it will change to red | E34: 6 | G34: 45674 | H34: 1000 | I34: 69.6 | J34: =SUM(H34:I34) -> 1069.6 | K34: PAID | M34: / | N34: 13.92 | P34: 46753 | Q34: =SUMIFS(J$2:J$1000, F$2:F$1000, ">=" & DATE(YEAR(P34), MONTH(P34), 1), F$2:F$1000, "<=" & EOMONTH(P34, 0)) -> 0
A35: if its Paid, then type the Paiment date = this will compute the profits | E35: 6 | G35: 45678 | H35: 1000 | I35: 62.4 | J35: =SUM(H35:I35) -> 1062.4 | K35: PAID | M35: / | N35: 12.48 | P35: 46784 | Q35: =SUMIFS(J$2:J$1000, F$2:F$1000, ">=" & DATE(YEAR(P35), MONTH(P35), 1), F$2:F$1000, "<=" & EOMONTH(P35, 0)) -> 0
A36: automatically in the portfolio value | E36: 6 | G36: 45678 | H36: 1000 | I36: 62.4 | J36: =SUM(H36:I36) -> 1062.4 | K36: PAID | M36: / | N36: 12.48 | P36: 46813 | Q36: =SUMIFS(J$2:J$1000, F$2:F$1000, ">=" & DATE(YEAR(P36), MONTH(P36), 1), F$2:F$1000, "<=" & EOMONTH(P36, 0)) -> 0
A37: then type (Paid) to change to green | E37: 6 | G37: 45678 | H37: 1000 | I37: 62.4 | J37: =SUM(H37:I37) -> 1062.4 | K37: PAID | M37: / | N37: 12.48 | P37: 46844 | Q37: =SUMIFS(J$2:J$1000, F$2:F$1000, ">=" & DATE(YEAR(P37), MONTH(P37), 1), F$2:F$1000, "<=" & EOMONTH(P37, 0)) -> 0
E38: 6 | G38: 45680 | H38: 1000 | I38: 62.4 | J38: =SUM(H38:I38) -> 1062.4 | K38: PAID | M38: / | N38: 12.48 | P38: 46874 | Q38: =SUMIFS(J$2:J$1000, F$2:F$1000, ">=" & DATE(YEAR(P38), MONTH(P38), 1), F$2:F$1000, "<=" & EOMONTH(P38, 0)) -> 0
A39: Note | E39: 6 | G39: 45681 | H39: 1000 | I39: 62.4 | J39: =SUM(H39:I39) -> 1062.4 | K39: PAID | M39: / | N39: 12.48 | P39: 46905 | Q39: =SUMIFS(J$2:J$1000, F$2:F$1000, ">=" & DATE(YEAR(P39), MONTH(P39), 1), F$2:F$1000, "<=" & EOMONTH(P39, 0)) -> 0
A40: Cash sum and subtract until cell 300. update if needed | E40: 6 | G40: 45682 | H40: 1000 | I40: 74.4 | J40: =SUM(H40:I40) -> 1074.4 | K40: PAID | M40: / | N40: 14.88 | P40: 46935 | Q40: =SUMIFS(J$2:J$1000, F$2:F$1000, ">=" & DATE(YEAR(P40), MONTH(P40), 1), F$2:F$1000, "<=" & EOMONTH(P40, 0)) -> 0
A41: المجموع | E41: 6 | G41: 45682 | H41: 1000 | I41: 74.4 | J41: =SUM(H41:I41) -> 1074.4 | K41: PAID | M41: / | N41: 14.88 | P41: 46966 | Q41: =SUMIFS(J$2:J$1000, F$2:F$1000, ">=" & DATE(YEAR(P41), MONTH(P41), 1), F$2:F$1000, "<=" & EOMONTH(P41, 0)) -> 0
E42: 6 | G42: 45682 | H42: 1000 | I42: 62.4 | J42: =SUM(H42:I42) -> 1062.4 | K42: PAID | M42: / | N42: 12.48 | P42: 46997 | Q42: =SUMIFS(J$2:J$1000, F$2:F$1000, ">=" & DATE(YEAR(P42), MONTH(P42), 1), F$2:F$1000, "<=" & EOMONTH(P42, 0)) -> 0
E43: 6 | G43: 45685 | H43: 1000 | I43: 74.4 | J43: =SUM(H43:I43) -> 1074.4 | K43: PAID | M43: / | N43: 14.88 | P43: 47027 | Q43: =SUMIFS(J$2:J$1000, F$2:F$1000, ">=" & DATE(YEAR(P43), MONTH(P43), 1), F$2:F$1000, "<=" & EOMONTH(P43, 0)) -> 0
E44: 6 | G44: 45686 | H44: 1000 | I44: 69.6 | J44: =SUM(H44:I44) -> 1069.6 | K44: PAID | M44: / | N44: 13.92 | P44: 47058 | Q44: =SUMIFS(J$2:J$1000, F$2:F$1000, ">=" & DATE(YEAR(P44), MONTH(P44), 1), F$2:F$1000, "<=" & EOMONTH(P44, 0)) -> 0
E45: 9 | G45: 20225-2-16 | H45: 2000 | I45: 208.8 | J45: =SUM(H45:I45) -> 2208.8 | K45: PAID | M45: / | N45: 13.92 | P45: 47088 | Q45: =SUMIFS(J$2:J$1000, F$2:F$1000, ">=" & DATE(YEAR(P45), MONTH(P45), 1), F$2:F$1000, "<=" & EOMONTH(P45, 0)) -> 0
E46: 6 | F46: 45681 | H46: 1000 | I46: 67.2 | J46: =SUM(H46:I46) -> 1067.2 | K46: =IF(F46<=TODAY(),"Check!","Waiting") -> Check! | L46: DEFF | M46: / | N46: 13.44 | P46: 47119 | Q46: =SUMIFS(J$2:J$1000, F$2:F$1000, ">=" & DATE(YEAR(P46), MONTH(P46), 1), F$2:F$1000, "<=" & EOMONTH(P46, 0)) -> 0
E47: 8 | G47: 45811 | H47: 1000 | I47: 108.8 | J47: =SUM(H47:I47) -> 1108.8 | K47: PAID | L47: DEF | M47: / | N47: 16.32 | P47: 47150 | Q47: =SUMIFS(J$2:J$1000, F$2:F$1000, ">=" & DATE(YEAR(P47), MONTH(P47), 1), F$2:F$1000, "<=" & EOMONTH(P47, 0)) -> 0
E48: 12 | G48: 45840 | H48: 2000 | I48: 259.2 | J48: =SUM(H48:I48) -> 2259.2 | K48: PAID | L48: EARLY | M48: / | N48: 12.96 | P48: 47178 | Q48: =SUMIFS(J$2:J$1000, F$2:F$1000, ">=" & DATE(YEAR(P48), MONTH(P48), 1), F$2:F$1000, "<=" & EOMONTH(P48, 0)) -> 0
E49: 12 | G49: 45846 | H49: 2000 | I49: 259.2 | J49: =SUM(H49:I49) -> 2259.2 | K49: PAID | L49: EARLY | M49: / | N49: 12.96 | P49: 47209 | Q49: =SUMIFS(J$2:J$1000, F$2:F$1000, ">=" & DATE(YEAR(P49), MONTH(P49), 1), F$2:F$1000, "<=" & EOMONTH(P49, 0)) -> 0
E50: 12 | G50: 45846 | H50: 2000 | I50: 259.2 | J50: =SUM(H50:I50) -> 2259.2 | K50: PAID | L50: EARLY | M50: / | N50: 12.96 | P50: 47239 | Q50: =SUMIFS(J$2:J$1000, F$2:F$1000, ">=" & DATE(YEAR(P50), MONTH(P50), 1), F$2:F$1000, "<=" & EOMONTH(P50, 0)) -> 0
E51: 12 | G51: 45846 | H51: 2000 | I51: 259.2 | J51: =SUM(H51:I51) -> 2259.2 | K51: PAID | L51: EARLY | M51: / | N51: 12.96 | P51: 47270 | Q51: =SUMIFS(J$2:J$1000, F$2:F$1000, ">=" & DATE(YEAR(P51), MONTH(P51), 1), F$2:F$1000, "<=" & EOMONTH(P51, 0)) -> 0
E52: 12 | G52: 45846 | H52: 2000 | I52: 259.2 | J52: =SUM(H52:I52) -> 2259.2 | K52: PAID | L52: EARLY | M52: / | N52: 12.96 | P52: 47300 | Q52: =SUMIFS(J$2:J$1000, F$2:F$1000, ">=" & DATE(YEAR(P52), MONTH(P52), 1), F$2:F$1000, "<=" & EOMONTH(P52, 0)) -> 0
P53: 47331 | Q53: =SUMIFS(J$2:J$1000, F$2:F$1000, ">=" & DATE(YEAR(P53), MONTH(P53), 1), F$2:F$1000, "<=" & EOMONTH(P53, 0)) -> 0
P54: 47362 | Q54: =SUMIFS(J$2:J$1000, F$2:F$1000, ">=" & DATE(YEAR(P54), MONTH(P54), 1), F$2:F$1000, "<=" & EOMONTH(P54, 0)) -> 0
A55: المأشرات | P55: 47392 | Q55: =SUMIFS(J$2:J$1000, F$2:F$1000, ">=" & DATE(YEAR(P55), MONTH(P55), 1), F$2:F$1000, "<=" & EOMONTH(P55, 0)) -> 0
A56: القيمة الأسمية | B56: صافي الأرباح | C56: عدد الأستثمارات | P56: 47423 | Q56: =SUMIFS(J$2:J$1000, F$2:F$1000, ">=" & DATE(YEAR(P56), MONTH(P56), 1), F$2:F$1000, "<=" & EOMONTH(P56, 0)) -> 0
A57: =SUMIFS(H36:H534,F36:F534,"<>") -> 1000 | B57: =SUMIFS(I36:I334,F36:F334,"<>") -> 67.2 | C57: =COUNT(N36:N534, "?*") -> 17 | P57: 47453 | Q57: =SUMIFS(J$2:J$1000, F$2:F$1000, ">=" & DATE(YEAR(P57), MONTH(P57), 1), F$2:F$1000, "<=" & EOMONTH(P57, 0)) -> 0
A58: العائد السنوي الفعلي | B58: العائد السنوي البسيط | C58: الفرص المكتملة | P58: 47484 | Q58: =SUMIFS(J$2:J$1000, F$2:F$1000, ">=" & DATE(YEAR(P58), MONTH(P58), 1), F$2:F$1000, "<=" & EOMONTH(P58, 0)) -> 0
A59: =(A61*100/B63)*12 -> 13.44 | B59: =AVERAGE(N2:N508) -> 13.397647 | C59: =COUNTIF(K34:K532, "Paid") -> 18 | P59: 47515 | Q59: =SUMIFS(J$2:J$1000, F$2:F$1000, ">=" & DATE(YEAR(P59), MONTH(P59), 1), F$2:F$1000, "<=" & EOMONTH(P59, 0)) -> 0
A60: العائد على الاستثمار | C60: الفرص النشطة | P60: 47543 | Q60: =SUMIFS(J$2:J$1000, F$2:F$1000, ">=" & DATE(YEAR(P60), MONTH(P60), 1), F$2:F$1000, "<=" & EOMONTH(P60, 0)) -> 0
A61: =TEXT(B57/A57, "0.00%") -> 6.72% | C61: =COUNTIF(L36:L534, "WAITING") -> 0 | P61: 47574 | Q61: =SUMIFS(J$2:J$1000, F$2:F$1000, ">=" & DATE(YEAR(P61), MONTH(P61), 1), F$2:F$1000, "<=" & EOMONTH(P61, 0)) -> 0
A62: متوسط المدة الكامل | B62: متوسط المدة النشط | C62: الفرص المتأخرة | P62: 47604 | Q62: =SUMIFS(J$2:J$1000, F$2:F$1000, ">=" & DATE(YEAR(P62), MONTH(P62), 1), F$2:F$1000, "<=" & EOMONTH(P62, 0)) -> 0
A63: =SUMPRODUCT(F36:F534, C36:C534) / SUM(F36:F534) -> 0 | B63: {=SUMPRODUCT((F2:F500<>"")*H2:H500*E2:E500)/SUMPRODUCT((F2:F500<>"")*H2:H500)} -> 6 | C63: =COUNTIF(M38:M536, "CHECK!") -> 0 | P63: 47635 | Q63: =SUMIFS(J$2:J$1000, F$2:F$1000, ">=" & DATE(YEAR(P63), MONTH(P63), 1), F$2:F$1000, "<=" & EOMONTH(P63, 0)) -> 0
A64: القيمة الأسمية المدفوعة | B64: صافي الأرباح المدفوع | C64: المبالغ المتأخرة | P64: 47665 | Q64: =SUMIFS(J$2:J$1000, F$2:F$1000, ">=" & DATE(YEAR(P64), MONTH(P64), 1), F$2:F$1000, "<=" & EOMONTH(P64, 0)) -> 0
A65: =SUMIFS(H44:H342,E44:E342,"<>") -> 15000 | B65: =SUMIFS(I44:I342,F44:F342,"<>") -> 67.2 | C65: =SUM(J2:J500) -> 73966.04 | P65: 47696 | Q65: =SUMIFS(J$2:J$1000, F$2:F$1000, ">=" & DATE(YEAR(P65), MONTH(P65), 1), F$2:F$1000, "<=" & EOMONTH(P65, 0)) -> 0
P66: 47727 | Q66: =SUMIFS(J$2:J$1000, F$2:F$1000, ">=" & DATE(YEAR(P66), MONTH(P66), 1), F$2:F$1000, "<=" & EOMONTH(P66, 0)) -> 0
P67: 47757 | Q67: =SUMIFS(J$2:J$1000, F$2:F$1000, ">=" & DATE(YEAR(P67), MONTH(P67), 1), F$2:F$1000, "<=" & EOMONTH(P67, 0)) -> 0
P68: 47788 | Q68: =SUMIFS(J$2:J$1000, F$2:F$1000, ">=" & DATE(YEAR(P68), MONTH(P68), 1), F$2:F$1000, "<=" & EOMONTH(P68, 0)) -> 0
